Workbook

Sheet 信息汇总
A1: 总添加人数 | B1: 有效 leads 人数/占比 | C1: 转化人数/占比 | D1: 填写问卷人数/占比 | E1: 领卡人数/占比 | F1: 进群人数/占比 | G1: 交作业人数/占比 | H1: 流失人数/占比 | J1: 未回复人数/占比 | K1: 挖需人数/占比 | L1: SA 类人数/占比 | M1: 建联人数/占比 | N1: 破冰人数/占比 | O1: 挖需人数/占比 | P1: 痛点人数/占比 | Q1: 匹配产品人数/占比 | R1: 异议解决人数/占比 | S1: 关单人数/占比 | T1: S 类人数/占比 | U1: A 类人数/占比 | V1: B 类人数/占比 | W1: 不跟进人数/占比 | X1: 在期会员人数/占比 | Y1: 骗子人数/占比 | Z1: 重复添加人数 | AA1: 往期会员人数/占比 | AB1: 领过体验卡人数/占比 | AC1: 待领取体验卡人数/占比 | AD1: 延期人数/占比
A2: {=SUMPRODUCT(--(LEN(A5:A1659)>0))} | B2: =A2-H2-X2-Y2-Z2 | C2: {=SUMPRODUCT(--(TRIM(H5:H1659)="已成交"))} | D2: {=SUMPRODUCT(--(LEN(X5:X1659)>0))} | E2: {=SUMPRODUCT(--(LEN(E5:E1659)>0))} | F2: {=SUMPRODUCT(--(LEN(F5:F1659)>0))} | G2: {=SUMPRODUCT(--(LEN(O5:O1659)>0))} | H2: {=SUMPRODUCT(--(TRIM(D5:D1659)="已流失"))} | J2: {=SUMPRODUCT(--(TRIM(H5:H1659)="建联"))} | K2: =O2 | L2: =T2+U2 | M2: {=SUMPRODUCT(--(TRIM(H5:H1659)="建联"))} | N2: {=SUMPRODUCT(--(TRIM(H5:H1659)="破冰"))} | O2: {=SUMPRODUCT(--(TRIM(H5:H1659)="需求"))} | P2: {=SUMPRODUCT(--(TRIM(H5:H1659)="痛点"))} | Q2: {=SUMPRODUCT(--(TRIM(H5:H1659)="匹配产品"))} | R2: {=SUMPRODUCT(--(TRIM(H5:H1659)="异议解决"))} | S2: {=SUMPRODUCT(--(TRIM(H5:H1659)="关单"))} | T2: {=SUMPRODUCT(--(TRIM(G5:G1659)="S"))} | U2: {=SUMPRODUCT(--(TRIM(G5:G1659)="A"))} | V2: {=SUMPRODUCT(--(TRIM(G5:G1659)="B"))} | W2: {=SUMPRODUCT(--(TRIM(G5:G1659)="不跟进"))} | X2: {=SUMPRODUCT(--(TRIM(U5:U1659)="会员_7"))} | Y2: {=SUMPRODUCT(--(TRIM(G5:G1659)="诈骗"))} | Z2: =COUNTIF(B5:B1659, "*重复*") | AA2: {=SUMPRODUCT(--(TRIM(U5:U1659)="会员_往期未续费"))} | AB2: {=SUMPRODUCT(--(TRIM(U5:U1659)="体验卡"))} | AC2: =B2-AA2-AB2 | AD2: {=SUMPRODUCT(--(TRIM(G5:G1659)="延期"))}
B3: =B2/A2 | C3: =C2/B2 | D3: =D2/B2 | E3: =E2/B2 | F3: =F2/B2 | G3: =G2/B2 | H3: =H2/A2 | J3: =J2/A2 | K3: =K2/B2+P3+Q3+R3+S3 | L3: =L2/B2 | M3: =M2/A2 | N3: =N2/B2+O3+P3+Q3+R3+S3 | O3: =O2/B2+P3+Q3+R3+S3 | P3: =P2/B2+Q3+R3+S3 | Q3: =Q2/B2+R3+S3 | R3: =R2/B2+S3 | S3: =S2/B2 | T3: =T2/B2 | U3: =U2/B2 | V3: =V2/A2 | W3: =W2/B2 | X3: =X2/A2 | Y3: =Y2/A2 | Z3: =Z2/A2 | AA3: =AA2/A2 | AB3: =AB2/A2 | AC3: =AC2/B2 | AD3: =AD2/B2
B4: 企微备注名 | C4: 所在账号 | D4: 是否流失 | E4: 是否领卡 | F4: 是否进群 | G4: 用户属性 | H4: 用户阶段 | J4: 用户备注 | K4: 用户基本信息 | L4: 第一课在线时长 | M4: 第一课回放时长 | N4: 第二课在线时长 | O4: 直播听后感 | P4: 作业 1 | Q4: 作业 2 | R4: 作业 3 | S4: 企业标签 | T4: 性别 | U4: 往期身份 | V4: 收货地址 | W4: 收件人 | X4: 您所在的城市为 | Y4: 您现在的工作是 | Z4: 您的工作年限是 | AA4: 工作或项目年收入 | AB4: 您目前所处的赚钱阶段 | AC4: 之前是否有做过项目的经历（如果有，可以简单说一下自己做过的项目~） | AD4: 从那些渠道了解的生财 | AE4: 请问来生财有术，主要是想解决赚钱路上那些方面的问题？我把相关资料发给你 | AF4: 是否进群 | AG4: IP 课 | AH4: 小报童 | AI4: 365问 | AJ4: 礼品卡 | AK4: 返差价 | AL4: 兑换话术 | AM4: 差价话术 | AN4: 星球编号 | AO4: 交付结束
A5: =IF('微伴数据'!A2="","",'微伴数据'!A2) | B5: =IF('微伴数据'!B2="","",'微伴数据'!B2) | C5: =IF('微伴数据'!G2="","",'微伴数据'!G2) | D5: =IF('微伴数据'!D2="","",'微伴数据'!D2) | E5: =IF('微伴数据'!CR2="","",'微伴数据'!CR2) | F5: =IF('微伴数据'!CL2="","",'微伴数据'!CL2) | G5: S | H5: 已成交 | I5: =VLOOKUP(A5,'Sheet9'!A:A,1,0) | K5: =T5&CHAR(10)&U5&CHAR(10)&V5&CHAR(10)&Y5&CHAR(10)&Z5&CHAR(10)&AA5&CHAR(10)&AB5&CHAR(10)&AC5&CHAR(10)&AD5&CHAR(10)&AE5 | L5: =IFERROR(VLOOKUP(#REF!,'第一课直播'!D:L,9,0),IFERROR(VLOOKUP('第一课回放'!C:H,5,0),"未到课")) | M5: =IFERROR(VLOOKUP(#REF!,'第一课回放'!C:H,5,0),"0:00:00") | N5: =IFERROR(VLOOKUP(#REF!,'第二课直播'!D:L,9,0),"未到课") | S5: =IFERROR(VLOOKUP(A5,'微伴数据'!A:DB,12,0),"") | T5: =IFERROR(VLOOKUP(A5,'微伴数据'!A:DB,32,0),"") | U5: =IFERROR(VLOOKUP(A5,'微伴数据'!A:DC,81,0),"") | V5: =IFERROR(VLOOKUP(#REF!,'星橙地址'!A:V,9,0),"") | W5: =IFERROR(VLOOKUP(#REF!,'星橙地址'!A:V,10,0),"") | X5: =IFERROR(VLOOKUP(A5,'星云问卷'!A:O,8,0),"") | Y5: =IFERROR(VLOOKUP(A5,'星云问卷'!A:O,9,0),"") | Z5: =IFERROR(VLOOKUP(A5,'星云问卷'!A:O,10,0),"") | AA5: =IFERROR(VLOOKUP(A5,'星云问卷'!A:O,11,0),"") | AB5: =IFERROR(VLOOKUP(A5,'星云问卷'!A:O,12,0),"") | AC5: =IFERROR(VLOOKUP(A5,'星云问卷'!A:O,13,0),"") | AD5: =IFERROR(VLOOKUP(A5,'星云问卷'!A:O,14,0),"") | AE5: =IFERROR(VLOOKUP(A5,'星云问卷'!A:O,15,0),"") | AF5: =IFERROR(VLOOKUP(A5,'微伴数据'!A:DB,72,0),"") | AG5: 54DCsd5b | AH5: https://xiaobot.net/invitation/ae6b3-8be22-0a6d1-870e1 | AI5: 6dvE2Dzy | AL5: =CONCATENATE( " 我把体验营用户专属福利给你发一下哈：" & CHAR(10) & CHAR(10), "1.《抖音商业IP课》" & CHAR(10), "兑换码：", AG5, CHAR(10), "兑换码使用地址：https://appamvpb5mq9834.h5.xiaoeknow.com/p/t/v1/ecommerce/mkt/redeem_index" & CHAR(10) & CHAR(10), "2.《生财有术66个项目精选》" & CHAR(10), "兑换码：", AH5, CHAR(10), "使用方式：微信搜索小报童投递-点击开始阅读-点击生财有术项目精选即可" & CHAR(10) & CHAR(10), "3.《生财365问》" & CHAR(10), "兑换码：", AI5, CHAR(10), "使用方式：https://appamvpb5mq9834.h5.xiaoeknow.com/p/t/v1/ecommerce/mkt/redeem_index")
A6: =IF('微伴数据'!A3="","",'微伴数据'!A3) | B6: =IF('微伴数据'!B3="","",'微伴数据'!B3) | C6: =IF('微伴数据'!G3="","",'微伴数据'!G3) | D6: =IF('微伴数据'!D3="","",'微伴数据'!D3) | E6: =IF('微伴数据'!CR3="","",'微伴数据'!CR3) | F6: =IF('微伴数据'!CL3="","",'微伴数据'!CL3) | G6: B | H6: 建联 | I6: =VLOOKUP(A6,'Sheet9'!A:A,1,0) | K6: =T6&CHAR(10)&U6&CHAR(10)&V6&CHAR(10)&Y6&CHAR(10)&Z6&CHAR(10)&AA6&CHAR(10)&AB6&CHAR(10)&AC6&CHAR(10)&AD6&CHAR(10)&AE6 | L6: =IFERROR(VLOOKUP(#REF!,'第一课直播'!D:L,9,0),IFERROR(VLOOKUP('第一课回放'!C:H,5,0),"未到课")) | M6: =IFERROR(VLOOKUP(#REF!,'第一课回放'!C:H,5,0),"0:00:00") | N6: =IFERROR(VLOOKUP(#REF!,'第二课直播'!D:L,9,0),"未到课") | S6: =IFERROR(VLOOKUP(A6,'微伴数据'!A:DB,12,0),"") | T6: =IFERROR(VLOOKUP(A6,'微伴数据'!A:DB,32,0),"") | U6: =IFERROR(VLOOKUP(A6,'微伴数据'!A:DC,81,0),"") | V6: =IFERROR(VLOOKUP(#REF!,'星橙地址'!A:V,9,0),"") | W6: =IFERROR(VLOOKUP(#REF!,'星橙地址'!A:V,10,0),"") | X6: =IFERROR(VLOOKUP(A6,'星云问卷'!A:O,8,0),"") | Y6: =IFERROR(VLOOKUP(A6,'星云问卷'!A:O,9,0),"") | Z6: =IFERROR(VLOOKUP(A6,'星云问卷'!A:O,10,0),"") | AA6: =IFERROR(VLOOKUP(A6,'星云问卷'!A:O,11,0),"") | AB6: =IFERROR(VLOOKUP(A6,'星云问卷'!A:O,12,0),"") | AC6: =IFERROR(VLOOKUP(A6,'星云问卷'!A:O,13,0),"") | AD6: =IFERROR(VLOOKUP(A6,'星云问卷'!A:O,14,0),"") | AE6: =IFERROR(VLOOKUP(A6,'星云问卷'!A:O,15,0),"") | AF6: =IFERROR(VLOOKUP(A6,'微伴数据'!A:DB,72,0),"") | AL6: =CONCATENATE( " 我把体验营用户专属福利给你发一下哈：" & CHAR(10) & CHAR(10), "1.《抖音商业IP课》" & CHAR(10), "兑换码：", AG6, CHAR(10), "兑换码使用地址：https://appamvpb5mq9834.h5.xiaoeknow.com/p/t/v1/ecommerce/mkt/redeem_index" & CHAR(10) & CHAR(10), "2.《生财有术66个项目精选》" & CHAR(10), "兑换码：", AH6, CHAR(10), "使用方式：微信搜索小报童投递-点击开始阅读-点击生财有术项目精选即可" & CHAR(10) & CHAR(10), "3.《生财365问》" & CHAR(10), "兑换码：", AI6, CHAR(10), "使用方式：https://appamvpb5mq9834.h5.xiaoeknow.com/p/t/v1/ecommerce/mkt/redeem_index")
A7: =IF('微伴数据'!A4="","",'微伴数据'!A4) | B7: =IF('微伴数据'!B4="","",'微伴数据'!B4) | C7: =IF('微伴数据'!G4="","",'微伴数据'!G4) | D7: =IF('微伴数据'!D4="","",'微伴数据'!D4) | E7: =IF('微伴数据'!CR4="","",'微伴数据'!CR4) | F7: =IF('微伴数据'!CL4="","",'微伴数据'!CL4) | G7: B | H7: 建联 | I7: =VLOOKUP(A7,'Sheet9'!A:A,1,0) | K7: =T7&CHAR(10)&U7&CHAR(10)&V7&CHAR(10)&Y7&CHAR(10)&Z7&CHAR(10)&AA7&CHAR(10)&AB7&CHAR(10)&AC7&CHAR(10)&AD7&CHAR(10)&AE7 | L7: =IFERROR(VLOOKUP(#REF!,'第一课直播'!D:L,9,0),IFERROR(VLOOKUP('第一课回放'!C:H,5,0),"未到课")) | M7: =IFERROR(VLOOKUP(#REF!,'第一课回放'!C:H,5,0),"0:00:00") | N7: =IFERROR(VLOOKUP(#REF!,'第二课直播'!D:L,9,0),"未到课") | S7: =IFERROR(VLOOKUP(A7,'微伴数据'!A:DB,12,0),"") | T7: =IFERROR(VLOOKUP(A7,'微伴数据'!A:DB,32,0),"") | U7: =IFERROR(VLOOKUP(A7,'微伴数据'!A:DC,81,0),"") | V7: =IFERROR(VLOOKUP(#REF!,'星橙地址'!A:V,9,0),"") | W7: =IFERROR(VLOOKUP(#REF!,'星橙地址'!A:V,10,0),"") | X7: =IFERROR(VLOOKUP(A7,'星云问卷'!A:O,8,0),"") | Y7: =IFERROR(VLOOKUP(A7,'星云问卷'!A:O,9,0),"") | Z7: =IFERROR(VLOOKUP(A7,'星云问卷'!A:O,10,0),"") | AA7: =IFERROR(VLOOKUP(A7,'星云问卷'!A:O,11,0),"") | AB7: =IFERROR(VLOOKUP(A7,'星云问卷'!A:O,12,0),"") | AC7: =IFERROR(VLOOKUP(A7,'星云问卷'!A:O,13,0),"") | AD7: =IFERROR(VLOOKUP(A7,'星云问卷'!A:O,14,0),"") | AE7: =IFERROR(VLOOKUP(A7,'星云问卷'!A:O,15,0),"") | AF7: =IFERROR(VLOOKUP(A7,'微伴数据'!A:DB,72,0),"") | AL7: =CONCATENATE( " 我把体验营用户专属福利给你发一下哈：" & CHAR(10) & CHAR(10), "1.《抖音商业IP课》" & CHAR(10), "兑换码：", AG7, CHAR(10), "兑换码使用地址：https://appamvpb5mq9834.h5.xiaoeknow.com/p/t/v1/ecommerce/mkt/redeem_index" & CHAR(10) & CHAR(10), "2.《生财有术66个项目精选》" & CHAR(10), "兑换码：", AH7, CHAR(10), "使用方式：微信搜索小报童投递-点击开始阅读-点击生财有术项目精选即可" & CHAR(10) & CHAR(10), "3.《生财365问》" & CHAR(10), "兑换码：", AI7, CHAR(10), "使用方式：https://appamvpb5mq9834.h5.xiaoeknow.com/p/t/v1/ecommerce/mkt/redeem_index")
A8: =IF('微伴数据'!A5="","",'微伴数据'!A5) | B8: =IF('微伴数据'!B5="","",'微伴数据'!B5) | C8: =IF('微伴数据'!G5="","",'微伴数据'!G5) | D8: =IF('微伴数据'!D5="","",'微伴数据'!D5) | E8: =IF('微伴数据'!CR5="","",'微伴数据'!CR5) | F8: =IF('微伴数据'!CL5="","",'微伴数据'!CL5) | G8: B | H8: 建联 | I8: =VLOOKUP(A8,'Sheet9'!A:A,1,0) | K8: =T8&CHAR(10)&U8&CHAR(10)&V8&CHAR(10)&Y8&CHAR(10)&Z8&CHAR(10)&AA8&CHAR(10)&AB8&CHAR(10)&AC8&CHAR(10)&AD8&CHAR(10)&AE8 | L8: =IFERROR(VLOOKUP(#REF!,'第一课直播'!D:L,9,0),IFERROR(VLOOKUP('第一课回放'!C:H,5,0),"未到课")) | M8: =IFERROR(VLOOKUP(#REF!,'第一课回放'!C:H,5,0),"0:00:00") | N8: =IFERROR(VLOOKUP(#REF!,'第二课直播'!D:L,9,0),"未到课") | S8: =IFERROR(VLOOKUP(A8,'微伴数据'!A:DB,12,0),"") | T8: =IFERROR(VLOOKUP(A8,'微伴数据'!A:DB,32,0),"") | U8: =IFERROR(VLOOKUP(A8,'微伴数据'!A:DC,81,0),"") | V8: =IFERROR(VLOOKUP(#REF!,'星橙地址'!A:V,9,0),"") | W8: =IFERROR(VLOOKUP(#REF!,'星橙地址'!A:V,10,0),"") | X8: =IFERROR(VLOOKUP(A8,'星云问卷'!A:O,8,0),"") | Y8: =IFERROR(VLOOKUP(A8,'星云问卷'!A:O,9,0),"") | Z8: =IFERROR(VLOOKUP(A8,'星云问卷'!A:O,10,0),"") | AA8: =IFERROR(VLOOKUP(A8,'星云问卷'!A:O,11,0),"") | AB8: =IFERROR(VLOOKUP(A8,'星云问卷'!A:O,12,0),"") | AC8: =IFERROR(VLOOKUP(A8,'星云问卷'!A:O,13,0),"") | AD8: =IFERROR(VLOOKUP(A8,'星云问卷'!A:O,14,0),"") | AE8: =IFERROR(VLOOKUP(A8,'星云问卷'!A:O,15,0),"") | AF8: =IFERROR(VLOOKUP(A8,'微伴数据'!A:DB,72,0),"") | AL8: =CONCATENATE( " 我把体验营用户专属福利给你发一下哈：" & CHAR(10) & CHAR(10), "1.《抖音商业IP课》" & CHAR(10), "兑换码：", AG8, CHAR(10), "兑换码使用地址：https://appamvpb5mq9834.h5.xiaoeknow.com/p/t/v1/ecommerce/mkt/redeem_index" & CHAR(10) & CHAR(10), "2.《生财有术66个项目精选》" & CHAR(10), "兑换码：", AH8, CHAR(10), "使用方式：微信搜索小报童投递-点击开始阅读-点击生财有术项目精选即可" & CHAR(10) & CHAR(10), "3.《生财365问》" & CHAR(10), "兑换码：", AI8, CHAR(10), "使用方式：https://appamvpb5mq9834.h5.xiaoeknow.com/p/t/v1/ecommerce/mkt/redeem_index")
A9: =IF('微伴数据'!A6="","",'微伴数据'!A6) | B9: =IF('微伴数据'!B6="","",'微伴数据'!B6) | C9: =IF('微伴数据'!G6="","",'微伴数据'!G6) | D9: =IF('微伴数据'!D6="","",'微伴数据'!D6) | E9: =IF('微伴数据'!CR6="","",'微伴数据'!CR6) | F9: =IF('微伴数据'!CL6="","",'微伴数据'!CL6) | G9: B | H9: 建联 | I9: =VLOOKUP(A9,'Sheet9'!A:A,1,0) | K9: =T9&CHAR(10)&U9&CHAR(10)&V9&CHAR(10)&Y9&CHAR(10)&Z9&CHAR(10)&AA9&CHAR(10)&AB9&CHAR(10)&AC9&CHAR(10)&AD9&CHAR(10)&AE9 | L9: =IFERROR(VLOOKUP(#REF!,'第一课直播'!D:L,9,0),IFERROR(VLOOKUP('第一课回放'!C:H,5,0),"未到课")) | M9: =IFERROR(VLOOKUP(#REF!,'第一课回放'!C:H,5,0),"0:00:00") | N9: =IFERROR(VLOOKUP(#REF!,'第二课直播'!D:L,9,0),"未到课") | S9: =IFERROR(VLOOKUP(A9,'微伴数据'!A:DB,12,0),"") | T9: =IFERROR(VLOOKUP(A9,'微伴数据'!A:DB,32,0),"") | U9: =IFERROR(VLOOKUP(A9,'微伴数据'!A:DC,81,0),"") | V9: =IFERROR(VLOOKUP(#REF!,'星橙地址'!A:V,9,0),"") | W9: =IFERROR(VLOOKUP(#REF!,'星橙地址'!A:V,10,0),"") | X9: =IFERROR(VLOOKUP(A9,'星云问卷'!A:O,8,0),"") | Y9: =IFERROR(VLOOKUP(A9,'星云问卷'!A:O,9,0),"") | Z9: =IFERROR(VLOOKUP(A9,'星云问卷'!A:O,10,0),"") | AA9: =IFERROR(VLOOKUP(A9,'星云问卷'!A:O,11,0),"") | AB9: =IFERROR(VLOOKUP(A9,'星云问卷'!A:O,12,0),"") | AC9: =IFERROR(VLOOKUP(A9,'星云问卷'!A:O,13,0),"") | AD9: =IFERROR(VLOOKUP(A9,'星云问卷'!A:O,14,0),"") | AE9: =IFERROR(VLOOKUP(A9,'星云问卷'!A:O,15,0),"") | AF9: =IFERROR(VLOOKUP(A9,'微伴数据'!A:DB,72,0),"") | AL9: =CONCATENATE( " 我把体验营用户专属福利给你发一下哈：" & CHAR(10) & CHAR(10), "1.《抖音商业IP课》" & CHAR(10), "兑换码：", AG9, CHAR(10), "兑换码使用地址：https://appamvpb5mq9834.h5.xiaoeknow.com/p/t/v1/ecommerce/mkt/redeem_index" & CHAR(10) & CHAR(10), "2.《生财有术66个项目精选》" & CHAR(10), "兑换码：", AH9, CHAR(10), "使用方式：微信搜索小报童投递-点击开始阅读-点击生财有术项目精选即可" & CHAR(10) & CHAR(10), "3.《生财365问》" & CHAR(10), "兑换码：", AI9, CHAR(10), "使用方式：https://appamvpb5mq9834.h5.xiaoeknow.com/p/t/v1/ecommerce/mkt/redeem_index")
A10: =IF('微伴数据'!A7="","",'微伴数据'!A7) | B10: =IF('微伴数据'!B7="","",'微伴数据'!B7) | C10: =IF('微伴数据'!G7="","",'微伴数据'!G7) | D10: =IF('微伴数据'!D7="","",'微伴数据'!D7) | E10: =IF('微伴数据'!CR7="","",'微伴数据'!CR7) | F10: =IF('微伴数据'!CL7="","",'微伴数据'!CL7) | G10: B | H10: 建联 | I10: =VLOOKUP(A10,'Sheet9'!A:A,1,0) | K10: =T10&CHAR(10)&U10&CHAR(10)&V10&CHAR(10)&Y10&CHAR(10)&Z10&CHAR(10)&AA10&CHAR(10)&AB10&CHAR(10)&AC10&CHAR(10)&AD10&CHAR(10)&AE10 | L10: =IFERROR(VLOOKUP(#REF!,'第一课直播'!D:L,9,0),IFERROR(VLOOKUP('第一课回放'!C:H,5,0),"未到课")) | M10: =IFERROR(VLOOKUP(#REF!,'第一课回放'!C:H,5,0),"0:00:00") | N10: =IFERROR(VLOOKUP(#REF!,'第二课直播'!D:L,9,0),"未到课") | S10: =IFERROR(VLOOKUP(A10,'微伴数据'!A:DB,12,0),"") | T10: =IFERROR(VLOOKUP(A10,'微伴数据'!A:DB,32,0),"") | U10: =IFERROR(VLOOKUP(A10,'微伴数据'!A:DC,81,0),"") | V10: =IFERROR(VLOOKUP(#REF!,'星橙地址'!A:V,9,0),"") | W10: =IFERROR(VLOOKUP(#REF!,'星橙地址'!A:V,10,0),"") | X10: =IFERROR(VLOOKUP(A10,'星云问卷'!A:O,8,0),"") | Y10: =IFERROR(VLOOKUP(A10,'星云问卷'!A:O,9,0),"") | Z10: =IFERROR(VLOOKUP(A10,'星云问卷'!A:O,10,0),"") | AA10: =IFERROR(VLOOKUP(A10,'星云问卷'!A:O,11,0),"") | AB10: =IFERROR(VLOOKUP(A10,'星云问卷'!A:O,12,0),"") | AC10: =IFERROR(VLOOKUP(A10,'星云问卷'!A:O,13,0),"") | AD10: =IFERROR(VLOOKUP(A10,'星云问卷'!A:O,14,0),"") | AE10: =IFERROR(VLOOKUP(A10,'星云问卷'!A:O,15,0),"") | AF10: =IFERROR(VLOOKUP(A10,'微伴数据'!A:DB,72,0),"") | AL10: =CONCATENATE( " 我把体验营用户专属福利给你发一下哈：" & CHAR(10) & CHAR(10), "1.《抖音商业IP课》" & CHAR(10), "兑换码：", AG10, CHAR(10), "兑换码使用地址：https://appamvpb5mq9834.h5.xiaoeknow.com/p/t/v1/ecommerce/mkt/redeem_index" & CHAR(10) & CHAR(10), "2.《生财有术66个项目精选》" & CHAR(10), "兑换码：", AH10, CHAR(10), "使用方式：微信搜索小报童投递-点击开始阅读-点击生财有术项目精选即可" & CHAR(10) & CHAR(10), "3.《生财365问》" & CHAR(10), "兑换码：", AI10, CHAR(10), "使用方式：https://appamvpb5mq9834.h5.xiaoeknow.com/p/t/v1/ecommerce/mkt/redeem_index")
A11: =IF('微伴数据'!A8="","",'微伴数据'!A8) | B11: =IF('微伴数据'!B8="","",'微伴数据'!B8) | C11: =IF('微伴数据'!G8="","",'微伴数据'!G8) | D11: =IF('微伴数据'!D8="","",'微伴数据'!D8) | E11: =IF('微伴数据'!CR8="","",'微伴数据'!CR8) | F11: =IF('微伴数据'!CL8="","",'微伴数据'!CL8) | G11: A | H11: 建联 | I11: =VLOOKUP(A11,'Sheet9'!A:A,1,0) | K11: =T11&CHAR(10)&U11&CHAR(10)&V11&CHAR(10)&Y11&CHAR(10)&Z11&CHAR(10)&AA11&CHAR(10)&AB11&CHAR(10)&AC11&CHAR(10)&AD11&CHAR(10)&AE11 | L11: =IFERROR(VLOOKUP(#REF!,'第一课直播'!D:L,9,0),IFERROR(VLOOKUP('第一课回放'!C:H,5,0),"未到课")) | M11: =IFERROR(VLOOKUP(#REF!,'第一课回放'!C:H,5,0),"0:00:00") | N11: =IFERROR(VLOOKUP(#REF!,'第二课直播'!D:L,9,0),"未到课") | S11: =IFERROR(VLOOKUP(A11,'微伴数据'!A:DB,12,0),"") | T11: =IFERROR(VLOOKUP(A11,'微伴数据'!A:DB,32,0),"") | U11: =IFERROR(VLOOKUP(A11,'微伴数据'!A:DC,81,0),"") | V11: =IFERROR(VLOOKUP(#REF!,'星橙地址'!A:V,9,0),"") | W11: =IFERROR(VLOOKUP(#REF!,'星橙地址'!A:V,10,0),"") | X11: =IFERROR(VLOOKUP(A11,'星云问卷'!A:O,8,0),"") | Y11: =IFERROR(VLOOKUP(A11,'星云问卷'!A:O,9,0),"") | Z11: =IFERROR(VLOOKUP(A11,'星云问卷'!A:O,10,0),"") | AA11: =IFERROR(VLOOKUP(A11,'星云问卷'!A:O,11,0),"") | AB11: =IFERROR(VLOOKUP(A11,'星云问卷'!A:O,12,0),"") | AC11: =IFERROR(VLOOKUP(A11,'星云问卷'!A:O,13,0),"") | AD11: =IFERROR(VLOOKUP(A11,'星云问卷'!A:O,14,0),"") | AE11: =IFERROR(VLOOKUP(A11,'星云问卷'!A:O,15,0),"") | AF11: =IFERROR(VLOOKUP(A11,'微伴数据'!A:DB,72,0),"") | AG11: 54BDGUcu | AH11: https://xiaobot.net/invitation/775fa-59965-f0225-3dbc4/ | AI11: 6drKTMfv | AL11: =CONCATENATE( " 我把体验营用户专属福利给你发一下哈：" & CHAR(10) & CHAR(10), "1.《抖音商业IP课》" & CHAR(10), "兑换码：", AG11, CHAR(10), "兑换码使用地址：https://appamvpb5mq9834.h5.xiaoeknow.com/p/t/v1/ecommerce/mkt/redeem_index" & CHAR(10) & CHAR(10), "2.《生财有术66个项目精选》" & CHAR(10), "兑换码：", AH11, CHAR(10), "使用方式：微信搜索小报童投递-点击开始阅读-点击生财有术项目精选即可" & CHAR(10) & CHAR(10), "3.《生财365问》" & CHAR(10), "兑换码：", AI11, CHAR(10), "使用方式：https://appamvpb5mq9834.h5.xiaoeknow.com/p/t/v1/ecommerce/mkt/redeem_index") | AO11: 纳入用户画像
A12: =IF('微伴数据'!A9="","",'微伴数据'!A9) | B12: =IF('微伴数据'!B9="","",'微伴数据'!B9) | C12: =IF('微伴数据'!G9="","",'微伴数据'!G9) | D12: =IF('微伴数据'!D9="","",'微伴数据'!D9) | E12: =IF('微伴数据'!CR9="","",'微伴数据'!CR9) | F12: =IF('微伴数据'!CL9="","",'微伴数据'!CL9) | G12: A | H12: 建联 | I12: =VLOOKUP(A12,'Sheet9'!A:A,1,0) | K12: =T12&CHAR(10)&U12&CHAR(10)&V12&CHAR(10)&Y12&CHAR(10)&Z12&CHAR(10)&AA12&CHAR(10)&AB12&CHAR(10)&AC12&CHAR(10)&AD12&CHAR(10)&AE12 | L12: =IFERROR(VLOOKUP(#REF!,'第一课直播'!D:L,9,0),IFERROR(VLOOKUP('第一课回放'!C:H,5,0),"未到课")) | M12: =IFERROR(VLOOKUP(#REF!,'第一课回放'!C:H,5,0),"0:00:00") | N12: =IFERROR(VLOOKUP(#REF!,'第二课直播'!D:L,9,0),"未到课") | S12: =IFERROR(VLOOKUP(A12,'微伴数据'!A:DB,12,0),"") | T12: =IFERROR(VLOOKUP(A12,'微伴数据'!A:DB,32,0),"") | U12: =IFERROR(VLOOKUP(A12,'微伴数据'!A:DC,81,0),"") | V12: =IFERROR(VLOOKUP(#REF!,'星橙地址'!A:V,9,0),"") | W12: =IFERROR(VLOOKUP(#REF!,'星橙地址'!A:V,10,0),"") | X12: =IFERROR(VLOOKUP(A12,'星云问卷'!A:O,8,0),"") | Y12: =IFERROR(VLOOKUP(A12,'星云问卷'!A:O,9,0),"") | Z12: =IFERROR(VLOOKUP(A12,'星云问卷'!A:O,10,0),"") | AA12: =IFERROR(VLOOKUP(A12,'星云问卷'!A:O,11,0),"") | AB12: =IFERROR(VLOOKUP(A12,'星云问卷'!A:O,12,0),"") | AC12: =IFERROR(VLOOKUP(A12,'星云问卷'!A:O,13,0),"") | AD12: =IFERROR(VLOOKUP(A12,'星云问卷'!A:O,14,0),"") | AE12: =IFERROR(VLOOKUP(A12,'星云问卷'!A:O,15,0),"") | AF12: =IFERROR(VLOOKUP(A12,'微伴数据'!A:DB,72,0),"") | AL12: =CONCATENATE( " 我把体验营用户专属福利给你发一下哈：" & CHAR(10) & CHAR(10), "1.《抖音商业IP课》" & CHAR(10), "兑换码：", AG12, CHAR(10), "兑换码使用地址：https://appamvpb5mq9834.h5.xiaoeknow.com/p/t/v1/ecommerce/mkt/redeem_index" & CHAR(10) & CHAR(10), "2.《生财有术66个项目精选》" & CHAR(10), "兑换码：", AH12, CHAR(10), "使用方式：微信搜索小报童投递-点击开始阅读-点击生财有术项目精选即可" & CHAR(10) & CHAR(10), "3.《生财365问》" & CHAR(10), "兑换码：", AI12, CHAR(10), "使用方式：https://appamvpb5mq9834.h5.xiaoeknow.com/p/t/v1/ecommerce/mkt/redeem_index")
A13: =IF('微伴数据'!A10="","",'微伴数据'!A10) | B13: =IF('微伴数据'!B10="","",'微伴数据'!B10) | C13: =IF('微伴数据'!G10="","",'微伴数据'!G10) | D13: =IF('微伴数据'!D10="","",'微伴数据'!D10) | E13: =IF('微伴数据'!CR10="","",'微伴数据'!CR10) | F13: =IF('微伴数据'!CL10="","",'微伴数据'!CL10) | G13: B | H13: 已成交 | I13: =VLOOKUP(A13,'Sheet9'!A:A,1,0) | K13: =T13&CHAR(10)&U13&CHAR(10)&V13&CHAR(10)&Y13&CHAR(10)&Z13&CHAR(10)&AA13&CHAR(10)&AB13&CHAR(10)&AC13&CHAR(10)&AD13&CHAR(10)&AE13 | L13: =IFERROR(VLOOKUP(#REF!,'第一课直播'!D:L,9,0),IFERROR(VLOOKUP('第一课回放'!C:H,5,0),"未到课")) | M13: =IFERROR(VLOOKUP(#REF!,'第一课回放'!C:H,5,0),"0:00:00") | N13: =IFERROR(VLOOKUP(#REF!,'第二课直播'!D:L,9,0),"未到课") | S13: =IFERROR(VLOOKUP(A13,'微伴数据'!A:DB,12,0),"") | T13: =IFERROR(VLOOKUP(A13,'微伴数据'!A:DB,32,0),"") | U13: =IFERROR(VLOOKUP(A13,'微伴数据'!A:DC,81,0),"") | V13: =IFERROR(VLOOKUP(#REF!,'星橙地址'!A:V,9,0),"") | W13: =IFERROR(VLOOKUP(#REF!,'星橙地址'!A:V,10,0),"") | X13: =IFERROR(VLOOKUP(A13,'星云问卷'!A:O,8,0),"") | Y13: =IFERROR(VLOOKUP(A13,'星云问卷'!A:O,9,0),"") | Z13: =IFERROR(VLOOKUP(A13,'星云问卷'!A:O,10,0),"") | AA13: =IFERROR(VLOOKUP(A13,'星云问卷'!A:O,11,0),"") | AB13: =IFERROR(VLOOKUP(A13,'星云问卷'!A:O,12,0),"") | AC13: =IFERROR(VLOOKUP(A13,'星云问卷'!A:O,13,0),"") | AD13: =IFERROR(VLOOKUP(A13,'星云问卷'!A:O,14,0),"") | AE13: =IFERROR(VLOOKUP(A13,'星云问卷'!A:O,15,0),"") | AF13: =IFERROR(VLOOKUP(A13,'微伴数据'!A:DB,72,0),"") | AL13: =CONCATENATE( " 我把体验营用户专属福利给你发一下哈：" & CHAR(10) & CHAR(10), "1.《抖音商业IP课》" & CHAR(10), "兑换码：", AG13, CHAR(10), "兑换码使用地址：https://appamvpb5mq9834.h5.xiaoeknow.com/p/t/v1/ecommerce/mkt/redeem_index" & CHAR(10) & CHAR(10), "2.《生财有术66个项目精选》" & CHAR(10), "兑换码：", AH13, CHAR(10), "使用方式：微信搜索小报童投递-点击开始阅读-点击生财有术项目精选即可" & CHAR(10) & CHAR(10), "3.《生财365问》" & CHAR(10), "兑换码：", AI13, CHAR(10), "使用方式：https://appamvpb5mq9834.h5.xiaoeknow.com/p/t/v1/ecommerce/mkt/redeem_index") | AO13: 纳入用户画像
A14: =IF('微伴数据'!A11="","",'微伴数据'!A11) | B14: =IF('微伴数据'!B11="","",'微伴数据'!B11) | C14: =IF('微伴数据'!G11="","",'微伴数据'!G11) | D14: =IF('微伴数据'!D11="","",'微伴数据'!D11) | E14: =IF('微伴数据'!CR11="","",'微伴数据'!CR11) | F14: =IF('微伴数据'!CL11="","",'微伴数据'!CL11) | G14: B | H14: 建联 | I14: =VLOOKUP(A14,'Sheet9'!A:A,1,0) | K14: =T14&CHAR(10)&U14&CHAR(10)&V14&CHAR(10)&Y14&CHAR(10)&Z14&CHAR(10)&AA14&CHAR(10)&AB14&CHAR(10)&AC14&CHAR(10)&AD14&CHAR(10)&AE14 | L14: =IFERROR(VLOOKUP(#REF!,'第一课直播'!D:L,9,0),IFERROR(VLOOKUP('第一课回放'!C:H,5,0),"未到课")) | M14: =IFERROR(VLOOKUP(#REF!,'第一课回放'!C:H,5,0),"0:00:00") | N14: =IFERROR(VLOOKUP(#REF!,'第二课直播'!D:L,9,0),"未到课") | S14: =IFERROR(VLOOKUP(A14,'微伴数据'!A:DB,12,0),"") | T14: =IFERROR(VLOOKUP(A14,'微伴数据'!A:DB,32,0),"") | U14: =IFERROR(VLOOKUP(A14,'微伴数据'!A:DC,81,0),"") | V14: =IFERROR(VLOOKUP(#REF!,'星橙地址'!A:V,9,0),"") | W14: =IFERROR(VLOOKUP(#REF!,'星橙地址'!A:V,10,0),"") | X14: =IFERROR(VLOOKUP(A14,'星云问卷'!A:O,8,0),"") | Y14: =IFERROR(VLOOKUP(A14,'星云问卷'!A:O,9,0),"") | Z14: =IFERROR(VLOOKUP(A14,'星云问卷'!A:O,10,0),"") | AA14: =IFERROR(VLOOKUP(A14,'星云问卷'!A:O,11,0),"") | AB14: =IFERROR(VLOOKUP(A14,'星云问卷'!A:O,12,0),"") | AC14: =IFERROR(VLOOKUP(A14,'星云问卷'!A:O,13,0),"") | AD14: =IFERROR(VLOOKUP(A14,'星云问卷'!A:O,14,0),"") | AE14: =IFERROR(VLOOKUP(A14,'星云问卷'!A:O,15,0),"") | AF14: =IFERROR(VLOOKUP(A14,'微伴数据'!A:DB,72,0),"") | AL14: =CONCATENATE( " 我把体验营用户专属福利给你发一下哈：" & CHAR(10) & CHAR(10), "1.《抖音商业IP课》" & CHAR(10), "兑换码：", AG14, CHAR(10), "兑换码使用地址：https://appamvpb5mq9834.h5.xiaoeknow.com/p/t/v1/ecommerce/mkt/redeem_index" & CHAR(10) & CHAR(10), "2.《生财有术66个项目精选》" & CHAR(10), "兑换码：", AH14, CHAR(10), "使用方式：微信搜索小报童投递-点击开始阅读-点击生财有术项目精选即可" & CHAR(10) & CHAR(10), "3.《生财365问》" & CHAR(10), "兑换码：", AI14, CHAR(10), "使用方式：https://appamvpb5mq9834.h5.xiaoeknow.com/p/t/v1/ecommerce/mkt/redeem_index")
A15: =IF('微伴数据'!A12="","",'微伴数据'!A12) | B15: =IF('微伴数据'!B12="","",'微伴数据'!B12) | C15: =IF('微伴数据'!G12="","",'微伴数据'!G12) | D15: =IF('微伴数据'!D12="","",'微伴数据'!D12) | E15: =IF('微伴数据'!CR12="","",'微伴数据'!CR12) | F15: =IF('微伴数据'!CL12="","",'微伴数据'!CL12) | G15: B | H15: 建联 | I15: =VLOOKUP(A15,'Sheet9'!A:A,1,0) | K15: =T15&CHAR(10)&U15&CHAR(10)&V15&CHAR(10)&Y15&CHAR(10)&Z15&CHAR(10)&AA15&CHAR(10)&AB15&CHAR(10)&AC15&CHAR(10)&AD15&CHAR(10)&AE15 | L15: =IFERROR(VLOOKUP(#REF!,'第一课直播'!D:L,9,0),IFERROR(VLOOKUP('第一课回放'!C:H,5,0),"未到课")) | M15: =IFERROR(VLOOKUP(#REF!,'第一课回放'!C:H,5,0),"0:00:00") | N15: =IFERROR(VLOOKUP(#REF!,'第二课直播'!D:L,9,0),"未到课") | S15: =IFERROR(VLOOKUP(A15,'微伴数据'!A:DB,12,0),"") | T15: =IFERROR(VLOOKUP(A15,'微伴数据'!A:DB,32,0),"") | U15: =IFERROR(VLOOKUP(A15,'微伴数据'!A:DC,81,0),"") | V15: =IFERROR(VLOOKUP(#REF!,'星橙地址'!A:V,9,0),"") | W15: =IFERROR(VLOOKUP(#REF!,'星橙地址'!A:V,10,0),"") | X15: =IFERROR(VLOOKUP(A15,'星云问卷'!A:O,8,0),"") | Y15: =IFERROR(VLOOKUP(A15,'星云问卷'!A:O,9,0),"") | Z15: =IFERROR(VLOOKUP(A15,'星云问卷'!A:O,10,0),"") | AA15: =IFERROR(VLOOKUP(A15,'星云问卷'!A:O,11,0),"") | AB15: =IFERROR(VLOOKUP(A15,'星云问卷'!A:O,12,0),"") | AC15: =IFERROR(VLOOKUP(A15,'星云问卷'!A:O,13,0),"") | AD15: =IFERROR(VLOOKUP(A15,'星云问卷'!A:O,14,0),"") | AE15: =IFERROR(VLOOKUP(A15,'星云问卷'!A:O,15,0),"") | AF15: =IFERROR(VLOOKUP(A15,'微伴数据'!A:DB,72,0),"") | AG15: 54Ax8QZg | AH15: https://xiaobot.net/invitation/46210-58465-12569-7f754/ | AI15: 6dqvWpDN | AL15: =CONCATENATE( " 我把体验营用户专属福利给你发一下哈：" & CHAR(10) & CHAR(10), "1.《抖音商业IP课》" & CHAR(10), "兑换码：", AG15, CHAR(10), "兑换码使用地址：https://appamvpb5mq9834.h5.xiaoeknow.com/p/t/v1/ecommerce/mkt/redeem_index" & CHAR(10) & CHAR(10), "2.《生财有术66个项目精选》" & CHAR(10), "兑换码：", AH15, CHAR(10), "使用方式：微信搜索小报童投递-点击开始阅读-点击生财有术项目精选即可" & CHAR(10) & CHAR(10), "3.《生财365问》" & CHAR(10), "兑换码：", AI15, CHAR(10), "使用方式：https://appamvpb5mq9834.h5.xiaoeknow.com/p/t/v1/ecommerce/mkt/redeem_index")
A16: =IF('微伴数据'!A13="","",'微伴数据'!A13) | B16: =IF('微伴数据'!B13="","",'微伴数据'!B13) | C16: =IF('微伴数据'!G13="","",'微伴数据'!G13) | D16: =IF('微伴数据'!D13="","",'微伴数据'!D13) | E16: =IF('微伴数据'!CR13="","",'微伴数据'!CR13) | F16: =IF('微伴数据'!CL13="","",'微伴数据'!CL13) | G16: B | H16: 建联 | I16: =VLOOKUP(A16,'Sheet9'!A:A,1,0) | K16: =T16&CHAR(10)&U16&CHAR(10)&V16&CHAR(10)&Y16&CHAR(10)&Z16&CHAR(10)&AA16&CHAR(10)&AB16&CHAR(10)&AC16&CHAR(10)&AD16&CHAR(10)&AE16 | L16: =IFERROR(VLOOKUP(#REF!,'第一课直播'!D:L,9,0),IFERROR(VLOOKUP('第一课回放'!C:H,5,0),"未到课")) | M16: =IFERROR(VLOOKUP(#REF!,'第一课回放'!C:H,5,0),"0:00:00") | N16: =IFERROR(VLOOKUP(#REF!,'第二课直播'!D:L,9,0),"未到课") | S16: =IFERROR(VLOOKUP(A16,'微伴数据'!A:DB,12,0),"") | T16: =IFERROR(VLOOKUP(A16,'微伴数据'!A:DB,32,0),"") | U16: =IFERROR(VLOOKUP(A16,'微伴数据'!A:DC,81,0),"") | V16: =IFERROR(VLOOKUP(#REF!,'星橙地址'!A:V,9,0),"") | W16: =IFERROR(VLOOKUP(#REF!,'星橙地址'!A:V,10,0),"") | X16: =IFERROR(VLOOKUP(A16,'星云问卷'!A:O,8,0),"") | Y16: =IFERROR(VLOOKUP(A16,'星云问卷'!A:O,9,0),"") | Z16: =IFERROR(VLOOKUP(A16,'星云问卷'!A:O,10,0),"") | AA16: =IFERROR(VLOOKUP(A16,'星云问卷'!A:O,11,0),"") | AB16: =IFERROR(VLOOKUP(A16,'星云问卷'!A:O,12,0),"") | AC16: =IFERROR(VLOOKUP(A16,'星云问卷'!A:O,13,0),"") | AD16: =IFERROR(VLOOKUP(A16,'星云问卷'!A:O,14,0),"") | AE16: =IFERROR(VLOOKUP(A16,'星云问卷'!A:O,15,0),"") | AF16: =IFERROR(VLOOKUP(A16,'微伴数据'!A:DB,72,0),"") | AG16: 547pkdFq | AH16: https://xiaobot.net/invitation/5e40f-70ae2-40ca9-98f6b/ | AI16: 6dhYjFah | AL16: =CONCATENATE( " 我把体验营用户专属福利给你发一下哈：" & CHAR(10) & CHAR(10), "1.《抖音商业IP课》" & CHAR(10), "兑换码：", AG16, CHAR(10), "兑换码使用地址：https://appamvpb5mq9834.h5.xiaoeknow.com/p/t/v1/ecommerce/mkt/redeem_index" & CHAR(10) & CHAR(10), "2.《生财有术66个项目精选》" & CHAR(10), "兑换码：", AH16, CHAR(10), "使用方式：微信搜索小报童投递-点击开始阅读-点击生财有术项目精选即可" & CHAR(10) & CHAR(10), "3.《生财365问》" & CHAR(10), "兑换码：", AI16, CHAR(10), "使用方式：https://appamvpb5mq9834.h5.xiaoeknow.com/p/t/v1/ecommerce/mkt/redeem_index")
A17: =IF('微伴数据'!A14="","",'微伴数据'!A14) | B17: =IF('微伴数据'!B14="","",'微伴数据'!B14) | C17: =IF('微伴数据'!G14="","",'微伴数据'!G14) | D17: =IF('微伴数据'!D14="","",'微伴数据'!D14) | E17: =IF('微伴数据'!CR14="","",'微伴数据'!CR14) | F17: =IF('微伴数据'!CL14="","",'微伴数据'!CL14) | G17: B | H17: 建联 | I17: =VLOOKUP(A17,'Sheet9'!A:A,1,0) | K17: =T17&CHAR(10)&U17&CHAR(10)&V17&CHAR(10)&Y17&CHAR(10)&Z17&CHAR(10)&AA17&CHAR(10)&AB17&CHAR(10)&AC17&CHAR(10)&AD17&CHAR(10)&AE17 | L17: =IFERROR(VLOOKUP(#REF!,'第一课直播'!D:L,9,0),IFERROR(VLOOKUP('第一课回放'!C:H,5,0),"未到课")) | M17: =IFERROR(VLOOKUP(#REF!,'第一课回放'!C:H,5,0),"0:00:00") | N17: =IFERROR(VLOOKUP(#REF!,'第二课直播'!D:L,9,0),"未到课") | S17: =IFERROR(VLOOKUP(A17,'微伴数据'!A:DB,12,0),"") | T17: =IFERROR(VLOOKUP(A17,'微伴数据'!A:DB,32,0),"") | U17: =IFERROR(VLOOKUP(A17,'微伴数据'!A:DC,81,0),"") | V17: =IFERROR(VLOOKUP(#REF!,'星橙地址'!A:V,9,0),"") | W17: =IFERROR(VLOOKUP(#REF!,'星橙地址'!A:V,10,0),"") | X17: =IFERROR(VLOOKUP(A17,'星云问卷'!A:O,8,0),"") | Y17: =IFERROR(VLOOKUP(A17,'星云问卷'!A:O,9,0),"") | Z17: =IFERROR(VLOOKUP(A17,'星云问卷'!A:O,10,0),"") | AA17: =IFERROR(VLOOKUP(A17,'星云问卷'!A:O,11,0),"") | AB17: =IFERROR(VLOOKUP(A17,'星云问卷'!A:O,12,0),"") | AC17: =IFERROR(VLOOKUP(A17,'星云问卷'!A:O,13,0),"") | AD17: =IFERROR(VLOOKUP(A17,'星云问卷'!A:O,14,0),"") | AE17: =IFERROR(VLOOKUP(A17,'星云问卷'!A:O,15,0),"") | AF17: =IFERROR(VLOOKUP(A17,'微伴数据'!A:DB,72,0),"") | AL17: =CONCATENATE( " 我把体验营用户专属福利给你发一下哈：" & CHAR(10) & CHAR(10), "1.《抖音商业IP课》" & CHAR(10), "兑换码：", AG17, CHAR(10), "兑换码使用地址：https://appamvpb5mq9834.h5.xiaoeknow.com/p/t/v1/ecommerce/mkt/redeem_index" & CHAR(10) & CHAR(10), "2.《生财有术66个项目精选》" & CHAR(10), "兑换码：", AH17, CHAR(10), "使用方式：微信搜索小报童投递-点击开始阅读-点击生财有术项目精选即可" & CHAR(10) & CHAR(10), "3.《生财365问》" & CHAR(10), "兑换码：", AI17, CHAR(10), "使用方式：https://appamvpb5mq9834.h5.xiaoeknow.com/p/t/v1/ecommerce/mkt/redeem_index")
A18: =IF('微伴数据'!A15="","",'微伴数据'!A15) | B18: =IF('微伴数据'!B15="","",'微伴数据'!B15) | C18: =IF('微伴数据'!G15="","",'微伴数据'!G15) | D18: =IF('微伴数据'!D15="","",'微伴数据'!D15) | E18: =IF('微伴数据'!CR15="","",'微伴数据'!CR15) | F18: =IF('微伴数据'!CL15="","",'微伴数据'!CL15) | G18: B | H18: 建联 | I18: =VLOOKUP(A18,'Sheet9'!A:A,1,0) | K18: =T18&CHAR(10)&U18&CHAR(10)&V18&CHAR(10)&Y18&CHAR(10)&Z18&CHAR(10)&AA18&CHAR(10)&AB18&CHAR(10)&AC18&CHAR(10)&AD18&CHAR(10)&AE18 | L18: =IFERROR(VLOOKUP(#REF!,'第一课直播'!D:L,9,0),IFERROR(VLOOKUP('第一课回放'!C:H,5,0),"未到课")) | M18: =IFERROR(VLOOKUP(#REF!,'第一课回放'!C:H,5,0),"0:00:00") | N18: =IFERROR(VLOOKUP(#REF!,'第二课直播'!D:L,9,0),"未到课") | S18: =IFERROR(VLOOKUP(A18,'微伴数据'!A:DB,12,0),"") | T18: =IFERROR(VLOOKUP(A18,'微伴数据'!A:DB,32,0),"") | U18: =IFERROR(VLOOKUP(A18,'微伴数据'!A:DC,81,0),"") | V18: =IFERROR(VLOOKUP(#REF!,'星橙地址'!A:V,9,0),"") | W18: =IFERROR(VLOOKUP(#REF!,'星橙地址'!A:V,10,0),"") | X18: =IFERROR(VLOOKUP(A18,'星云问卷'!A:O,8,0),"") | Y18: =IFERROR(VLOOKUP(A18,'星云问卷'!A:O,9,0),"") | Z18: =IFERROR(VLOOKUP(A18,'星云问卷'!A:O,10,0),"") | AA18: =IFERROR(VLOOKUP(A18,'星云问卷'!A:O,11,0),"") | AB18: =IFERROR(VLOOKUP(A18,'星云问卷'!A:O,12,0),"") | AC18: =IFERROR(VLOOKUP(A18,'星云问卷'!A:O,13,0),"") | AD18: =IFERROR(VLOOKUP(A18,'星云问卷'!A:O,14,0),"") | AE18: =IFERROR(VLOOKUP(A18,'星云问卷'!A:O,15,0),"") | AF18: =IFERROR(VLOOKUP(A18,'微伴数据'!A:DB,72,0),"") | AL18: =CONCATENATE( " 我把体验营用户专属福利给你发一下哈：" & CHAR(10) & CHAR(10), "1.《抖音商业IP课》" & CHAR(10), "兑换码：", AG18, CHAR(10), "兑换码使用地址：https://appamvpb5mq9834.h5.xiaoeknow.com/p/t/v1/ecommerce/mkt/redeem_index" & CHAR(10) & CHAR(10), "2.《生财有术66个项目精选》" & CHAR(10), "兑换码：", AH18, CHAR(10), "使用方式：微信搜索小报童投递-点击开始阅读-点击生财有术项目精选即可" & CHAR(10) & CHAR(10), "3.《生财365问》" & CHAR(10), "兑换码：", AI18, CHAR(10), "使用方式：https://appamvpb5mq9834.h5.xiaoeknow.com/p/t/v1/ecommerce/mkt/redeem_index")
A19: =IF('微伴数据'!A16="","",'微伴数据'!A16) | B19: =IF('微伴数据'!B16="","",'微伴数据'!B16) | C19: =IF('微伴数据'!G16="","",'微伴数据'!G16) | D19: =IF('微伴数据'!D16="","",'微伴数据'!D16) | E19: =IF('微伴数据'!CR16="","",'微伴数据'!CR16) | F19: =IF('微伴数据'!CL16="","",'微伴数据'!CL16) | G19: B | H19: 建联 | I19: =VLOOKUP(A19,'Sheet9'!A:A,1,0) | K19: =T19&CHAR(10)&U19&CHAR(10)&V19&CHAR(10)&Y19&CHAR(10)&Z19&CHAR(10)&AA19&CHAR(10)&AB19&CHAR(10)&AC19&CHAR(10)&AD19&CHAR(10)&AE19 | L19: =IFERROR(VLOOKUP(#REF!,'第一课直播'!D:L,9,0),IFERROR(VLOOKUP('第一课回放'!C:H,5,0),"未到课")) | M19: =IFERROR(VLOOKUP(#REF!,'第一课回放'!C:H,5,0),"0:00:00") | N19: =IFERROR(VLOOKUP(#REF!,'第二课直播'!D:L,9,0),"未到课") | S19: =IFERROR(VLOOKUP(A19,'微伴数据'!A:DB,12,0),"") | T19: =IFERROR(VLOOKUP(A19,'微伴数据'!A:DB,32,0),"") | U19: =IFERROR(VLOOKUP(A19,'微伴数据'!A:DC,81,0),"") | V19: =IFERROR(VLOOKUP(#REF!,'星橙地址'!A:V,9,0),"") | W19: =IFERROR(VLOOKUP(#REF!,'星橙地址'!A:V,10,0),"") | X19: =IFERROR(VLOOKUP(A19,'星云问卷'!A:O,8,0),"") | Y19: =IFERROR(VLOOKUP(A19,'星云问卷'!A:O,9,0),"") | Z19: =IFERROR(VLOOKUP(A19,'星云问卷'!A:O,10,0),"") | AA19: =IFERROR(VLOOKUP(A19,'星云问卷'!A:O,11,0),"") | AB19: =IFERROR(VLOOKUP(A19,'星云问卷'!A:O,12,0),"") | AC19: =IFERROR(VLOOKUP(A19,'星云问卷'!A:O,13,0),"") | AD19: =IFERROR(VLOOKUP(A19,'星云问卷'!A:O,14,0),"") | AE19: =IFERROR(VLOOKUP(A19,'星云问卷'!A:O,15,0),"") | AF19: =IFERROR(VLOOKUP(A19,'微伴数据'!A:DB,72,0),"") | AG19: 54AkhdvV | AH19: https://xiaobot.net/invitation/11952-f5d0b-a1c7a-8bd6f/ | AI19: 6dqbDhPk | AL19: =CONCATENATE( " 我把体验营用户专属福利给你发一下哈：" & CHAR(10) & CHAR(10), "1.《抖音商业IP课》" & CHAR(10), "兑换码：", AG19, CHAR(10), "兑换码使用地址：https://appamvpb5mq9834.h5.xiaoeknow.com/p/t/v1/ecommerce/mkt/redeem_index" & CHAR(10) & CHAR(10), "2.《生财有术66个项目精选》" & CHAR(10), "兑换码：", AH19, CHAR(10), "使用方式：微信搜索小报童投递-点击开始阅读-点击生财有术项目精选即可" & CHAR(10) & CHAR(10), "3.《生财365问》" & CHAR(10), "兑换码：", AI19, CHAR(10), "使用方式：https://appamvpb5mq9834.h5.xiaoeknow.com/p/t/v1/ecommerce/mkt/redeem_index")
A20: =IF('微伴数据'!A17="","",'微伴数据'!A17) | B20: =IF('微伴数据'!B17="","",'微伴数据'!B17) | C20: =IF('微伴数据'!G17="","",'微伴数据'!G17) | D20: =IF('微伴数据'!D17="","",'微伴数据'!D17) | E20: =IF('微伴数据'!CR17="","",'微伴数据'!CR17) | F20: =IF('微伴数据'!CL17="","",'微伴数据'!CL17) | G20: B | H20: 建联 | I20: =VLOOKUP(A20,'Sheet9'!A:A,1,0) | K20: =T20&CHAR(10)&U20&CHAR(10)&V20&CHAR(10)&Y20&CHAR(10)&Z20&CHAR(10)&AA20&CHAR(10)&AB20&CHAR(10)&AC20&CHAR(10)&AD20&CHAR(10)&AE20 | L20: =IFERROR(VLOOKUP(#REF!,'第一课直播'!D:L,9,0),IFERROR(VLOOKUP('第一课回放'!C:H,5,0),"未到课")) | M20: =IFERROR(VLOOKUP(#REF!,'第一课回放'!C:H,5,0),"0:00:00") | N20: =IFERROR(VLOOKUP(#REF!,'第二课直播'!D:L,9,0),"未到课") | S20: =IFERROR(VLOOKUP(A20,'微伴数据'!A:DB,12,0),"") | T20: =IFERROR(VLOOKUP(A20,'微伴数据'!A:DB,32,0),"") | U20: 会员_7 | V20: =IFERROR(VLOOKUP(#REF!,'星橙地址'!A:V,9,0),"") | W20: =IFERROR(VLOOKUP(#REF!,'星橙地址'!A:V,10,0),"") | X20: =IFERROR(VLOOKUP(A20,'星云问卷'!A:O,8,0),"") | Y20: =IFERROR(VLOOKUP(A20,'星云问卷'!A:O,9,0),"") | Z20: =IFERROR(VLOOKUP(A20,'星云问卷'!A:O,10,0),"") | AA20: =IFERROR(VLOOKUP(A20,'星云问卷'!A:O,11,0),"") | AB20: =IFERROR(VLOOKUP(A20,'星云问卷'!A:O,12,0),"") | AC20: =IFERROR(VLOOKUP(A20,'星云问卷'!A:O,13,0),"") | AD20: =IFERROR(VLOOKUP(A20,'星云问卷'!A:O,14,0),"") | AE20: =IFERROR(VLOOKUP(A20,'星云问卷'!A:O,15,0),"") | AF20: =IFERROR(VLOOKUP(A20,'微伴数据'!A:DB,72,0),"") | AL20: =CONCATENATE( " 我把体验营用户专属福利给你发一下哈：" & CHAR(10) & CHAR(10), "1.《抖音商业IP课》" & CHAR(10), "兑换码：", AG20, CHAR(10), "兑换码使用地址：https://appamvpb5mq9834.h5.xiaoeknow.com/p/t/v1/ecommerce/mkt/redeem_index" & CHAR(10) & CHAR(10), "2.《生财有术66个项目精选》" & CHAR(10), "兑换码：", AH20, CHAR(10), "使用方式：微信搜索小报童投递-点击开始阅读-点击生财有术项目精选即可" & CHAR(10) & CHAR(10), "3.《生财365问》" & CHAR(10), "兑换码：", AI20, CHAR(10), "使用方式：https://appamvpb5mq9834.h5.xiaoeknow.com/p/t/v1/ecommerce/mkt/redeem_index") | AO20: 纳入用户画像
A21: =IF('微伴数据'!A18="","",'微伴数据'!A18) | B21: =IF('微伴数据'!B18="","",'微伴数据'!B18) | C21: =IF('微伴数据'!G18="","",'微伴数据'!G18) | D21: =IF('微伴数据'!D18="","",'微伴数据'!D18) | E21: =IF('微伴数据'!CR18="","",'微伴数据'!CR18) | F21: =IF('微伴数据'!CL18="","",'微伴数据'!CL18) | G21: S | H21: 建联 | I21: =VLOOKUP(A21,'Sheet9'!A:A,1,0) | K21: =T21&CHAR(10)&U21&CHAR(10)&V21&CHAR(10)&Y21&CHAR(10)&Z21&CHAR(10)&AA21&CHAR(10)&AB21&CHAR(10)&AC21&CHAR(10)&AD21&CHAR(10)&AE21 | L21: =IFERROR(VLOOKUP(#REF!,'第一课直播'!D:L,9,0),IFERROR(VLOOKUP('第一课回放'!C:H,5,0),"未到课")) | M21: =IFERROR(VLOOKUP(#REF!,'第一课回放'!C:H,5,0),"0:00:00") | N21: =IFERROR(VLOOKUP(#REF!,'第二课直播'!D:L,9,0),"未到课") | S21: =IFERROR(VLOOKUP(A21,'微伴数据'!A:DB,12,0),"") | T21: =IFERROR(VLOOKUP(A21,'微伴数据'!A:DB,32,0),"") | U21: =IFERROR(VLOOKUP(A21,'微伴数据'!A:DC,81,0),"") | V21: =IFERROR(VLOOKUP(#REF!,'星橙地址'!A:V,9,0),"") | W21: =IFERROR(VLOOKUP(#REF!,'星橙地址'!A:V,10,0),"") | X21: =IFERROR(VLOOKUP(A21,'星云问卷'!A:O,8,0),"") | Y21: =IFERROR(VLOOKUP(A21,'星云问卷'!A:O,9,0),"") | Z21: =IFERROR(VLOOKUP(A21,'星云问卷'!A:O,10,0),"") | AA21: =IFERROR(VLOOKUP(A21,'星云问卷'!A:O,11,0),"") | AB21: =IFERROR(VLOOKUP(A21,'星云问卷'!A:O,12,0),"") | AC21: =IFERROR(VLOOKUP(A21,'星云问卷'!A:O,13,0),"") | AD21: =IFERROR(VLOOKUP(A21,'星云问卷'!A:O,14,0),"") | AE21: =IFERROR(VLOOKUP(A21,'星云问卷'!A:O,15,0),"") | AF21: =IFERROR(VLOOKUP(A21,'微伴数据'!A:DB,72,0),"") | AL21: =CONCATENATE( " 我把体验营用户专属福利给你发一下哈：" & CHAR(10) & CHAR(10), "1.《抖音商业IP课》" & CHAR(10), "兑换码：", AG21, CHAR(10), "兑换码使用地址：https://appamvpb5mq9834.h5.xiaoeknow.com/p/t/v1/ecommerce/mkt/redeem_index" & CHAR(10) & CHAR(10), "2.《生财有术66个项目精选》" & CHAR(10), "兑换码：", AH21, CHAR(10), "使用方式：微信搜索小报童投递-点击开始阅读-点击生财有术项目精选即可" & CHAR(10) & CHAR(10), "3.《生财365问》" & CHAR(10), "兑换码：", AI21, CHAR(10), "使用方式：https://appamvpb5mq9834.h5.xiaoeknow.com/p/t/v1/ecommerce/mkt/redeem_index")
A22: =IF('微伴数据'!A19="","",'微伴数据'!A19) | B22: =IF('微伴数据'!B19="","",'微伴数据'!B19) | C22: =IF('微伴数据'!G19="","",'微伴数据'!G19) | D22: =IF('微伴数据'!D19="","",'微伴数据'!D19) | E22: =IF('微伴数据'!CR19="","",'微伴数据'!CR19) | F22: =IF('微伴数据'!CL19="","",'微伴数据'!CL19) | G22: B | H22: 建联 | I22: =VLOOKUP(A22,'Sheet9'!A:A,1,0) | K22: =T22&CHAR(10)&U22&CHAR(10)&V22&CHAR(10)&Y22&CHAR(10)&Z22&CHAR(10)&AA22&CHAR(10)&AB22&CHAR(10)&AC22&CHAR(10)&AD22&CHAR(10)&AE22 | L22: =IFERROR(VLOOKUP(#REF!,'第一课直播'!D:L,9,0),IFERROR(VLOOKUP('第一课回放'!C:H,5,0),"未到课")) | M22: =IFERROR(VLOOKUP(#REF!,'第一课回放'!C:H,5,0),"0:00:00") | N22: =IFERROR(VLOOKUP(#REF!,'第二课直播'!D:L,9,0),"未到课") | S22: =IFERROR(VLOOKUP(A22,'微伴数据'!A:DB,12,0),"") | T22: =IFERROR(VLOOKUP(A22,'微伴数据'!A:DB,32,0),"") | U22: =IFERROR(VLOOKUP(A22,'微伴数据'!A:DC,81,0),"") | V22: =IFERROR(VLOOKUP(#REF!,'星橙地址'!A:V,9,0),"") | W22: =IFERROR(VLOOKUP(#REF!,'星橙地址'!A:V,10,0),"") | X22: =IFERROR(VLOOKUP(A22,'星云问卷'!A:O,8,0),"") | Y22: =IFERROR(VLOOKUP(A22,'星云问卷'!A:O,9,0),"") | Z22: =IFERROR(VLOOKUP(A22,'星云问卷'!A:O,10,0),"") | AA22: =IFERROR(VLOOKUP(A22,'星云问卷'!A:O,11,0),"") | AB22: =IFERROR(VLOOKUP(A22,'星云问卷'!A:O,12,0),"") | AC22: =IFERROR(VLOOKUP(A22,'星云问卷'!A:O,13,0),"") | AD22: =IFERROR(VLOOKUP(A22,'星云问卷'!A:O,14,0),"") | AE22: =IFERROR(VLOOKUP(A22,'星云问卷'!A:O,15,0),"") | AF22: =IFERROR(VLOOKUP(A22,'微伴数据'!A:DB,72,0),"") | AL22: =CONCATENATE( " 我把体验营用户专属福利给你发一下哈：" & CHAR(10) & CHAR(10), "1.《抖音商业IP课》" & CHAR(10), "兑换码：", AG22, CHAR(10), "兑换码使用地址：https://appamvpb5mq9834.h5.xiaoeknow.com/p/t/v1/ecommerce/mkt/redeem_index" & CHAR(10) & CHAR(10), "2.《生财有术66个项目精选》" & CHAR(10), "兑换码：", AH22, CHAR(10), "使用方式：微信搜索小报童投递-点击开始阅读-点击生财有术项目精选即可" & CHAR(10) & CHAR(10), "3.《生财365问》" & CHAR(10), "兑换码：", AI22, CHAR(10), "使用方式：https://appamvpb5mq9834.h5.xiaoeknow.com/p/t/v1/ecommerce/mkt/redeem_index")
A23: =IF('微伴数据'!A20="","",'微伴数据'!A20) | B23: =IF('微伴数据'!B20="","",'微伴数据'!B20) | C23: =IF('微伴数据'!G20="","",'微伴数据'!G20) | D23: =IF('微伴数据'!D20="","",'微伴数据'!D20) | E23: =IF('微伴数据'!CR20="","",'微伴数据'!CR20) | F23: =IF('微伴数据'!CL20="","",'微伴数据'!CL20) | G23: B | H23: 建联 | I23: =VLOOKUP(A23,'Sheet9'!A:A,1,0) | K23: =T23&CHAR(10)&U23&CHAR(10)&V23&CHAR(10)&Y23&CHAR(10)&Z23&CHAR(10)&AA23&CHAR(10)&AB23&CHAR(10)&AC23&CHAR(10)&AD23&CHAR(10)&AE23 | L23: =IFERROR(VLOOKUP(#REF!,'第一课直播'!D:L,9,0),IFERROR(VLOOKUP('第一课回放'!C:H,5,0),"未到课")) | M23: =IFERROR(VLOOKUP(#REF!,'第一课回放'!C:H,5,0),"0:00:00") | N23: =IFERROR(VLOOKUP(#REF!,'第二课直播'!D:L,9,0),"未到课") | S23: =IFERROR(VLOOKUP(A23,'微伴数据'!A:DB,12,0),"") | T23: =IFERROR(VLOOKUP(A23,'微伴数据'!A:DB,32,0),"") | U23: =IFERROR(VLOOKUP(A23,'微伴数据'!A:DC,81,0),"") | V23: =IFERROR(VLOOKUP(#REF!,'星橙地址'!A:V,9,0),"") | W23: =IFERROR(VLOOKUP(#REF!,'星橙地址'!A:V,10,0),"") | X23: =IFERROR(VLOOKUP(A23,'星云问卷'!A:O,8,0),"") | Y23: =IFERROR(VLOOKUP(A23,'星云问卷'!A:O,9,0),"") | Z23: =IFERROR(VLOOKUP(A23,'星云问卷'!A:O,10,0),"") | AA23: =IFERROR(VLOOKUP(A23,'星云问卷'!A:O,11,0),"") | AB23: =IFERROR(VLOOKUP(A23,'星云问卷'!A:O,12,0),"") | AC23: =IFERROR(VLOOKUP(A23,'星云问卷'!A:O,13,0),"") | AD23: =IFERROR(VLOOKUP(A23,'星云问卷'!A:O,14,0),"") | AE23: =IFERROR(VLOOKUP(A23,'星云问卷'!A:O,15,0),"") | AF23: =IFERROR(VLOOKUP(A23,'微伴数据'!A:DB,72,0),"") | AL23: =CONCATENATE( " 我把体验营用户专属福利给你发一下哈：" & CHAR(10) & CHAR(10), "1.《抖音商业IP课》" & CHAR(10), "兑换码：", AG23, CHAR(10), "兑换码使用地址：https://appamvpb5mq9834.h5.xiaoeknow.com/p/t/v1/ecommerce/mkt/redeem_index" & CHAR(10) & CHAR(10), "2.《生财有术66个项目精选》" & CHAR(10), "兑换码：", AH23, CHAR(10), "使用方式：微信搜索小报童投递-点击开始阅读-点击生财有术项目精选即可" & CHAR(10) & CHAR(10), "3.《生财365问》" & CHAR(10), "兑换码：", AI23, CHAR(10), "使用方式：https://appamvpb5mq9834.h5.xiaoeknow.com/p/t/v1/ecommerce/mkt/redeem_index")
A24: =IF('微伴数据'!A21="","",'微伴数据'!A21) | B24: =IF('微伴数据'!B21="","",'微伴数据'!B21) | C24: =IF('微伴数据'!G21="","",'微伴数据'!G21) | D24: =IF('微伴数据'!D21="","",'微伴数据'!D21) | E24: =IF('微伴数据'!CR21="","",'微伴数据'!CR21) | F24: =IF('微伴数据'!CL21="","",'微伴数据'!CL21) | G24: A | H24: 建联 | I24: =VLOOKUP(A24,'Sheet9'!A:A,1,0) | K24: =T24&CHAR(10)&U24&CHAR(10)&V24&CHAR(10)&Y24&CHAR(10)&Z24&CHAR(10)&AA24&CHAR(10)&AB24&CHAR(10)&AC24&CHAR(10)&AD24&CHAR(10)&AE24 | L24: =IFERROR(VLOOKUP(#REF!,'第一课直播'!D:L,9,0),IFERROR(VLOOKUP('第一课回放'!C:H,5,0),"未到课")) | M24: =IFERROR(VLOOKUP(#REF!,'第一课回放'!C:H,5,0),"0:00:00") | N24: =IFERROR(VLOOKUP(#REF!,'第二课直播'!D:L,9,0),"未到课") | S24: =IFERROR(VLOOKUP(A24,'微伴数据'!A:DB,12,0),"") | T24: =IFERROR(VLOOKUP(A24,'微伴数据'!A:DB,32,0),"") | U24: =IFERROR(VLOOKUP(A24,'微伴数据'!A:DC,81,0),"") | V24: =IFERROR(VLOOKUP(#REF!,'星橙地址'!A:V,9,0),"") | W24: =IFERROR(VLOOKUP(#REF!,'星橙地址'!A:V,10,0),"") | X24: =IFERROR(VLOOKUP(A24,'星云问卷'!A:O,8,0),"") | Y24: =IFERROR(VLOOKUP(A24,'星云问卷'!A:O,9,0),"") | Z24: =IFERROR(VLOOKUP(A24,'星云问卷'!A:O,10,0),"") | AA24: =IFERROR(VLOOKUP(A24,'星云问卷'!A:O,11,0),"") | AB24: =IFERROR(VLOOKUP(A24,'星云问卷'!A:O,12,0),"") | AC24: =IFERROR(VLOOKUP(A24,'星云问卷'!A:O,13,0),"") | AD24: =IFERROR(VLOOKUP(A24,'星云问卷'!A:O,14,0),"") | AE24: =IFERROR(VLOOKUP(A24,'星云问卷'!A:O,15,0),"") | AF24: =IFERROR(VLOOKUP(A24,'微伴数据'!A:DB,72,0),"") | AL24: =CONCATENATE( " 我把体验营用户专属福利给你发一下哈：" & CHAR(10) & CHAR(10), "1.《抖音商业IP课》" & CHAR(10), "兑换码：", AG24, CHAR(10), "兑换码使用地址：https://appamvpb5mq9834.h5.xiaoeknow.com/p/t/v1/ecommerce/mkt/redeem_index" & CHAR(10) & CHAR(10), "2.《生财有术66个项目精选》" & CHAR(10), "兑换码：", AH24, CHAR(10), "使用方式：微信搜索小报童投递-点击开始阅读-点击生财有术项目精选即可" & CHAR(10) & CHAR(10), "3.《生财365问》" & CHAR(10), "兑换码：", AI24, CHAR(10), "使用方式：https://appamvpb5mq9834.h5.xiaoeknow.com/p/t/v1/ecommerce/mkt/redeem_index")
A25: =IF('微伴数据'!A22="","",'微伴数据'!A22) | B25: =IF('微伴数据'!B22="","",'微伴数据'!B22) | C25: =IF('微伴数据'!G22="","",'微伴数据'!G22) | D25: =IF('微伴数据'!D22="","",'微伴数据'!D22) | E25: =IF('微伴数据'!CR22="","",'微伴数据'!CR22) | F25: =IF('微伴数据'!CL22="","",'微伴数据'!CL22) | G25: B | H25: 建联 | I25: =VLOOKUP(A25,'Sheet9'!A:A,1,0) | K25: =T25&CHAR(10)&U25&CHAR(10)&V25&CHAR(10)&Y25&CHAR(10)&Z25&CHAR(10)&AA25&CHAR(10)&AB25&CHAR(10)&AC25&CHAR(10)&AD25&CHAR(10)&AE25 | L25: =IFERROR(VLOOKUP(#REF!,'第一课直播'!D:L,9,0),IFERROR(VLOOKUP('第一课回放'!C:H,5,0),"未到课")) | M25: =IFERROR(VLOOKUP(#REF!,'第一课回放'!C:H,5,0),"0:00:00") | N25: =IFERROR(VLOOKUP(#REF!,'第二课直播'!D:L,9,0),"未到课") | S25: =IFERROR(VLOOKUP(A25,'微伴数据'!A:DB,12,0),"") | T25: =IFERROR(VLOOKUP(A25,'微伴数据'!A:DB,32,0),"") | U25: =IFERROR(VLOOKUP(A25,'微伴数据'!A:DC,81,0),"") | V25: =IFERROR(VLOOKUP(#REF!,'星橙地址'!A:V,9,0),"") | W25: =IFERROR(VLOOKUP(#REF!,'星橙地址'!A:V,10,0),"") | X25: =IFERROR(VLOOKUP(A25,'星云问卷'!A:O,8,0),"") | Y25: =IFERROR(VLOOKUP(A25,'星云问卷'!A:O,9,0),"") | Z25: =IFERROR(VLOOKUP(A25,'星云问卷'!A:O,10,0),"") | AA25: =IFERROR(VLOOKUP(A25,'星云问卷'!A:O,11,0),"") | AB25: =IFERROR(VLOOKUP(A25,'星云问卷'!A:O,12,0),"") | AC25: =IFERROR(VLOOKUP(A25,'星云问卷'!A:O,13,0),"") | AD25: =IFERROR(VLOOKUP(A25,'星云问卷'!A:O,14,0),"") | AE25: =IFERROR(VLOOKUP(A25,'星云问卷'!A:O,15,0),"") | AF25: =IFERROR(VLOOKUP(A25,'微伴数据'!A:DB,72,0),"") | AL25: =CONCATENATE( " 我把体验营用户专属福利给你发一下哈：" & CHAR(10) & CHAR(10), "1.《抖音商业IP课》" & CHAR(10), "兑换码：", AG25, CHAR(10), "兑换码使用地址：https://appamvpb5mq9834.h5.xiaoeknow.com/p/t/v1/ecommerce/mkt/redeem_index" & CHAR(10) & CHAR(10), "2.《生财有术66个项目精选》" & CHAR(10), "兑换码：", AH25, CHAR(10), "使用方式：微信搜索小报童投递-点击开始阅读-点击生财有术项目精选即可" & CHAR(10) & CHAR(10), "3.《生财365问》" & CHAR(10), "兑换码：", AI25, CHAR(10), "使用方式：https://appamvpb5mq9834.h5.xiaoeknow.com/p/t/v1/ecommerce/mkt/redeem_index")
A26: =IF('微伴数据'!A23="","",'微伴数据'!A23) | B26: =IF('微伴数据'!B23="","",'微伴数据'!B23) | C26: =IF('微伴数据'!G23="","",'微伴数据'!G23) | D26: =IF('微伴数据'!D23="","",'微伴数据'!D23) | E26: =IF('微伴数据'!CR23="","",'微伴数据'!CR23) | F26: =IF('微伴数据'!CL23="","",'微伴数据'!CL23) | G26: B | H26: 建联 | I26: =VLOOKUP(A26,'Sheet9'!A:A,1,0) | K26: =T26&CHAR(10)&U26&CHAR(10)&V26&CHAR(10)&Y26&CHAR(10)&Z26&CHAR(10)&AA26&CHAR(10)&AB26&CHAR(10)&AC26&CHAR(10)&AD26&CHAR(10)&AE26 | L26: =IFERROR(VLOOKUP(#REF!,'第一课直播'!D:L,9,0),IFERROR(VLOOKUP('第一课回放'!C:H,5,0),"未到课")) | M26: =IFERROR(VLOOKUP(#REF!,'第一课回放'!C:H,5,0),"0:00:00") | N26: =IFERROR(VLOOKUP(#REF!,'第二课直播'!D:L,9,0),"未到课") | S26: =IFERROR(VLOOKUP(A26,'微伴数据'!A:DB,12,0),"") | T26: =IFERROR(VLOOKUP(A26,'微伴数据'!A:DB,32,0),"") | U26: =IFERROR(VLOOKUP(A26,'微伴数据'!A:DC,81,0),"") | V26: =IFERROR(VLOOKUP(#REF!,'星橙地址'!A:V,9,0),"") | W26: =IFERROR(VLOOKUP(#REF!,'星橙地址'!A:V,10,0),"") | X26: =IFERROR(VLOOKUP(A26,'星云问卷'!A:O,8,0),"") | Y26: =IFERROR(VLOOKUP(A26,'星云问卷'!A:O,9,0),"") | Z26: =IFERROR(VLOOKUP(A26,'星云问卷'!A:O,10,0),"") | AA26: =IFERROR(VLOOKUP(A26,'星云问卷'!A:O,11,0),"") | AB26: =IFERROR(VLOOKUP(A26,'星云问卷'!A:O,12,0),"") | AC26: =IFERROR(VLOOKUP(A26,'星云问卷'!A:O,13,0),"") | AD26: =IFERROR(VLOOKUP(A26,'星云问卷'!A:O,14,0),"") | AE26: =IFERROR(VLOOKUP(A26,'星云问卷'!A:O,15,0),"") | AF26: =IFERROR(VLOOKUP(A26,'微伴数据'!A:DB,72,0),"") | AL26: =CONCATENATE( " 我把体验营用户专属福利给你发一下哈：" & CHAR(10) & CHAR(10), "1.《抖音商业IP课》" & CHAR(10), "兑换码：", AG26, CHAR(10), "兑换码使用地址：https://appamvpb5mq9834.h5.xiaoeknow.com/p/t/v1/ecommerce/mkt/redeem_index" & CHAR(10) & CHAR(10), "2.《生财有术66个项目精选》" & CHAR(10), "兑换码：", AH26, CHAR(10), "使用方式：微信搜索小报童投递-点击开始阅读-点击生财有术项目精选即可" & CHAR(10) & CHAR(10), "3.《生财365问》" & CHAR(10), "兑换码：", AI26, CHAR(10), "使用方式：https://appamvpb5mq9834.h5.xiaoeknow.com/p/t/v1/ecommerce/mkt/redeem_index")
A27: =IF('微伴数据'!A24="","",'微伴数据'!A24) | B27: =IF('微伴数据'!B24="","",'微伴数据'!B24) | C27: =IF('微伴数据'!G24="","",'微伴数据'!G24) | D27: =IF('微伴数据'!D24="","",'微伴数据'!D24) | E27: =IF('微伴数据'!CR24="","",'微伴数据'!CR24) | F27: =IF('微伴数据'!CL24="","",'微伴数据'!CL24) | G27: B | H27: 建联 | I27: =VLOOKUP(A27,'Sheet9'!A:A,1,0) | K27: =T27&CHAR(10)&U27&CHAR(10)&V27&CHAR(10)&Y27&CHAR(10)&Z27&CHAR(10)&AA27&CHAR(10)&AB27&CHAR(10)&AC27&CHAR(10)&AD27&CHAR(10)&AE27 | L27: =IFERROR(VLOOKUP(#REF!,'第一课直播'!D:L,9,0),IFERROR(VLOOKUP('第一课回放'!C:H,5,0),"未到课")) | M27: =IFERROR(VLOOKUP(#REF!,'第一课回放'!C:H,5,0),"0:00:00") | N27: =IFERROR(VLOOKUP(#REF!,'第二课直播'!D:L,9,0),"未到课") | S27: =IFERROR(VLOOKUP(A27,'微伴数据'!A:DB,12,0),"") | T27: =IFERROR(VLOOKUP(A27,'微伴数据'!A:DB,32,0),"") | U27: =IFERROR(VLOOKUP(A27,'微伴数据'!A:DC,81,0),"") | V27: =IFERROR(VLOOKUP(#REF!,'星橙地址'!A:V,9,0),"") | W27: =IFERROR(VLOOKUP(#REF!,'星橙地址'!A:V,10,0),"") | X27: =IFERROR(VLOOKUP(A27,'星云问卷'!A:O,8,0),"") | Y27: =IFERROR(VLOOKUP(A27,'星云问卷'!A:O,9,0),"") | Z27: =IFERROR(VLOOKUP(A27,'星云问卷'!A:O,10,0),"") | AA27: =IFERROR(VLOOKUP(A27,'星云问卷'!A:O,11,0),"") | AB27: =IFERROR(VLOOKUP(A27,'星云问卷'!A:O,12,0),"") | AC27: =IFERROR(VLOOKUP(A27,'星云问卷'!A:O,13,0),"") | AD27: =IFERROR(VLOOKUP(A27,'星云问卷'!A:O,14,0),"") | AE27: =IFERROR(VLOOKUP(A27,'星云问卷'!A:O,15,0),"") | AF27: =IFERROR(VLOOKUP(A27,'微伴数据'!A:DB,72,0),"") | AG27: 547ug7e2 | AH27: https://xiaobot.net/invitation/a8a86-59098-d48bc-77bfc/ | AI27: 6dj2ZTM8 | AL27: =CONCATENATE( " 我把体验营用户专属福利给你发一下哈：" & CHAR(10) & CHAR(10), "1.《抖音商业IP课》" & CHAR(10), "兑换码：", AG27, CHAR(10), "兑换码使用地址：https://appamvpb5mq9834.h5.xiaoeknow.com/p/t/v1/ecommerce/mkt/redeem_index" & CHAR(10) & CHAR(10), "2.《生财有术66个项目精选》" & CHAR(10), "兑换码：", AH27, CHAR(10), "使用方式：微信搜索小报童投递-点击开始阅读-点击生财有术项目精选即可" & CHAR(10) & CHAR(10), "3.《生财365问》" & CHAR(10), "兑换码：", AI27, CHAR(10), "使用方式：https://appamvpb5mq9834.h5.xiaoeknow.com/p/t/v1/ecommerce/mkt/redeem_index")
A28: =IF('微伴数据'!A25="","",'微伴数据'!A25) | B28: =IF('微伴数据'!B25="","",'微伴数据'!B25) | C28: =IF('微伴数据'!G25="","",'微伴数据'!G25) | D28: =IF('微伴数据'!D25="","",'微伴数据'!D25) | E28: =IF('微伴数据'!CR25="","",'微伴数据'!CR25) | F28: =IF('微伴数据'!CL25="","",'微伴数据'!CL25) | G28: A | H28: 建联 | I28: =VLOOKUP(A28,'Sheet9'!A:A,1,0) | K28: =T28&CHAR(10)&U28&CHAR(10)&V28&CHAR(10)&Y28&CHAR(10)&Z28&CHAR(10)&AA28&CHAR(10)&AB28&CHAR(10)&AC28&CHAR(10)&AD28&CHAR(10)&AE28 | L28: =IFERROR(VLOOKUP(#REF!,'第一课直播'!D:L,9,0),IFERROR(VLOOKUP('第一课回放'!C:H,5,0),"未到课")) | M28: =IFERROR(VLOOKUP(#REF!,'第一课回放'!C:H,5,0),"0:00:00") | N28: =IFERROR(VLOOKUP(#REF!,'第二课直播'!D:L,9,0),"未到课") | S28: =IFERROR(VLOOKUP(A28,'微伴数据'!A:DB,12,0),"") | T28: =IFERROR(VLOOKUP(A28,'微伴数据'!A:DB,32,0),"") | U28: =IFERROR(VLOOKUP(A28,'微伴数据'!A:DC,81,0),"") | V28: =IFERROR(VLOOKUP(#REF!,'星橙地址'!A:V,9,0),"") | W28: =IFERROR(VLOOKUP(#REF!,'星橙地址'!A:V,10,0),"") | X28: =IFERROR(VLOOKUP(A28,'星云问卷'!A:O,8,0),"") | Y28: =IFERROR(VLOOKUP(A28,'星云问卷'!A:O,9,0),"") | Z28: =IFERROR(VLOOKUP(A28,'星云问卷'!A:O,10,0),"") | AA28: =IFERROR(VLOOKUP(A28,'星云问卷'!A:O,11,0),"") | AB28: =IFERROR(VLOOKUP(A28,'星云问卷'!A:O,12,0),"") | AC28: =IFERROR(VLOOKUP(A28,'星云问卷'!A:O,13,0),"") | AD28: =IFERROR(VLOOKUP(A28,'星云问卷'!A:O,14,0),"") | AE28: =IFERROR(VLOOKUP(A28,'星云问卷'!A:O,15,0),"") | AF28: =IFERROR(VLOOKUP(A28,'微伴数据'!A:DB,72,0),"") | AL28: =CONCATENATE( " 我把体验营用户专属福利给你发一下哈：" & CHAR(10) & CHAR(10), "1.《抖音商业IP课》" & CHAR(10), "兑换码：", AG28, CHAR(10), "兑换码使用地址：https://appamvpb5mq9834.h5.xiaoeknow.com/p/t/v1/ecommerce/mkt/redeem_index" & CHAR(10) & CHAR(10), "2.《生财有术66个项目精选》" & CHAR(10), "兑换码：", AH28, CHAR(10), "使用方式：微信搜索小报童投递-点击开始阅读-点击生财有术项目精选即可" & CHAR(10) & CHAR(10), "3.《生财365问》" & CHAR(10), "兑换码：", AI28, CHAR(10), "使用方式：https://appamvpb5mq9834.h5.xiaoeknow.com/p/t/v1/ecommerce/mkt/redeem_index")
A29: =IF('微伴数据'!A26="","",'微伴数据'!A26) | B29: =IF('微伴数据'!B26="","",'微伴数据'!B26) | C29: =IF('微伴数据'!G26="","",'微伴数据'!G26) | D29: =IF('微伴数据'!D26="","",'微伴数据'!D26) | E29: =IF('微伴数据'!CR26="","",'微伴数据'!CR26) | F29: =IF('微伴数据'!CL26="","",'微伴数据'!CL26) | G29: A | H29: 建联 | I29: =VLOOKUP(A29,'Sheet9'!A:A,1,0) | K29: =T29&CHAR(10)&U29&CHAR(10)&V29&CHAR(10)&Y29&CHAR(10)&Z29&CHAR(10)&AA29&CHAR(10)&AB29&CHAR(10)&AC29&CHAR(10)&AD29&CHAR(10)&AE29 | L29: =IFERROR(VLOOKUP(#REF!,'第一课直播'!D:L,9,0),IFERROR(VLOOKUP('第一课回放'!C:H,5,0),"未到课")) | M29: =IFERROR(VLOOKUP(#REF!,'第一课回放'!C:H,5,0),"0:00:00") | N29: =IFERROR(VLOOKUP(#REF!,'第二课直播'!D:L,9,0),"未到课") | S29: =IFERROR(VLOOKUP(A29,'微伴数据'!A:DB,12,0),"") | T29: =IFERROR(VLOOKUP(A29,'微伴数据'!A:DB,32,0),"") | U29: =IFERROR(VLOOKUP(A29,'微伴数据'!A:DC,81,0),"") | V29: =IFERROR(VLOOKUP(#REF!,'星橙地址'!A:V,9,0),"") | W29: =IFERROR(VLOOKUP(#REF!,'星橙地址'!A:V,10,0),"") | X29: =IFERROR(VLOOKUP(A29,'星云问卷'!A:O,8,0),"") | Y29: =IFERROR(VLOOKUP(A29,'星云问卷'!A:O,9,0),"") | Z29: =IFERROR(VLOOKUP(A29,'星云问卷'!A:O,10,0),"") | AA29: =IFERROR(VLOOKUP(A29,'星云问卷'!A:O,11,0),"") | AB29: =IFERROR(VLOOKUP(A29,'星云问卷'!A:O,12,0),"") | AC29: =IFERROR(VLOOKUP(A29,'星云问卷'!A:O,13,0),"") | AD29: =IFERROR(VLOOKUP(A29,'星云问卷'!A:O,14,0),"") | AE29: =IFERROR(VLOOKUP(A29,'星云问卷'!A:O,15,0),"") | AF29: =IFERROR(VLOOKUP(A29,'微伴数据'!A:DB,72,0),"") | AL29: =CONCATENATE( " 我把体验营用户专属福利给你发一下哈：" & CHAR(10) & CHAR(10), "1.《抖音商业IP课》" & CHAR(10), "兑换码：", AG29, CHAR(10), "兑换码使用地址：https://appamvpb5mq9834.h5.xiaoeknow.com/p/t/v1/ecommerce/mkt/redeem_index" & CHAR(10) & CHAR(10), "2.《生财有术66个项目精选》" & CHAR(10), "兑换码：", AH29, CHAR(10), "使用方式：微信搜索小报童投递-点击开始阅读-点击生财有术项目精选即可" & CHAR(10) & CHAR(10), "3.《生财365问》" & CHAR(10), "兑换码：", AI29, CHAR(10), "使用方式：https://appamvpb5mq9834.h5.xiaoeknow.com/p/t/v1/ecommerce/mkt/redeem_index")
A30: =IF('微伴数据'!A27="","",'微伴数据'!A27) | B30: =IF('微伴数据'!B27="","",'微伴数据'!B27) | C30: =IF('微伴数据'!G27="","",'微伴数据'!G27) | D30: =IF('微伴数据'!D27="","",'微伴数据'!D27) | E30: =IF('微伴数据'!CR27="","",'微伴数据'!CR27) | F30: =IF('微伴数据'!CL27="","",'微伴数据'!CL27) | G30: B | H30: 建联 | I30: =VLOOKUP(A30,'Sheet9'!A:A,1,0) | K30: =T30&CHAR(10)&U30&CHAR(10)&V30&CHAR(10)&Y30&CHAR(10)&Z30&CHAR(10)&AA30&CHAR(10)&AB30&CHAR(10)&AC30&CHAR(10)&AD30&CHAR(10)&AE30 | L30: =IFERROR(VLOOKUP(#REF!,'第一课直播'!D:L,9,0),IFERROR(VLOOKUP('第一课回放'!C:H,5,0),"未到课")) | M30: =IFERROR(VLOOKUP(#REF!,'第一课回放'!C:H,5,0),"0:00:00") | N30: =IFERROR(VLOOKUP(#REF!,'第二课直播'!D:L,9,0),"未到课") | S30: =IFERROR(VLOOKUP(A30,'微伴数据'!A:DB,12,0),"") | T30: =IFERROR(VLOOKUP(A30,'微伴数据'!A:DB,32,0),"") | U30: =IFERROR(VLOOKUP(A30,'微伴数据'!A:DC,81,0),"") | V30: =IFERROR(VLOOKUP(#REF!,'星橙地址'!A:V,9,0),"") | W30: =IFERROR(VLOOKUP(#REF!,'星橙地址'!A:V,10,0),"") | X30: =IFERROR(VLOOKUP(A30,'星云问卷'!A:O,8,0),"") | Y30: =IFERROR(VLOOKUP(A30,'星云问卷'!A:O,9,0),"") | Z30: =IFERROR(VLOOKUP(A30,'星云问卷'!A:O,10,0),"") | AA30: =IFERROR(VLOOKUP(A30,'星云问卷'!A:O,11,0),"") | AB30: =IFERROR(VLOOKUP(A30,'星云问卷'!A:O,12,0),"") | AC30: =IFERROR(VLOOKUP(A30,'星云问卷'!A:O,13,0),"") | AD30: =IFERROR(VLOOKUP(A30,'星云问卷'!A:O,14,0),"") | AE30: =IFERROR(VLOOKUP(A30,'星云问卷'!A:O,15,0),"") | AF30: =IFERROR(VLOOKUP(A30,'微伴数据'!A:DB,72,0),"") | AL30: =CONCATENATE( " 我把体验营用户专属福利给你发一下哈：" & CHAR(10) & CHAR(10), "1.《抖音商业IP课》" & CHAR(10), "兑换码：", AG30, CHAR(10), "兑换码使用地址：https://appamvpb5mq9834.h5.xiaoeknow.com/p/t/v1/ecommerce/mkt/redeem_index" & CHAR(10) & CHAR(10), "2.《生财有术66个项目精选》" & CHAR(10), "兑换码：", AH30, CHAR(10), "使用方式：微信搜索小报童投递-点击开始阅读-点击生财有术项目精选即可" & CHAR(10) & CHAR(10), "3.《生财365问》" & CHAR(10), "兑换码：", AI30, CHAR(10), "使用方式：https://appamvpb5mq9834.h5.xiaoeknow.com/p/t/v1/ecommerce/mkt/redeem_index")
A31: =IF('微伴数据'!A28="","",'微伴数据'!A28) | B31: =IF('微伴数据'!B28="","",'微伴数据'!B28) | C31: =IF('微伴数据'!G28="","",'微伴数据'!G28) | D31: =IF('微伴数据'!D28="","",'微伴数据'!D28) | E31: =IF('微伴数据'!CR28="","",'微伴数据'!CR28) | F31: =IF('微伴数据'!CL28="","",'微伴数据'!CL28) | G31: B | H31: 建联 | I31: =VLOOKUP(A31,'Sheet9'!A:A,1,0) | K31: =T31&CHAR(10)&U31&CHAR(10)&V31&CHAR(10)&Y31&CHAR(10)&Z31&CHAR(10)&AA31&CHAR(10)&AB31&CHAR(10)&AC31&CHAR(10)&AD31&CHAR(10)&AE31 | L31: =IFERROR(VLOOKUP(#REF!,'第一课直播'!D:L,9,0),IFERROR(VLOOKUP('第一课回放'!C:H,5,0),"未到课")) | M31: =IFERROR(VLOOKUP(#REF!,'第一课回放'!C:H,5,0),"0:00:00") | N31: =IFERROR(VLOOKUP(#REF!,'第二课直播'!D:L,9,0),"未到课") | S31: =IFERROR(VLOOKUP(A31,'微伴数据'!A:DB,12,0),"") | T31: =IFERROR(VLOOKUP(A31,'微伴数据'!A:DB,32,0),"") | U31: =IFERROR(VLOOKUP(A31,'微伴数据'!A:DC,81,0),"") | V31: =IFERROR(VLOOKUP(#REF!,'星橙地址'!A:V,9,0),"") | W31: =IFERROR(VLOOKUP(#REF!,'星橙地址'!A:V,10,0),"") | X31: =IFERROR(VLOOKUP(A31,'星云问卷'!A:O,8,0),"") | Y31: =IFERROR(VLOOKUP(A31,'星云问卷'!A:O,9,0),"") | Z31: =IFERROR(VLOOKUP(A31,'星云问卷'!A:O,10,0),"") | AA31: =IFERROR(VLOOKUP(A31,'星云问卷'!A:O,11,0),"") | AB31: =IFERROR(VLOOKUP(A31,'星云问卷'!A:O,12,0),"") | AC31: =IFERROR(VLOOKUP(A31,'星云问卷'!A:O,13,0),"") | AD31: =IFERROR(VLOOKUP(A31,'星云问卷'!A:O,14,0),"") | AE31: =IFERROR(VLOOKUP(A31,'星云问卷'!A:O,15,0),"") | AF31: =IFERROR(VLOOKUP(A31,'微伴数据'!A:DB,72,0),"") | AL31: =CONCATENATE( " 我把体验营用户专属福利给你发一下哈：" & CHAR(10) & CHAR(10), "1.《抖音商业IP课》" & CHAR(10), "兑换码：", AG31, CHAR(10), "兑换码使用地址：https://appamvpb5mq9834.h5.xiaoeknow.com/p/t/v1/ecommerce/mkt/redeem_index" & CHAR(10) & CHAR(10), "2.《生财有术66个项目精选》" & CHAR(10), "兑换码：", AH31, CHAR(10), "使用方式：微信搜索小报童投递-点击开始阅读-点击生财有术项目精选即可" & CHAR(10) & CHAR(10), "3.《生财365问》" & CHAR(10), "兑换码：", AI31, CHAR(10), "使用方式：https://appamvpb5mq9834.h5.xiaoeknow.com/p/t/v1/ecommerce/mkt/redeem_index")
A32: =IF('微伴数据'!A29="","",'微伴数据'!A29) | B32: =IF('微伴数据'!B29="","",'微伴数据'!B29) | C32: =IF('微伴数据'!G29="","",'微伴数据'!G29) | D32: =IF('微伴数据'!D29="","",'微伴数据'!D29) | E32: =IF('微伴数据'!CR29="","",'微伴数据'!CR29) | F32: =IF('微伴数据'!CL29="","",'微伴数据'!CL29) | G32: B | H32: 建联 | I32: =VLOOKUP(A32,'Sheet9'!A:A,1,0) | K32: =T32&CHAR(10)&U32&CHAR(10)&V32&CHAR(10)&Y32&CHAR(10)&Z32&CHAR(10)&AA32&CHAR(10)&AB32&CHAR(10)&AC32&CHAR(10)&AD32&CHAR(10)&AE32 | L32: =IFERROR(VLOOKUP(#REF!,'第一课直播'!D:L,9,0),IFERROR(VLOOKUP('第一课回放'!C:H,5,0),"未到课")) | M32: =IFERROR(VLOOKUP(#REF!,'第一课回放'!C:H,5,0),"0:00:00") | N32: =IFERROR(VLOOKUP(#REF!,'第二课直播'!D:L,9,0),"未到课") | S32: =IFERROR(VLOOKUP(A32,'微伴数据'!A:DB,12,0),"") | T32: =IFERROR(VLOOKUP(A32,'微伴数据'!A:DB,32,0),"") | U32: =IFERROR(VLOOKUP(A32,'微伴数据'!A:DC,81,0),"") | V32: =IFERROR(VLOOKUP(#REF!,'星橙地址'!A:V,9,0),"") | W32: =IFERROR(VLOOKUP(#REF!,'星橙地址'!A:V,10,0),"") | X32: =IFERROR(VLOOKUP(A32,'星云问卷'!A:O,8,0),"") | Y32: =IFERROR(VLOOKUP(A32,'星云问卷'!A:O,9,0),"") | Z32: =IFERROR(VLOOKUP(A32,'星云问卷'!A:O,10,0),"") | AA32: =IFERROR(VLOOKUP(A32,'星云问卷'!A:O,11,0),"") | AB32: =IFERROR(VLOOKUP(A32,'星云问卷'!A:O,12,0),"") | AC32: =IFERROR(VLOOKUP(A32,'星云问卷'!A:O,13,0),"") | AD32: =IFERROR(VLOOKUP(A32,'星云问卷'!A:O,14,0),"") | AE32: =IFERROR(VLOOKUP(A32,'星云问卷'!A:O,15,0),"") | AF32: =IFERROR(VLOOKUP(A32,'微伴数据'!A:DB,72,0),"") | AH32: https://xiaobot.net/invitation/ce769-b9f3f-3088d-544df/ | AI32: 6dfrXujW | AL32: =CONCATENATE( " 我把体验营用户专属福利给你发一下哈：" & CHAR(10) & CHAR(10), "1.《抖音商业IP课》" & CHAR(10), "兑换码：", AG32, CHAR(10), "兑换码使用地址：https://appamvpb5mq9834.h5.xiaoeknow.com/p/t/v1/ecommerce/mkt/redeem_index" & CHAR(10) & CHAR(10), "2.《生财有术66个项目精选》" & CHAR(10), "兑换码：", AH32, CHAR(10), "使用方式：微信搜索小报童投递-点击开始阅读-点击生财有术项目精选即可" & CHAR(10) & CHAR(10), "3.《生财365问》" & CHAR(10), "兑换码：", AI32, CHAR(10), "使用方式：https://appamvpb5mq9834.h5.xiaoeknow.com/p/t/v1/ecommerce/mkt/redeem_index") | AO32: 纳入用户画像
A33: =IF('微伴数据'!A30="","",'微伴数据'!A30) | B33: =IF('微伴数据'!B30="","",'微伴数据'!B30) | C33: =IF('微伴数据'!G30="","",'微伴数据'!G30) | D33: =IF('微伴数据'!D30="","",'微伴数据'!D30) | E33: =IF('微伴数据'!CR30="","",'微伴数据'!CR30) | F33: =IF('微伴数据'!CL30="","",'微伴数据'!CL30) | G33: A | H33: 建联 | I33: =VLOOKUP(A33,'Sheet9'!A:A,1,0) | K33: =T33&CHAR(10)&U33&CHAR(10)&V33&CHAR(10)&Y33&CHAR(10)&Z33&CHAR(10)&AA33&CHAR(10)&AB33&CHAR(10)&AC33&CHAR(10)&AD33&CHAR(10)&AE33 | L33: =IFERROR(VLOOKUP(#REF!,'第一课直播'!D:L,9,0),IFERROR(VLOOKUP('第一课回放'!C:H,5,0),"未到课")) | M33: =IFERROR(VLOOKUP(#REF!,'第一课回放'!C:H,5,0),"0:00:00") | N33: =IFERROR(VLOOKUP(#REF!,'第二课直播'!D:L,9,0),"未到课") | S33: =IFERROR(VLOOKUP(A33,'微伴数据'!A:DB,12,0),"") | T33: =IFERROR(VLOOKUP(A33,'微伴数据'!A:DB,32,0),"") | U33: =IFERROR(VLOOKUP(A33,'微伴数据'!A:DC,81,0),"") | V33: =IFERROR(VLOOKUP(#REF!,'星橙地址'!A:V,9,0),"") | W33: =IFERROR(VLOOKUP(#REF!,'星橙地址'!A:V,10,0),"") | X33: =IFERROR(VLOOKUP(A33,'星云问卷'!A:O,8,0),"") | Y33: =IFERROR(VLOOKUP(A33,'星云问卷'!A:O,9,0),"") | Z33: =IFERROR(VLOOKUP(A33,'星云问卷'!A:O,10,0),"") | AA33: =IFERROR(VLOOKUP(A33,'星云问卷'!A:O,11,0),"") | AB33: =IFERROR(VLOOKUP(A33,'星云问卷'!A:O,12,0),"") | AC33: =IFERROR(VLOOKUP(A33,'星云问卷'!A:O,13,0),"") | AD33: =IFERROR(VLOOKUP(A33,'星云问卷'!A:O,14,0),"") | AE33: =IFERROR(VLOOKUP(A33,'星云问卷'!A:O,15,0),"") | AF33: =IFERROR(VLOOKUP(A33,'微伴数据'!A:DB,72,0),"") | AL33: =CONCATENATE( " 我把体验营用户专属福利给你发一下哈：" & CHAR(10) & CHAR(10), "1.《抖音商业IP课》" & CHAR(10), "兑换码：", AG33, CHAR(10), "兑换码使用地址：https://appamvpb5mq9834.h5.xiaoeknow.com/p/t/v1/ecommerce/mkt/redeem_index" & CHAR(10) & CHAR(10), "2.《生财有术66个项目精选》" & CHAR(10), "兑换码：", AH33, CHAR(10), "使用方式：微信搜索小报童投递-点击开始阅读-点击生财有术项目精选即可" & CHAR(10) & CHAR(10), "3.《生财365问》" & CHAR(10), "兑换码：", AI33, CHAR(10), "使用方式：https://appamvpb5mq9834.h5.xiaoeknow.com/p/t/v1/ecommerce/mkt/redeem_index")
A34: =IF('微伴数据'!A31="","",'微伴数据'!A31) | B34: =IF('微伴数据'!B31="","",'微伴数据'!B31) | C34: =IF('微伴数据'!G31="","",'微伴数据'!G31) | D34: =IF('微伴数据'!D31="","",'微伴数据'!D31) | E34: =IF('微伴数据'!CR31="","",'微伴数据'!CR31) | F34: =IF('微伴数据'!CL31="","",'微伴数据'!CL31) | G34: B | H34: 建联 | I34: =VLOOKUP(A34,'Sheet9'!A:A,1,0) | K34: =T34&CHAR(10)&U34&CHAR(10)&V34&CHAR(10)&Y34&CHAR(10)&Z34&CHAR(10)&AA34&CHAR(10)&AB34&CHAR(10)&AC34&CHAR(10)&AD34&CHAR(10)&AE34 | L34: =IFERROR(VLOOKUP(#REF!,'第一课直播'!D:L,9,0),IFERROR(VLOOKUP('第一课回放'!C:H,5,0),"未到课")) | M34: =IFERROR(VLOOKUP(#REF!,'第一课回放'!C:H,5,0),"0:00:00") | N34: =IFERROR(VLOOKUP(#REF!,'第二课直播'!D:L,9,0),"未到课") | S34: =IFERROR(VLOOKUP(A34,'微伴数据'!A:DB,12,0),"") | T34: =IFERROR(VLOOKUP(A34,'微伴数据'!A:DB,32,0),"") | U34: =IFERROR(VLOOKUP(A34,'微伴数据'!A:DC,81,0),"") | V34: =IFERROR(VLOOKUP(#REF!,'星橙地址'!A:V,9,0),"") | W34: =IFERROR(VLOOKUP(#REF!,'星橙地址'!A:V,10,0),"") | X34: =IFERROR(VLOOKUP(A34,'星云问卷'!A:O,8,0),"") | Y34: =IFERROR(VLOOKUP(A34,'星云问卷'!A:O,9,0),"") | Z34: =IFERROR(VLOOKUP(A34,'星云问卷'!A:O,10,0),"") | AA34: =IFERROR(VLOOKUP(A34,'星云问卷'!A:O,11,0),"") | AB34: =IFERROR(VLOOKUP(A34,'星云问卷'!A:O,12,0),"") | AC34: =IFERROR(VLOOKUP(A34,'星云问卷'!A:O,13,0),"") | AD34: =IFERROR(VLOOKUP(A34,'星云问卷'!A:O,14,0),"") | AE34: =IFERROR(VLOOKUP(A34,'星云问卷'!A:O,15,0),"") | AF34: =IFERROR(VLOOKUP(A34,'微伴数据'!A:DB,72,0),"") | AL34: =CONCATENATE( " 我把体验营用户专属福利给你发一下哈：" & CHAR(10) & CHAR(10), "1.《抖音商业IP课》" & CHAR(10), "兑换码：", AG34, CHAR(10), "兑换码使用地址：https://appamvpb5mq9834.h5.xiaoeknow.com/p/t/v1/ecommerce/mkt/redeem_index" & CHAR(10) & CHAR(10), "2.《生财有术66个项目精选》" & CHAR(10), "兑换码：", AH34, CHAR(10), "使用方式：微信搜索小报童投递-点击开始阅读-点击生财有术项目精选即可" & CHAR(10) & CHAR(10), "3.《生财365问》" & CHAR(10), "兑换码：", AI34, CHAR(10), "使用方式：https://appamvpb5mq9834.h5.xiaoeknow.com/p/t/v1/ecommerce/mkt/redeem_index")
A35: =IF('微伴数据'!A32="","",'微伴数据'!A32) | B35: =IF('微伴数据'!B32="","",'微伴数据'!B32) | C35: =IF('微伴数据'!G32="","",'微伴数据'!G32) | D35: =IF('微伴数据'!D32="","",'微伴数据'!D32) | E35: =IF('微伴数据'!CR32="","",'微伴数据'!CR32) | F35: =IF('微伴数据'!CL32="","",'微伴数据'!CL32) | G35: B | H35: 建联 | I35: =VLOOKUP(A35,'Sheet9'!A:A,1,0) | K35: =T35&CHAR(10)&U35&CHAR(10)&V35&CHAR(10)&Y35&CHAR(10)&Z35&CHAR(10)&AA35&CHAR(10)&AB35&CHAR(10)&AC35&CHAR(10)&AD35&CHAR(10)&AE35 | L35: =IFERROR(VLOOKUP(#REF!,'第一课直播'!D:L,9,0),IFERROR(VLOOKUP('第一课回放'!C:H,5,0),"未到课")) | M35: =IFERROR(VLOOKUP(#REF!,'第一课回放'!C:H,5,0),"0:00:00") | N35: =IFERROR(VLOOKUP(#REF!,'第二课直播'!D:L,9,0),"未到课") | S35: =IFERROR(VLOOKUP(A35,'微伴数据'!A:DB,12,0),"") | T35: =IFERROR(VLOOKUP(A35,'微伴数据'!A:DB,32,0),"") | U35: =IFERROR(VLOOKUP(A35,'微伴数据'!A:DC,81,0),"") | V35: =IFERROR(VLOOKUP(#REF!,'星橙地址'!A:V,9,0),"") | W35: =IFERROR(VLOOKUP(#REF!,'星橙地址'!A:V,10,0),"") | X35: =IFERROR(VLOOKUP(A35,'星云问卷'!A:O,8,0),"") | Y35: =IFERROR(VLOOKUP(A35,'星云问卷'!A:O,9,0),"") | Z35: =IFERROR(VLOOKUP(A35,'星云问卷'!A:O,10,0),"") | AA35: =IFERROR(VLOOKUP(A35,'星云问卷'!A:O,11,0),"") | AB35: =IFERROR(VLOOKUP(A35,'星云问卷'!A:O,12,0),"") | AC35: =IFERROR(VLOOKUP(A35,'星云问卷'!A:O,13,0),"") | AD35: =IFERROR(VLOOKUP(A35,'星云问卷'!A:O,14,0),"") | AE35: =IFERROR(VLOOKUP(A35,'星云问卷'!A:O,15,0),"") | AF35: =IFERROR(VLOOKUP(A35,'微伴数据'!A:DB,72,0),"") | AG35: 547WKxS6 | AH35: https://xiaobot.net/invitation/6d594-8c7c9-8ba02-f2c1d/ | AI35: 6dh4zc9X | AL35: =CONCATENATE( " 我把体验营用户专属福利给你发一下哈：" & CHAR(10) & CHAR(10), "1.《抖音商业IP课》" & CHAR(10), "兑换码：", AG35, CHAR(10), "兑换码使用地址：https://appamvpb5mq9834.h5.xiaoeknow.com/p/t/v1/ecommerce/mkt/redeem_index" & CHAR(10) & CHAR(10), "2.《生财有术66个项目精选》" & CHAR(10), "兑换码：", AH35, CHAR(10), "使用方式：微信搜索小报童投递-点击开始阅读-点击生财有术项目精选即可" & CHAR(10) & CHAR(10), "3.《生财365问》" & CHAR(10), "兑换码：", AI35, CHAR(10), "使用方式：https://appamvpb5mq9834.h5.xiaoeknow.com/p/t/v1/ecommerce/mkt/redeem_index")
A36: =IF('微伴数据'!A33="","",'微伴数据'!A33) | B36: =IF('微伴数据'!B33="","",'微伴数据'!B33) | C36: =IF('微伴数据'!G33="","",'微伴数据'!G33) | D36: =IF('微伴数据'!D33="","",'微伴数据'!D33) | E36: =IF('微伴数据'!CR33="","",'微伴数据'!CR33) | F36: =IF('微伴数据'!CL33="","",'微伴数据'!CL33) | G36: A | H36: 已成交 | I36: =VLOOKUP(A36,'Sheet9'!A:A,1,0) | K36: =T36&CHAR(10)&U36&CHAR(10)&V36&CHAR(10)&Y36&CHAR(10)&Z36&CHAR(10)&AA36&CHAR(10)&AB36&CHAR(10)&AC36&CHAR(10)&AD36&CHAR(10)&AE36 | L36: =IFERROR(VLOOKUP(#REF!,'第一课直播'!D:L,9,0),IFERROR(VLOOKUP('第一课回放'!C:H,5,0),"未到课")) | M36: =IFERROR(VLOOKUP(#REF!,'第一课回放'!C:H,5,0),"0:00:00") | N36: =IFERROR(VLOOKUP(#REF!,'第二课直播'!D:L,9,0),"未到课") | S36: =IFERROR(VLOOKUP(A36,'微伴数据'!A:DB,12,0),"") | T36: =IFERROR(VLOOKUP(A36,'微伴数据'!A:DB,32,0),"") | U36: =IFERROR(VLOOKUP(A36,'微伴数据'!A:DC,81,0),"") | V36: =IFERROR(VLOOKUP(#REF!,'星橙地址'!A:V,9,0),"") | W36: =IFERROR(VLOOKUP(#REF!,'星橙地址'!A:V,10,0),"") | X36: =IFERROR(VLOOKUP(A36,'星云问卷'!A:O,8,0),"") | Y36: =IFERROR(VLOOKUP(A36,'星云问卷'!A:O,9,0),"") | Z36: =IFERROR(VLOOKUP(A36,'星云问卷'!A:O,10,0),"") | AA36: =IFERROR(VLOOKUP(A36,'星云问卷'!A:O,11,0),"") | AB36: =IFERROR(VLOOKUP(A36,'星云问卷'!A:O,12,0),"") | AC36: =IFERROR(VLOOKUP(A36,'星云问卷'!A:O,13,0),"") | AD36: =IFERROR(VLOOKUP(A36,'星云问卷'!A:O,14,0),"") | AE36: =IFERROR(VLOOKUP(A36,'星云问卷'!A:O,15,0),"") | AF36: =IFERROR(VLOOKUP(A36,'微伴数据'!A:DB,72,0),"") | AG36: 54DD2gU3 | AH36: https://xiaobot.net/invitation/9f74d-7582d-266ae-c2b1c | AI36: 6dvEDdSr | AL36: =CONCATENATE( " 我把体验营用户专属福利给你发一下哈：" & CHAR(10) & CHAR(10), "1.《抖音商业IP课》" & CHAR(10), "兑换码：", AG36, CHAR(10), "兑换码使用地址：https://appamvpb5mq9834.h5.xiaoeknow.com/p/t/v1/ecommerce/mkt/redeem_index" & CHAR(10) & CHAR(10), "2.《生财有术66个项目精选》" & CHAR(10), "兑换码：", AH36, CHAR(10), "使用方式：微信搜索小报童投递-点击开始阅读-点击生财有术项目精选即可" & CHAR(10) & CHAR(10), "3.《生财365问》" & CHAR(10), "兑换码：", AI36, CHAR(10), "使用方式：https://appamvpb5mq9834.h5.xiaoeknow.com/p/t/v1/ecommerce/mkt/redeem_index")
A37: =IF('微伴数据'!A34="","",'微伴数据'!A34) | B37: =IF('微伴数据'!B34="","",'微伴数据'!B34) | C37: =IF('微伴数据'!G34="","",'微伴数据'!G34) | D37: =IF('微伴数据'!D34="","",'微伴数据'!D34) | E37: =IF('微伴数据'!CR34="","",'微伴数据'!CR34) | F37: =IF('微伴数据'!CL34="","",'微伴数据'!CL34) | G37: A | H37: 建联 | I37: =VLOOKUP(A37,'Sheet9'!A:A,1,0) | K37: =T37&CHAR(10)&U37&CHAR(10)&V37&CHAR(10)&Y37&CHAR(10)&Z37&CHAR(10)&AA37&CHAR(10)&AB37&CHAR(10)&AC37&CHAR(10)&AD37&CHAR(10)&AE37 | L37: =IFERROR(VLOOKUP(#REF!,'第一课直播'!D:L,9,0),IFERROR(VLOOKUP('第一课回放'!C:H,5,0),"未到课")) | M37: =IFERROR(VLOOKUP(#REF!,'第一课回放'!C:H,5,0),"0:00:00") | N37: =IFERROR(VLOOKUP(#REF!,'第二课直播'!D:L,9,0),"未到课") | S37: =IFERROR(VLOOKUP(A37,'微伴数据'!A:DB,12,0),"") | T37: =IFERROR(VLOOKUP(A37,'微伴数据'!A:DB,32,0),"") | U37: =IFERROR(VLOOKUP(A37,'微伴数据'!A:DC,81,0),"") | V37: =IFERROR(VLOOKUP(#REF!,'星橙地址'!A:V,9,0),"") | W37: =IFERROR(VLOOKUP(#REF!,'星橙地址'!A:V,10,0),"") | X37: =IFERROR(VLOOKUP(A37,'星云问卷'!A:O,8,0),"") | Y37: =IFERROR(VLOOKUP(A37,'星云问卷'!A:O,9,0),"") | Z37: =IFERROR(VLOOKUP(A37,'星云问卷'!A:O,10,0),"") | AA37: =IFERROR(VLOOKUP(A37,'星云问卷'!A:O,11,0),"") | AB37: =IFERROR(VLOOKUP(A37,'星云问卷'!A:O,12,0),"") | AC37: =IFERROR(VLOOKUP(A37,'星云问卷'!A:O,13,0),"") | AD37: =IFERROR(VLOOKUP(A37,'星云问卷'!A:O,14,0),"") | AE37: =IFERROR(VLOOKUP(A37,'星云问卷'!A:O,15,0),"") | AF37: =IFERROR(VLOOKUP(A37,'微伴数据'!A:DB,72,0),"") | AL37: =CONCATENATE( " 我把体验营用户专属福利给你发一下哈：" & CHAR(10) & CHAR(10), "1.《抖音商业IP课》" & CHAR(10), "兑换码：", AG37, CHAR(10), "兑换码使用地址：https://appamvpb5mq9834.h5.xiaoeknow.com/p/t/v1/ecommerce/mkt/redeem_index" & CHAR(10) & CHAR(10), "2.《生财有术66个项目精选》" & CHAR(10), "兑换码：", AH37, CHAR(10), "使用方式：微信搜索小报童投递-点击开始阅读-点击生财有术项目精选即可" & CHAR(10) & CHAR(10), "3.《生财365问》" & CHAR(10), "兑换码：", AI37, CHAR(10), "使用方式：https://appamvpb5mq9834.h5.xiaoeknow.com/p/t/v1/ecommerce/mkt/redeem_index")
A38: =IF('微伴数据'!A35="","",'微伴数据'!A35) | B38: =IF('微伴数据'!B35="","",'微伴数据'!B35) | C38: =IF('微伴数据'!G35="","",'微伴数据'!G35) | D38: =IF('微伴数据'!D35="","",'微伴数据'!D35) | E38: =IF('微伴数据'!CR35="","",'微伴数据'!CR35) | F38: =IF('微伴数据'!CL35="","",'微伴数据'!CL35) | G38: B | H38: 建联 | I38: =VLOOKUP(A38,'Sheet9'!A:A,1,0) | K38: =T38&CHAR(10)&U38&CHAR(10)&V38&CHAR(10)&Y38&CHAR(10)&Z38&CHAR(10)&AA38&CHAR(10)&AB38&CHAR(10)&AC38&CHAR(10)&AD38&CHAR(10)&AE38 | L38: =IFERROR(VLOOKUP(#REF!,'第一课直播'!D:L,9,0),IFERROR(VLOOKUP('第一课回放'!C:H,5,0),"未到课")) | M38: =IFERROR(VLOOKUP(#REF!,'第一课回放'!C:H,5,0),"0:00:00") | N38: =IFERROR(VLOOKUP(#REF!,'第二课直播'!D:L,9,0),"未到课") | S38: =IFERROR(VLOOKUP(A38,'微伴数据'!A:DB,12,0),"") | T38: =IFERROR(VLOOKUP(A38,'微伴数据'!A:DB,32,0),"") | U38: =IFERROR(VLOOKUP(A38,'微伴数据'!A:DC,81,0),"") | V38: =IFERROR(VLOOKUP(#REF!,'星橙地址'!A:V,9,0),"") | W38: =IFERROR(VLOOKUP(#REF!,'星橙地址'!A:V,10,0),"") | X38: =IFERROR(VLOOKUP(A38,'星云问卷'!A:O,8,0),"") | Y38: =IFERROR(VLOOKUP(A38,'星云问卷'!A:O,9,0),"") | Z38: =IFERROR(VLOOKUP(A38,'星云问卷'!A:O,10,0),"") | AA38: =IFERROR(VLOOKUP(A38,'星云问卷'!A:O,11,0),"") | AB38: =IFERROR(VLOOKUP(A38,'星云问卷'!A:O,12,0),"") | AC38: =IFERROR(VLOOKUP(A38,'星云问卷'!A:O,13,0),"") | AD38: =IFERROR(VLOOKUP(A38,'星云问卷'!A:O,14,0),"") | AE38: =IFERROR(VLOOKUP(A38,'星云问卷'!A:O,15,0),"") | AF38: =IFERROR(VLOOKUP(A38,'微伴数据'!A:DB,72,0),"") | AL38: =CONCATENATE( " 我把体验营用户专属福利给你发一下哈：" & CHAR(10) & CHAR(10), "1.《抖音商业IP课》" & CHAR(10), "兑换码：", AG38, CHAR(10), "兑换码使用地址：https://appamvpb5mq9834.h5.xiaoeknow.com/p/t/v1/ecommerce/mkt/redeem_index" & CHAR(10) & CHAR(10), "2.《生财有术66个项目精选》" & CHAR(10), "兑换码：", AH38, CHAR(10), "使用方式：微信搜索小报童投递-点击开始阅读-点击生财有术项目精选即可" & CHAR(10) & CHAR(10), "3.《生财365问》" & CHAR(10), "兑换码：", AI38, CHAR(10), "使用方式：https://appamvpb5mq9834.h5.xiaoeknow.com/p/t/v1/ecommerce/mkt/redeem_index")
A39: =IF('微伴数据'!A36="","",'微伴数据'!A36) | B39: =IF('微伴数据'!B36="","",'微伴数据'!B36) | C39: =IF('微伴数据'!G36="","",'微伴数据'!G36) | D39: =IF('微伴数据'!D36="","",'微伴数据'!D36) | E39: =IF('微伴数据'!CR36="","",'微伴数据'!CR36) | F39: =IF('微伴数据'!CL36="","",'微伴数据'!CL36) | G39: B | H39: 建联 | I39: =VLOOKUP(A39,'Sheet9'!A:A,1,0) | K39: =T39&CHAR(10)&U39&CHAR(10)&V39&CHAR(10)&Y39&CHAR(10)&Z39&CHAR(10)&AA39&CHAR(10)&AB39&CHAR(10)&AC39&CHAR(10)&AD39&CHAR(10)&AE39 | L39: =IFERROR(VLOOKUP(#REF!,'第一课直播'!D:L,9,0),IFERROR(VLOOKUP('第一课回放'!C:H,5,0),"未到课")) | M39: =IFERROR(VLOOKUP(#REF!,'第一课回放'!C:H,5,0),"0:00:00") | N39: =IFERROR(VLOOKUP(#REF!,'第二课直播'!D:L,9,0),"未到课") | S39: =IFERROR(VLOOKUP(A39,'微伴数据'!A:DB,12,0),"") | T39: =IFERROR(VLOOKUP(A39,'微伴数据'!A:DB,32,0),"") | U39: =IFERROR(VLOOKUP(A39,'微伴数据'!A:DC,81,0),"") | V39: =IFERROR(VLOOKUP(#REF!,'星橙地址'!A:V,9,0),"") | W39: =IFERROR(VLOOKUP(#REF!,'星橙地址'!A:V,10,0),"") | X39: =IFERROR(VLOOKUP(A39,'星云问卷'!A:O,8,0),"") | Y39: =IFERROR(VLOOKUP(A39,'星云问卷'!A:O,9,0),"") | Z39: =IFERROR(VLOOKUP(A39,'星云问卷'!A:O,10,0),"") | AA39: =IFERROR(VLOOKUP(A39,'星云问卷'!A:O,11,0),"") | AB39: =IFERROR(VLOOKUP(A39,'星云问卷'!A:O,12,0),"") | AC39: =IFERROR(VLOOKUP(A39,'星云问卷'!A:O,13,0),"") | AD39: =IFERROR(VLOOKUP(A39,'星云问卷'!A:O,14,0),"") | AE39: =IFERROR(VLOOKUP(A39,'星云问卷'!A:O,15,0),"") | AF39: =IFERROR(VLOOKUP(A39,'微伴数据'!A:DB,72,0),"") | AL39: =CONCATENATE( " 我把体验营用户专属福利给你发一下哈：" & CHAR(10) & CHAR(10), "1.《抖音商业IP课》" & CHAR(10), "兑换码：", AG39, CHAR(10), "兑换码使用地址：https://appamvpb5mq9834.h5.xiaoeknow.com/p/t/v1/ecommerce/mkt/redeem_index" & CHAR(10) & CHAR(10), "2.《生财有术66个项目精选》" & CHAR(10), "兑换码：", AH39, CHAR(10), "使用方式：微信搜索小报童投递-点击开始阅读-点击生财有术项目精选即可" & CHAR(10) & CHAR(10), "3.《生财365问》" & CHAR(10), "兑换码：", AI39, CHAR(10), "使用方式：https://appamvpb5mq9834.h5.xiaoeknow.com/p/t/v1/ecommerce/mkt/redeem_index")
A40: =IF('微伴数据'!A37="","",'微伴数据'!A37) | B40: =IF('微伴数据'!B37="","",'微伴数据'!B37) | C40: =IF('微伴数据'!G37="","",'微伴数据'!G37) | D40: =IF('微伴数据'!D37="","",'微伴数据'!D37) | E40: =IF('微伴数据'!CR37="","",'微伴数据'!CR37) | F40: =IF('微伴数据'!CL37="","",'微伴数据'!CL37) | G40: B | H40: 建联 | I40: =VLOOKUP(A40,'Sheet9'!A:A,1,0) | K40: =T40&CHAR(10)&U40&CHAR(10)&V40&CHAR(10)&Y40&CHAR(10)&Z40&CHAR(10)&AA40&CHAR(10)&AB40&CHAR(10)&AC40&CHAR(10)&AD40&CHAR(10)&AE40 | L40: =IFERROR(VLOOKUP(#REF!,'第一课直播'!D:L,9,0),IFERROR(VLOOKUP('第一课回放'!C:H,5,0),"未到课")) | M40: =IFERROR(VLOOKUP(#REF!,'第一课回放'!C:H,5,0),"0:00:00") | N40: =IFERROR(VLOOKUP(#REF!,'第二课直播'!D:L,9,0),"未到课") | S40: =IFERROR(VLOOKUP(A40,'微伴数据'!A:DB,12,0),"") | T40: =IFERROR(VLOOKUP(A40,'微伴数据'!A:DB,32,0),"") | U40: =IFERROR(VLOOKUP(A40,'微伴数据'!A:DC,81,0),"") | V40: =IFERROR(VLOOKUP(#REF!,'星橙地址'!A:V,9,0),"") | W40: =IFERROR(VLOOKUP(#REF!,'星橙地址'!A:V,10,0),"") | X40: =IFERROR(VLOOKUP(A40,'星云问卷'!A:O,8,0),"") | Y40: =IFERROR(VLOOKUP(A40,'星云问卷'!A:O,9,0),"") | Z40: =IFERROR(VLOOKUP(A40,'星云问卷'!A:O,10,0),"") | AA40: =IFERROR(VLOOKUP(A40,'星云问卷'!A:O,11,0),"") | AB40: =IFERROR(VLOOKUP(A40,'星云问卷'!A:O,12,0),"") | AC40: =IFERROR(VLOOKUP(A40,'星云问卷'!A:O,13,0),"") | AD40: =IFERROR(VLOOKUP(A40,'星云问卷'!A:O,14,0),"") | AE40: =IFERROR(VLOOKUP(A40,'星云问卷'!A:O,15,0),"") | AF40: =IFERROR(VLOOKUP(A40,'微伴数据'!A:DB,72,0),"") | AL40: =CONCATENATE( " 我把体验营用户专属福利给你发一下哈：" & CHAR(10) & CHAR(10), "1.《抖音商业IP课》" & CHAR(10), "兑换码：", AG40, CHAR(10), "兑换码使用地址：https://appamvpb5mq9834.h5.xiaoeknow.com/p/t/v1/ecommerce/mkt/redeem_index" & CHAR(10) & CHAR(10), "2.《生财有术66个项目精选》" & CHAR(10), "兑换码：", AH40, CHAR(10), "使用方式：微信搜索小报童投递-点击开始阅读-点击生财有术项目精选即可" & CHAR(10) & CHAR(10), "3.《生财365问》" & CHAR(10), "兑换码：", AI40, CHAR(10), "使用方式：https://appamvpb5mq9834.h5.xiaoeknow.com/p/t/v1/ecommerce/mkt/redeem_index")
A41: =IF('微伴数据'!A38="","",'微伴数据'!A38) | B41: =IF('微伴数据'!B38="","",'微伴数据'!B38) | C41: =IF('微伴数据'!G38="","",'微伴数据'!G38) | D41: =IF('微伴数据'!D38="","",'微伴数据'!D38) | E41: =IF('微伴数据'!CR38="","",'微伴数据'!CR38) | F41: =IF('微伴数据'!CL38="","",'微伴数据'!CL38) | G41: B | H41: 建联 | I41: =VLOOKUP(A41,'Sheet9'!A:A,1,0) | K41: =T41&CHAR(10)&U41&CHAR(10)&V41&CHAR(10)&Y41&CHAR(10)&Z41&CHAR(10)&AA41&CHAR(10)&AB41&CHAR(10)&AC41&CHAR(10)&AD41&CHAR(10)&AE41 | L41: =IFERROR(VLOOKUP(#REF!,'第一课直播'!D:L,9,0),IFERROR(VLOOKUP('第一课回放'!C:H,5,0),"未到课")) | M41: =IFERROR(VLOOKUP(#REF!,'第一课回放'!C:H,5,0),"0:00:00") | N41: =IFERROR(VLOOKUP(#REF!,'第二课直播'!D:L,9,0),"未到课") | S41: =IFERROR(VLOOKUP(A41,'微伴数据'!A:DB,12,0),"") | T41: =IFERROR(VLOOKUP(A41,'微伴数据'!A:DB,32,0),"") | U41: =IFERROR(VLOOKUP(A41,'微伴数据'!A:DC,81,0),"") | V41: =IFERROR(VLOOKUP(#REF!,'星橙地址'!A:V,9,0),"") | W41: =IFERROR(VLOOKUP(#REF!,'星橙地址'!A:V,10,0),"") | X41: =IFERROR(VLOOKUP(A41,'星云问卷'!A:O,8,0),"") | Y41: =IFERROR(VLOOKUP(A41,'星云问卷'!A:O,9,0),"") | Z41: =IFERROR(VLOOKUP(A41,'星云问卷'!A:O,10,0),"") | AA41: =IFERROR(VLOOKUP(A41,'星云问卷'!A:O,11,0),"") | AB41: =IFERROR(VLOOKUP(A41,'星云问卷'!A:O,12,0),"") | AC41: =IFERROR(VLOOKUP(A41,'星云问卷'!A:O,13,0),"") | AD41: =IFERROR(VLOOKUP(A41,'星云问卷'!A:O,14,0),"") | AE41: =IFERROR(VLOOKUP(A41,'星云问卷'!A:O,15,0),"") | AF41: =IFERROR(VLOOKUP(A41,'微伴数据'!A:DB,72,0),"") | AL41: =CONCATENATE( " 我把体验营用户专属福利给你发一下哈：" & CHAR(10) & CHAR(10), "1.《抖音商业IP课》" & CHAR(10), "兑换码：", AG41, CHAR(10), "兑换码使用地址：https://appamvpb5mq9834.h5.xiaoeknow.com/p/t/v1/ecommerce/mkt/redeem_index" & CHAR(10) & CHAR(10), "2.《生财有术66个项目精选》" & CHAR(10), "兑换码：", AH41, CHAR(10), "使用方式：微信搜索小报童投递-点击开始阅读-点击生财有术项目精选即可" & CHAR(10) & CHAR(10), "3.《生财365问》" & CHAR(10), "兑换码：", AI41, CHAR(10), "使用方式：https://appamvpb5mq9834.h5.xiaoeknow.com/p/t/v1/ecommerce/mkt/redeem_index")
A42: =IF('微伴数据'!A39="","",'微伴数据'!A39) | B42: =IF('微伴数据'!B39="","",'微伴数据'!B39) | C42: =IF('微伴数据'!G39="","",'微伴数据'!G39) | D42: =IF('微伴数据'!D39="","",'微伴数据'!D39) | E42: =IF('微伴数据'!CR39="","",'微伴数据'!CR39) | F42: =IF('微伴数据'!CL39="","",'微伴数据'!CL39) | G42: A | H42: 建联 | I42: =VLOOKUP(A42,'Sheet9'!A:A,1,0) | K42: =T42&CHAR(10)&U42&CHAR(10)&V42&CHAR(10)&Y42&CHAR(10)&Z42&CHAR(10)&AA42&CHAR(10)&AB42&CHAR(10)&AC42&CHAR(10)&AD42&CHAR(10)&AE42 | L42: =IFERROR(VLOOKUP(#REF!,'第一课直播'!D:L,9,0),IFERROR(VLOOKUP('第一课回放'!C:H,5,0),"未到课")) | M42: =IFERROR(VLOOKUP(#REF!,'第一课回放'!C:H,5,0),"0:00:00") | N42: =IFERROR(VLOOKUP(#REF!,'第二课直播'!D:L,9,0),"未到课") | S42: =IFERROR(VLOOKUP(A42,'微伴数据'!A:DB,12,0),"") | T42: =IFERROR(VLOOKUP(A42,'微伴数据'!A:DB,32,0),"") | U42: =IFERROR(VLOOKUP(A42,'微伴数据'!A:DC,81,0),"") | V42: =IFERROR(VLOOKUP(#REF!,'星橙地址'!A:V,9,0),"") | W42: =IFERROR(VLOOKUP(#REF!,'星橙地址'!A:V,10,0),"") | X42: =IFERROR(VLOOKUP(A42,'星云问卷'!A:O,8,0),"") | Y42: =IFERROR(VLOOKUP(A42,'星云问卷'!A:O,9,0),"") | Z42: =IFERROR(VLOOKUP(A42,'星云问卷'!A:O,10,0),"") | AA42: =IFERROR(VLOOKUP(A42,'星云问卷'!A:O,11,0),"") | AB42: =IFERROR(VLOOKUP(A42,'星云问卷'!A:O,12,0),"") | AC42: =IFERROR(VLOOKUP(A42,'星云问卷'!A:O,13,0),"") | AD42: =IFERROR(VLOOKUP(A42,'星云问卷'!A:O,14,0),"") | AE42: =IFERROR(VLOOKUP(A42,'星云问卷'!A:O,15,0),"") | AF42: =IFERROR(VLOOKUP(A42,'微伴数据'!A:DB,72,0),"") | AL42: =CONCATENATE( " 我把体验营用户专属福利给你发一下哈：" & CHAR(10) & CHAR(10), "1.《抖音商业IP课》" & CHAR(10), "兑换码：", AG42, CHAR(10), "兑换码使用地址：https://appamvpb5mq9834.h5.xiaoeknow.com/p/t/v1/ecommerce/mkt/redeem_index" & CHAR(10) & CHAR(10), "2.《生财有术66个项目精选》" & CHAR(10), "兑换码：", AH42, CHAR(10), "使用方式：微信搜索小报童投递-点击开始阅读-点击生财有术项目精选即可" & CHAR(10) & CHAR(10), "3.《生财365问》" & CHAR(10), "兑换码：", AI42, CHAR(10), "使用方式：https://appamvpb5mq9834.h5.xiaoeknow.com/p/t/v1/ecommerce/mkt/redeem_index") | AO42: 纳入用户画像
A43: =IF('微伴数据'!A40="","",'微伴数据'!A40) | B43: =IF('微伴数据'!B40="","",'微伴数据'!B40) | C43: =IF('微伴数据'!G40="","",'微伴数据'!G40) | D43: =IF('微伴数据'!D40="","",'微伴数据'!D40) | E43: =IF('微伴数据'!CR40="","",'微伴数据'!CR40) | F43: =IF('微伴数据'!CL40="","",'微伴数据'!CL40) | G43: S | H43: 建联 | I43: =VLOOKUP(A43,'Sheet9'!A:A,1,0) | K43: =T43&CHAR(10)&U43&CHAR(10)&V43&CHAR(10)&Y43&CHAR(10)&Z43&CHAR(10)&AA43&CHAR(10)&AB43&CHAR(10)&AC43&CHAR(10)&AD43&CHAR(10)&AE43 | L43: =IFERROR(VLOOKUP(#REF!,'第一课直播'!D:L,9,0),IFERROR(VLOOKUP('第一课回放'!C:H,5,0),"未到课")) | M43: =IFERROR(VLOOKUP(#REF!,'第一课回放'!C:H,5,0),"0:00:00") | N43: =IFERROR(VLOOKUP(#REF!,'第二课直播'!D:L,9,0),"未到课") | S43: =IFERROR(VLOOKUP(A43,'微伴数据'!A:DB,12,0),"") | T43: =IFERROR(VLOOKUP(A43,'微伴数据'!A:DB,32,0),"") | U43: =IFERROR(VLOOKUP(A43,'微伴数据'!A:DC,81,0),"") | V43: =IFERROR(VLOOKUP(#REF!,'星橙地址'!A:V,9,0),"") | W43: =IFERROR(VLOOKUP(#REF!,'星橙地址'!A:V,10,0),"") | X43: =IFERROR(VLOOKUP(A43,'星云问卷'!A:O,8,0),"") | Y43: =IFERROR(VLOOKUP(A43,'星云问卷'!A:O,9,0),"") | Z43: =IFERROR(VLOOKUP(A43,'星云问卷'!A:O,10,0),"") | AA43: =IFERROR(VLOOKUP(A43,'星云问卷'!A:O,11,0),"") | AB43: =IFERROR(VLOOKUP(A43,'星云问卷'!A:O,12,0),"") | AC43: =IFERROR(VLOOKUP(A43,'星云问卷'!A:O,13,0),"") | AD43: =IFERROR(VLOOKUP(A43,'星云问卷'!A:O,14,0),"") | AE43: =IFERROR(VLOOKUP(A43,'星云问卷'!A:O,15,0),"") | AF43: =IFERROR(VLOOKUP(A43,'微伴数据'!A:DB,72,0),"") | AH43: https://xiaobot.net/invitation/a85e7-1b5e7-95d43-78f75/ | AI43: 6dgGe2gH | AL43: =CONCATENATE( " 我把体验营用户专属福利给你发一下哈：" & CHAR(10) & CHAR(10), "1.《抖音商业IP课》" & CHAR(10), "兑换码：", AG43, CHAR(10), "兑换码使用地址：https://appamvpb5mq9834.h5.xiaoeknow.com/p/t/v1/ecommerce/mkt/redeem_index" & CHAR(10) & CHAR(10), "2.《生财有术66个项目精选》" & CHAR(10), "兑换码：", AH43, CHAR(10), "使用方式：微信搜索小报童投递-点击开始阅读-点击生财有术项目精选即可" & CHAR(10) & CHAR(10), "3.《生财365问》" & CHAR(10), "兑换码：", AI43, CHAR(10), "使用方式：https://appamvpb5mq9834.h5.xiaoeknow.com/p/t/v1/ecommerce/mkt/redeem_index")
A44: =IF('微伴数据'!A41="","",'微伴数据'!A41) | B44: =IF('微伴数据'!B41="","",'微伴数据'!B41) | C44: =IF('微伴数据'!G41="","",'微伴数据'!G41) | D44: =IF('微伴数据'!D41="","",'微伴数据'!D41) | E44: =IF('微伴数据'!CR41="","",'微伴数据'!CR41) | F44: =IF('微伴数据'!CL41="","",'微伴数据'!CL41) | G44: B | H44: 建联 | I44: =VLOOKUP(A44,'Sheet9'!A:A,1,0) | K44: =T44&CHAR(10)&U44&CHAR(10)&V44&CHAR(10)&Y44&CHAR(10)&Z44&CHAR(10)&AA44&CHAR(10)&AB44&CHAR(10)&AC44&CHAR(10)&AD44&CHAR(10)&AE44 | L44: =IFERROR(VLOOKUP(#REF!,'第一课直播'!D:L,9,0),IFERROR(VLOOKUP('第一课回放'!C:H,5,0),"未到课")) | M44: =IFERROR(VLOOKUP(#REF!,'第一课回放'!C:H,5,0),"0:00:00") | N44: =IFERROR(VLOOKUP(#REF!,'第二课直播'!D:L,9,0),"未到课") | S44: =IFERROR(VLOOKUP(A44,'微伴数据'!A:DB,12,0),"") | T44: =IFERROR(VLOOKUP(A44,'微伴数据'!A:DB,32,0),"") | U44: =IFERROR(VLOOKUP(A44,'微伴数据'!A:DC,81,0),"") | V44: =IFERROR(VLOOKUP(#REF!,'星橙地址'!A:V,9,0),"") | W44: =IFERROR(VLOOKUP(#REF!,'星橙地址'!A:V,10,0),"") | X44: =IFERROR(VLOOKUP(A44,'星云问卷'!A:O,8,0),"") | Y44: =IFERROR(VLOOKUP(A44,'星云问卷'!A:O,9,0),"") | Z44: =IFERROR(VLOOKUP(A44,'星云问卷'!A:O,10,0),"") | AA44: =IFERROR(VLOOKUP(A44,'星云问卷'!A:O,11,0),"") | AB44: =IFERROR(VLOOKUP(A44,'星云问卷'!A:O,12,0),"") | AC44: =IFERROR(VLOOKUP(A44,'星云问卷'!A:O,13,0),"") | AD44: =IFERROR(VLOOKUP(A44,'星云问卷'!A:O,14,0),"") | AE44: =IFERROR(VLOOKUP(A44,'星云问卷'!A:O,15,0),"") | AF44: =IFERROR(VLOOKUP(A44,'微伴数据'!A:DB,72,0),"") | AL44: =CONCATENATE( " 我把体验营用户专属福利给你发一下哈：" & CHAR(10) & CHAR(10), "1.《抖音商业IP课》" & CHAR(10), "兑换码：", AG44, CHAR(10), "兑换码使用地址：https://appamvpb5mq9834.h5.xiaoeknow.com/p/t/v1/ecommerce/mkt/redeem_index" & CHAR(10) & CHAR(10), "2.《生财有术66个项目精选》" & CHAR(10), "兑换码：", AH44, CHAR(10), "使用方式：微信搜索小报童投递-点击开始阅读-点击生财有术项目精选即可" & CHAR(10) & CHAR(10), "3.《生财365问》" & CHAR(10), "兑换码：", AI44, CHAR(10), "使用方式：https://appamvpb5mq9834.h5.xiaoeknow.com/p/t/v1/ecommerce/mkt/redeem_index")
A45: =IF('微伴数据'!A42="","",'微伴数据'!A42) | B45: =IF('微伴数据'!B42="","",'微伴数据'!B42) | C45: =IF('微伴数据'!G42="","",'微伴数据'!G42) | D45: =IF('微伴数据'!D42="","",'微伴数据'!D42) | E45: =IF('微伴数据'!CR42="","",'微伴数据'!CR42) | F45: =IF('微伴数据'!CL42="","",'微伴数据'!CL42) | G45: S | H45: 需求 | I45: =VLOOKUP(A45,'Sheet9'!A:A,1,0) | J45: 是的。昨天没听课，今天会看回放，时间有的，预算没有多少 | K45: =T45&CHAR(10)&U45&CHAR(10)&V45&CHAR(10)&Y45&CHAR(10)&Z45&CHAR(10)&AA45&CHAR(10)&AB45&CHAR(10)&AC45&CHAR(10)&AD45&CHAR(10)&AE45 | L45: =IFERROR(VLOOKUP(#REF!,'第一课直播'!D:L,9,0),IFERROR(VLOOKUP('第一课回放'!C:H,5,0),"未到课")) | M45: =IFERROR(VLOOKUP(#REF!,'第一课回放'!C:H,5,0),"0:00:00") | N45: =IFERROR(VLOOKUP(#REF!,'第二课直播'!D:L,9,0),"未到课") | S45: =IFERROR(VLOOKUP(A45,'微伴数据'!A:DB,12,0),"") | T45: =IFERROR(VLOOKUP(A45,'微伴数据'!A:DB,32,0),"") | U45: =IFERROR(VLOOKUP(A45,'微伴数据'!A:DC,81,0),"") | V45: =IFERROR(VLOOKUP(#REF!,'星橙地址'!A:V,9,0),"") | W45: =IFERROR(VLOOKUP(#REF!,'星橙地址'!A:V,10,0),"") | X45: =IFERROR(VLOOKUP(A45,'星云问卷'!A:O,8,0),"") | Y45: =IFERROR(VLOOKUP(A45,'星云问卷'!A:O,9,0),"") | Z45: =IFERROR(VLOOKUP(A45,'星云问卷'!A:O,10,0),"") | AA45: =IFERROR(VLOOKUP(A45,'星云问卷'!A:O,11,0),"") | AB45: =IFERROR(VLOOKUP(A45,'星云问卷'!A:O,12,0),"") | AC45: =IFERROR(VLOOKUP(A45,'星云问卷'!A:O,13,0),"") | AD45: =IFERROR(VLOOKUP(A45,'星云问卷'!A:O,14,0),"") | AE45: =IFERROR(VLOOKUP(A45,'星云问卷'!A:O,15,0),"") | AF45: =IFERROR(VLOOKUP(A45,'微伴数据'!A:DB,72,0),"") | AL45: =CONCATENATE( " 我把体验营用户专属福利给你发一下哈：" & CHAR(10) & CHAR(10), "1.《抖音商业IP课》" & CHAR(10), "兑换码：", AG45, CHAR(10), "兑换码使用地址：https://appamvpb5mq9834.h5.xiaoeknow.com/p/t/v1/ecommerce/mkt/redeem_index" & CHAR(10) & CHAR(10), "2.《生财有术66个项目精选》" & CHAR(10), "兑换码：", AH45, CHAR(10), "使用方式：微信搜索小报童投递-点击开始阅读-点击生财有术项目精选即可" & CHAR(10) & CHAR(10), "3.《生财365问》" & CHAR(10), "兑换码：", AI45, CHAR(10), "使用方式：https://appamvpb5mq9834.h5.xiaoeknow.com/p/t/v1/ecommerce/mkt/redeem_index")
A46: =IF('微伴数据'!A43="","",'微伴数据'!A43) | B46: =IF('微伴数据'!B43="","",'微伴数据'!B43) | C46: =IF('微伴数据'!G43="","",'微伴数据'!G43) | D46: =IF('微伴数据'!D43="","",'微伴数据'!D43) | E46: =IF('微伴数据'!CR43="","",'微伴数据'!CR43) | F46: =IF('微伴数据'!CL43="","",'微伴数据'!CL43) | G46: B | H46: 建联 | I46: =VLOOKUP(A46,'Sheet9'!A:A,1,0) | K46: =T46&CHAR(10)&U46&CHAR(10)&V46&CHAR(10)&Y46&CHAR(10)&Z46&CHAR(10)&AA46&CHAR(10)&AB46&CHAR(10)&AC46&CHAR(10)&AD46&CHAR(10)&AE46 | L46: =IFERROR(VLOOKUP(#REF!,'第一课直播'!D:L,9,0),IFERROR(VLOOKUP('第一课回放'!C:H,5,0),"未到课")) | M46: =IFERROR(VLOOKUP(#REF!,'第一课回放'!C:H,5,0),"0:00:00") | N46: =IFERROR(VLOOKUP(#REF!,'第二课直播'!D:L,9,0),"未到课") | S46: =IFERROR(VLOOKUP(A46,'微伴数据'!A:DB,12,0),"") | T46: =IFERROR(VLOOKUP(A46,'微伴数据'!A:DB,32,0),"") | U46: =IFERROR(VLOOKUP(A46,'微伴数据'!A:DC,81,0),"") | V46: =IFERROR(VLOOKUP(#REF!,'星橙地址'!A:V,9,0),"") | W46: =IFERROR(VLOOKUP(#REF!,'星橙地址'!A:V,10,0),"") | X46: =IFERROR(VLOOKUP(A46,'星云问卷'!A:O,8,0),"") | Y46: =IFERROR(VLOOKUP(A46,'星云问卷'!A:O,9,0),"") | Z46: =IFERROR(VLOOKUP(A46,'星云问卷'!A:O,10,0),"") | AA46: =IFERROR(VLOOKUP(A46,'星云问卷'!A:O,11,0),"") | AB46: =IFERROR(VLOOKUP(A46,'星云问卷'!A:O,12,0),"") | AC46: =IFERROR(VLOOKUP(A46,'星云问卷'!A:O,13,0),"") | AD46: =IFERROR(VLOOKUP(A46,'星云问卷'!A:O,14,0),"") | AE46: =IFERROR(VLOOKUP(A46,'星云问卷'!A:O,15,0),"") | AF46: =IFERROR(VLOOKUP(A46,'微伴数据'!A:DB,72,0),"") | AL46: =CONCATENATE( " 我把体验营用户专属福利给你发一下哈：" & CHAR(10) & CHAR(10), "1.《抖音商业IP课》" & CHAR(10), "兑换码：", AG46, CHAR(10), "兑换码使用地址：https://appamvpb5mq9834.h5.xiaoeknow.com/p/t/v1/ecommerce/mkt/redeem_index" & CHAR(10) & CHAR(10), "2.《生财有术66个项目精选》" & CHAR(10), "兑换码：", AH46, CHAR(10), "使用方式：微信搜索小报童投递-点击开始阅读-点击生财有术项目精选即可" & CHAR(10) & CHAR(10), "3.《生财365问》" & CHAR(10), "兑换码：", AI46, CHAR(10), "使用方式：https://appamvpb5mq9834.h5.xiaoeknow.com/p/t/v1/ecommerce/mkt/redeem_index")
A47: =IF('微伴数据'!A44="","",'微伴数据'!A44) | B47: =IF('微伴数据'!B44="","",'微伴数据'!B44) | C47: =IF('微伴数据'!G44="","",'微伴数据'!G44) | D47: =IF('微伴数据'!D44="","",'微伴数据'!D44) | E47: =IF('微伴数据'!CR44="","",'微伴数据'!CR44) | F47: =IF('微伴数据'!CL44="","",'微伴数据'!CL44) | G47: B | H47: 建联 | I47: =VLOOKUP(A47,'Sheet9'!A:A,1,0) | K47: =T47&CHAR(10)&U47&CHAR(10)&V47&CHAR(10)&Y47&CHAR(10)&Z47&CHAR(10)&AA47&CHAR(10)&AB47&CHAR(10)&AC47&CHAR(10)&AD47&CHAR(10)&AE47 | L47: =IFERROR(VLOOKUP(#REF!,'第一课直播'!D:L,9,0),IFERROR(VLOOKUP('第一课回放'!C:H,5,0),"未到课")) | M47: =IFERROR(VLOOKUP(#REF!,'第一课回放'!C:H,5,0),"0:00:00") | N47: =IFERROR(VLOOKUP(#REF!,'第二课直播'!D:L,9,0),"未到课") | S47: =IFERROR(VLOOKUP(A47,'微伴数据'!A:DB,12,0),"") | T47: =IFERROR(VLOOKUP(A47,'微伴数据'!A:DB,32,0),"") | U47: =IFERROR(VLOOKUP(A47,'微伴数据'!A:DC,81,0),"") | V47: =IFERROR(VLOOKUP(#REF!,'星橙地址'!A:V,9,0),"") | W47: =IFERROR(VLOOKUP(#REF!,'星橙地址'!A:V,10,0),"") | X47: =IFERROR(VLOOKUP(A47,'星云问卷'!A:O,8,0),"") | Y47: =IFERROR(VLOOKUP(A47,'星云问卷'!A:O,9,0),"") | Z47: =IFERROR(VLOOKUP(A47,'星云问卷'!A:O,10,0),"") | AA47: =IFERROR(VLOOKUP(A47,'星云问卷'!A:O,11,0),"") | AB47: =IFERROR(VLOOKUP(A47,'星云问卷'!A:O,12,0),"") | AC47: =IFERROR(VLOOKUP(A47,'星云问卷'!A:O,13,0),"") | AD47: =IFERROR(VLOOKUP(A47,'星云问卷'!A:O,14,0),"") | AE47: =IFERROR(VLOOKUP(A47,'星云问卷'!A:O,15,0),"") | AF47: =IFERROR(VLOOKUP(A47,'微伴数据'!A:DB,72,0),"") | AG47: 54Ae7p9s | AH47: https://xiaobot.net/invitation/27f19-d53a6-31087-ab1b4/ | AI47: 6dqTs8WW | AL47: =CONCATENATE( " 我把体验营用户专属福利给你发一下哈：" & CHAR(10) & CHAR(10), "1.《抖音商业IP课》" & CHAR(10), "兑换码：", AG47, CHAR(10), "兑换码使用地址：https://appamvpb5mq9834.h5.xiaoeknow.com/p/t/v1/ecommerce/mkt/redeem_index" & CHAR(10) & CHAR(10), "2.《生财有术66个项目精选》" & CHAR(10), "兑换码：", AH47, CHAR(10), "使用方式：微信搜索小报童投递-点击开始阅读-点击生财有术项目精选即可" & CHAR(10) & CHAR(10), "3.《生财365问》" & CHAR(10), "兑换码：", AI47, CHAR(10), "使用方式：https://appamvpb5mq9834.h5.xiaoeknow.com/p/t/v1/ecommerce/mkt/redeem_index")
A48: =IF('微伴数据'!A45="","",'微伴数据'!A45) | B48: =IF('微伴数据'!B45="","",'微伴数据'!B45) | C48: =IF('微伴数据'!G45="","",'微伴数据'!G45) | D48: =IF('微伴数据'!D45="","",'微伴数据'!D45) | E48: =IF('微伴数据'!CR45="","",'微伴数据'!CR45) | F48: =IF('微伴数据'!CL45="","",'微伴数据'!CL45) | G48: B | H48: 建联 | I48: =VLOOKUP(A48,'Sheet9'!A:A,1,0) | K48: =T48&CHAR(10)&U48&CHAR(10)&V48&CHAR(10)&Y48&CHAR(10)&Z48&CHAR(10)&AA48&CHAR(10)&AB48&CHAR(10)&AC48&CHAR(10)&AD48&CHAR(10)&AE48 | L48: =IFERROR(VLOOKUP(#REF!,'第一课直播'!D:L,9,0),IFERROR(VLOOKUP('第一课回放'!C:H,5,0),"未到课")) | M48: =IFERROR(VLOOKUP(#REF!,'第一课回放'!C:H,5,0),"0:00:00") | N48: =IFERROR(VLOOKUP(#REF!,'第二课直播'!D:L,9,0),"未到课") | S48: =IFERROR(VLOOKUP(A48,'微伴数据'!A:DB,12,0),"") | T48: =IFERROR(VLOOKUP(A48,'微伴数据'!A:DB,32,0),"") | U48: =IFERROR(VLOOKUP(A48,'微伴数据'!A:DC,81,0),"") | V48: =IFERROR(VLOOKUP(#REF!,'星橙地址'!A:V,9,0),"") | W48: =IFERROR(VLOOKUP(#REF!,'星橙地址'!A:V,10,0),"") | X48: =IFERROR(VLOOKUP(A48,'星云问卷'!A:O,8,0),"") | Y48: =IFERROR(VLOOKUP(A48,'星云问卷'!A:O,9,0),"") | Z48: =IFERROR(VLOOKUP(A48,'星云问卷'!A:O,10,0),"") | AA48: =IFERROR(VLOOKUP(A48,'星云问卷'!A:O,11,0),"") | AB48: =IFERROR(VLOOKUP(A48,'星云问卷'!A:O,12,0),"") | AC48: =IFERROR(VLOOKUP(A48,'星云问卷'!A:O,13,0),"") | AD48: =IFERROR(VLOOKUP(A48,'星云问卷'!A:O,14,0),"") | AE48: =IFERROR(VLOOKUP(A48,'星云问卷'!A:O,15,0),"") | AF48: =IFERROR(VLOOKUP(A48,'微伴数据'!A:DB,72,0),"") | AL48: =CONCATENATE( " 我把体验营用户专属福利给你发一下哈：" & CHAR(10) & CHAR(10), "1.《抖音商业IP课》" & CHAR(10), "兑换码：", AG48, CHAR(10), "兑换码使用地址：https://appamvpb5mq9834.h5.xiaoeknow.com/p/t/v1/ecommerce/mkt/redeem_index" & CHAR(10) & CHAR(10), "2.《生财有术66个项目精选》" & CHAR(10), "兑换码：", AH48, CHAR(10), "使用方式：微信搜索小报童投递-点击开始阅读-点击生财有术项目精选即可" & CHAR(10) & CHAR(10), "3.《生财365问》" & CHAR(10), "兑换码：", AI48, CHAR(10), "使用方式：https://appamvpb5mq9834.h5.xiaoeknow.com/p/t/v1/ecommerce/mkt/redeem_index")
A49: =IF('微伴数据'!A46="","",'微伴数据'!A46) | B49: =IF('微伴数据'!B46="","",'微伴数据'!B46) | C49: =IF('微伴数据'!G46="","",'微伴数据'!G46) | D49: =IF('微伴数据'!D46="","",'微伴数据'!D46) | E49: =IF('微伴数据'!CR46="","",'微伴数据'!CR46) | F49: =IF('微伴数据'!CL46="","",'微伴数据'!CL46) | G49: B | H49: 建联 | I49: =VLOOKUP(A49,'Sheet9'!A:A,1,0) | K49: =T49&CHAR(10)&U49&CHAR(10)&V49&CHAR(10)&Y49&CHAR(10)&Z49&CHAR(10)&AA49&CHAR(10)&AB49&CHAR(10)&AC49&CHAR(10)&AD49&CHAR(10)&AE49 | L49: =IFERROR(VLOOKUP(#REF!,'第一课直播'!D:L,9,0),IFERROR(VLOOKUP('第一课回放'!C:H,5,0),"未到课")) | M49: =IFERROR(VLOOKUP(#REF!,'第一课回放'!C:H,5,0),"0:00:00") | N49: =IFERROR(VLOOKUP(#REF!,'第二课直播'!D:L,9,0),"未到课") | S49: =IFERROR(VLOOKUP(A49,'微伴数据'!A:DB,12,0),"") | T49: =IFERROR(VLOOKUP(A49,'微伴数据'!A:DB,32,0),"") | U49: =IFERROR(VLOOKUP(A49,'微伴数据'!A:DC,81,0),"") | V49: =IFERROR(VLOOKUP(#REF!,'星橙地址'!A:V,9,0),"") | W49: =IFERROR(VLOOKUP(#REF!,'星橙地址'!A:V,10,0),"") | X49: =IFERROR(VLOOKUP(A49,'星云问卷'!A:O,8,0),"") | Y49: =IFERROR(VLOOKUP(A49,'星云问卷'!A:O,9,0),"") | Z49: =IFERROR(VLOOKUP(A49,'星云问卷'!A:O,10,0),"") | AA49: =IFERROR(VLOOKUP(A49,'星云问卷'!A:O,11,0),"") | AB49: =IFERROR(VLOOKUP(A49,'星云问卷'!A:O,12,0),"") | AC49: =IFERROR(VLOOKUP(A49,'星云问卷'!A:O,13,0),"") | AD49: =IFERROR(VLOOKUP(A49,'星云问卷'!A:O,14,0),"") | AE49: =IFERROR(VLOOKUP(A49,'星云问卷'!A:O,15,0),"") | AF49: =IFERROR(VLOOKUP(A49,'微伴数据'!A:DB,72,0),"") | AL49: =CONCATENATE( " 我把体验营用户专属福利给你发一下哈：" & CHAR(10) & CHAR(10), "1.《抖音商业IP课》" & CHAR(10), "兑换码：", AG49, CHAR(10), "兑换码使用地址：https://appamvpb5mq9834.h5.xiaoeknow.com/p/t/v1/ecommerce/mkt/redeem_index" & CHAR(10) & CHAR(10), "2.《生财有术66个项目精选》" & CHAR(10), "兑换码：", AH49, CHAR(10), "使用方式：微信搜索小报童投递-点击开始阅读-点击生财有术项目精选即可" & CHAR(10) & CHAR(10), "3.《生财365问》" & CHAR(10), "兑换码：", AI49, CHAR(10), "使用方式：https://appamvpb5mq9834.h5.xiaoeknow.com/p/t/v1/ecommerce/mkt/redeem_index")
A50: =IF('微伴数据'!A47="","",'微伴数据'!A47) | B50: =IF('微伴数据'!B47="","",'微伴数据'!B47) | C50: =IF('微伴数据'!G47="","",'微伴数据'!G47) | D50: =IF('微伴数据'!D47="","",'微伴数据'!D47) | E50: =IF('微伴数据'!CR47="","",'微伴数据'!CR47) | F50: =IF('微伴数据'!CL47="","",'微伴数据'!CL47) | G50: B | H50: 建联 | I50: =VLOOKUP(A50,'Sheet9'!A:A,1,0) | K50: =T50&CHAR(10)&U50&CHAR(10)&V50&CHAR(10)&Y50&CHAR(10)&Z50&CHAR(10)&AA50&CHAR(10)&AB50&CHAR(10)&AC50&CHAR(10)&AD50&CHAR(10)&AE50 | L50: =IFERROR(VLOOKUP(#REF!,'第一课直播'!D:L,9,0),IFERROR(VLOOKUP('第一课回放'!C:H,5,0),"未到课")) | M50: =IFERROR(VLOOKUP(#REF!,'第一课回放'!C:H,5,0),"0:00:00") | N50: =IFERROR(VLOOKUP(#REF!,'第二课直播'!D:L,9,0),"未到课") | S50: =IFERROR(VLOOKUP(A50,'微伴数据'!A:DB,12,0),"") | T50: =IFERROR(VLOOKUP(A50,'微伴数据'!A:DB,32,0),"") | U50: =IFERROR(VLOOKUP(A50,'微伴数据'!A:DC,81,0),"") | V50: =IFERROR(VLOOKUP(#REF!,'星橙地址'!A:V,9,0),"") | W50: =IFERROR(VLOOKUP(#REF!,'星橙地址'!A:V,10,0),"") | X50: =IFERROR(VLOOKUP(A50,'星云问卷'!A:O,8,0),"") | Y50: =IFERROR(VLOOKUP(A50,'星云问卷'!A:O,9,0),"") | Z50: =IFERROR(VLOOKUP(A50,'星云问卷'!A:O,10,0),"") | AA50: =IFERROR(VLOOKUP(A50,'星云问卷'!A:O,11,0),"") | AB50: =IFERROR(VLOOKUP(A50,'星云问卷'!A:O,12,0),"") | AC50: =IFERROR(VLOOKUP(A50,'星云问卷'!A:O,13,0),"") | AD50: =IFERROR(VLOOKUP(A50,'星云问卷'!A:O,14,0),"") | AE50: =IFERROR(VLOOKUP(A50,'星云问卷'!A:O,15,0),"") | AF50: =IFERROR(VLOOKUP(A50,'微伴数据'!A:DB,72,0),"") | AL50: =CONCATENATE( " 我把体验营用户专属福利给你发一下哈：" & CHAR(10) & CHAR(10), "1.《抖音商业IP课》" & CHAR(10), "兑换码：", AG50, CHAR(10), "兑换码使用地址：https://appamvpb5mq9834.h5.xiaoeknow.com/p/t/v1/ecommerce/mkt/redeem_index" & CHAR(10) & CHAR(10), "2.《生财有术66个项目精选》" & CHAR(10), "兑换码：", AH50, CHAR(10), "使用方式：微信搜索小报童投递-点击开始阅读-点击生财有术项目精选即可" & CHAR(10) & CHAR(10), "3.《生财365问》" & CHAR(10), "兑换码：", AI50, CHAR(10), "使用方式：https://appamvpb5mq9834.h5.xiaoeknow.com/p/t/v1/ecommerce/mkt/redeem_index")
A51: =IF('微伴数据'!A48="","",'微伴数据'!A48) | B51: =IF('微伴数据'!B48="","",'微伴数据'!B48) | C51: =IF('微伴数据'!G48="","",'微伴数据'!G48) | D51: =IF('微伴数据'!D48="","",'微伴数据'!D48) | E51: =IF('微伴数据'!CR48="","",'微伴数据'!CR48) | F51: =IF('微伴数据'!CL48="","",'微伴数据'!CL48) | G51: A | H51: 建联 | I51: =VLOOKUP(A51,'Sheet9'!A:A,1,0) | K51: =T51&CHAR(10)&U51&CHAR(10)&V51&CHAR(10)&Y51&CHAR(10)&Z51&CHAR(10)&AA51&CHAR(10)&AB51&CHAR(10)&AC51&CHAR(10)&AD51&CHAR(10)&AE51 | L51: =IFERROR(VLOOKUP(#REF!,'第一课直播'!D:L,9,0),IFERROR(VLOOKUP('第一课回放'!C:H,5,0),"未到课")) | M51: =IFERROR(VLOOKUP(#REF!,'第一课回放'!C:H,5,0),"0:00:00") | N51: =IFERROR(VLOOKUP(#REF!,'第二课直播'!D:L,9,0),"未到课") | S51: =IFERROR(VLOOKUP(A51,'微伴数据'!A:DB,12,0),"") | T51: =IFERROR(VLOOKUP(A51,'微伴数据'!A:DB,32,0),"") | U51: =IFERROR(VLOOKUP(A51,'微伴数据'!A:DC,81,0),"") | V51: =IFERROR(VLOOKUP(#REF!,'星橙地址'!A:V,9,0),"") | W51: =IFERROR(VLOOKUP(#REF!,'星橙地址'!A:V,10,0),"") | X51: =IFERROR(VLOOKUP(A51,'星云问卷'!A:O,8,0),"") | Y51: =IFERROR(VLOOKUP(A51,'星云问卷'!A:O,9,0),"") | Z51: =IFERROR(VLOOKUP(A51,'星云问卷'!A:O,10,0),"") | AA51: =IFERROR(VLOOKUP(A51,'星云问卷'!A:O,11,0),"") | AB51: =IFERROR(VLOOKUP(A51,'星云问卷'!A:O,12,0),"") | AC51: =IFERROR(VLOOKUP(A51,'星云问卷'!A:O,13,0),"") | AD51: =IFERROR(VLOOKUP(A51,'星云问卷'!A:O,14,0),"") | AE51: =IFERROR(VLOOKUP(A51,'星云问卷'!A:O,15,0),"") | AF51: =IFERROR(VLOOKUP(A51,'微伴数据'!A:DB,72,0),"") | AL51: =CONCATENATE( " 我把体验营用户专属福利给你发一下哈：" & CHAR(10) & CHAR(10), "1.《抖音商业IP课》" & CHAR(10), "兑换码：", AG51, CHAR(10), "兑换码使用地址：https://appamvpb5mq9834.h5.xiaoeknow.com/p/t/v1/ecommerce/mkt/redeem_index" & CHAR(10) & CHAR(10), "2.《生财有术66个项目精选》" & CHAR(10), "兑换码：", AH51, CHAR(10), "使用方式：微信搜索小报童投递-点击开始阅读-点击生财有术项目精选即可" & CHAR(10) & CHAR(10), "3.《生财365问》" & CHAR(10), "兑换码：", AI51, CHAR(10), "使用方式：https://appamvpb5mq9834.h5.xiaoeknow.com/p/t/v1/ecommerce/mkt/redeem_index")
A52: =IF('微伴数据'!A49="","",'微伴数据'!A49) | B52: =IF('微伴数据'!B49="","",'微伴数据'!B49) | C52: =IF('微伴数据'!G49="","",'微伴数据'!G49) | D52: =IF('微伴数据'!D49="","",'微伴数据'!D49) | E52: =IF('微伴数据'!CR49="","",'微伴数据'!CR49) | F52: =IF('微伴数据'!CL49="","",'微伴数据'!CL49) | G52: B | H52: 建联 | I52: =VLOOKUP(A52,'Sheet9'!A:A,1,0) | K52: =T52&CHAR(10)&U52&CHAR(10)&V52&CHAR(10)&Y52&CHAR(10)&Z52&CHAR(10)&AA52&CHAR(10)&AB52&CHAR(10)&AC52&CHAR(10)&AD52&CHAR(10)&AE52 | L52: =IFERROR(VLOOKUP(#REF!,'第一课直播'!D:L,9,0),IFERROR(VLOOKUP('第一课回放'!C:H,5,0),"未到课")) | M52: =IFERROR(VLOOKUP(#REF!,'第一课回放'!C:H,5,0),"0:00:00") | N52: =IFERROR(VLOOKUP(#REF!,'第二课直播'!D:L,9,0),"未到课") | S52: =IFERROR(VLOOKUP(A52,'微伴数据'!A:DB,12,0),"") | T52: =IFERROR(VLOOKUP(A52,'微伴数据'!A:DB,32,0),"") | U52: =IFERROR(VLOOKUP(A52,'微伴数据'!A:DC,81,0),"") | V52: =IFERROR(VLOOKUP(#REF!,'星橙地址'!A:V,9,0),"") | W52: =IFERROR(VLOOKUP(#REF!,'星橙地址'!A:V,10,0),"") | X52: =IFERROR(VLOOKUP(A52,'星云问卷'!A:O,8,0),"") | Y52: =IFERROR(VLOOKUP(A52,'星云问卷'!A:O,9,0),"") | Z52: =IFERROR(VLOOKUP(A52,'星云问卷'!A:O,10,0),"") | AA52: =IFERROR(VLOOKUP(A52,'星云问卷'!A:O,11,0),"") | AB52: =IFERROR(VLOOKUP(A52,'星云问卷'!A:O,12,0),"") | AC52: =IFERROR(VLOOKUP(A52,'星云问卷'!A:O,13,0),"") | AD52: =IFERROR(VLOOKUP(A52,'星云问卷'!A:O,14,0),"") | AE52: =IFERROR(VLOOKUP(A52,'星云问卷'!A:O,15,0),"") | AF52: =IFERROR(VLOOKUP(A52,'微伴数据'!A:DB,72,0),"") | AG52: 54Ck7ZYH | AH52: https://xiaobot.net/invitation/e1eb1-82100-c48eb-dda0b/ | AI52: 6duJGwuH | AL52: =CONCATENATE( " 我把体验营用户专属福利给你发一下哈：" & CHAR(10) & CHAR(10), "1.《抖音商业IP课》" & CHAR(10), "兑换码：", AG52, CHAR(10), "兑换码使用地址：https://appamvpb5mq9834.h5.xiaoeknow.com/p/t/v1/ecommerce/mkt/redeem_index" & CHAR(10) & CHAR(10), "2.《生财有术66个项目精选》" & CHAR(10), "兑换码：", AH52, CHAR(10), "使用方式：微信搜索小报童投递-点击开始阅读-点击生财有术项目精选即可" & CHAR(10) & CHAR(10), "3.《生财365问》" & CHAR(10), "兑换码：", AI52, CHAR(10), "使用方式：https://appamvpb5mq9834.h5.xiaoeknow.com/p/t/v1/ecommerce/mkt/redeem_index")
A53: =IF('微伴数据'!A50="","",'微伴数据'!A50) | B53: =IF('微伴数据'!B50="","",'微伴数据'!B50) | C53: =IF('微伴数据'!G50="","",'微伴数据'!G50) | D53: =IF('微伴数据'!D50="","",'微伴数据'!D50) | E53: =IF('微伴数据'!CR50="","",'微伴数据'!CR50) | F53: =IF('微伴数据'!CL50="","",'微伴数据'!CL50) | G53: A | H53: 建联 | I53: =VLOOKUP(A53,'Sheet9'!A:A,1,0) | K53: =T53&CHAR(10)&U53&CHAR(10)&V53&CHAR(10)&Y53&CHAR(10)&Z53&CHAR(10)&AA53&CHAR(10)&AB53&CHAR(10)&AC53&CHAR(10)&AD53&CHAR(10)&AE53 | L53: =IFERROR(VLOOKUP(#REF!,'第一课直播'!D:L,9,0),IFERROR(VLOOKUP('第一课回放'!C:H,5,0),"未到课")) | M53: =IFERROR(VLOOKUP(#REF!,'第一课回放'!C:H,5,0),"0:00:00") | N53: =IFERROR(VLOOKUP(#REF!,'第二课直播'!D:L,9,0),"未到课") | S53: =IFERROR(VLOOKUP(A53,'微伴数据'!A:DB,12,0),"") | T53: =IFERROR(VLOOKUP(A53,'微伴数据'!A:DB,32,0),"") | U53: =IFERROR(VLOOKUP(A53,'微伴数据'!A:DC,81,0),"") | V53: =IFERROR(VLOOKUP(#REF!,'星橙地址'!A:V,9,0),"") | W53: =IFERROR(VLOOKUP(#REF!,'星橙地址'!A:V,10,0),"") | X53: =IFERROR(VLOOKUP(A53,'星云问卷'!A:O,8,0),"") | Y53: =IFERROR(VLOOKUP(A53,'星云问卷'!A:O,9,0),"") | Z53: =IFERROR(VLOOKUP(A53,'星云问卷'!A:O,10,0),"") | AA53: =IFERROR(VLOOKUP(A53,'星云问卷'!A:O,11,0),"") | AB53: =IFERROR(VLOOKUP(A53,'星云问卷'!A:O,12,0),"") | AC53: =IFERROR(VLOOKUP(A53,'星云问卷'!A:O,13,0),"") | AD53: =IFERROR(VLOOKUP(A53,'星云问卷'!A:O,14,0),"") | AE53: =IFERROR(VLOOKUP(A53,'星云问卷'!A:O,15,0),"") | AF53: =IFERROR(VLOOKUP(A53,'微伴数据'!A:DB,72,0),"") | AG53: 548HuM8Q | AH53: https://xiaobot.net/invitation/85b61-c45a7-dca3d-6d468/ | AI53: 6djhX6W8 | AL53: =CONCATENATE( " 我把体验营用户专属福利给你发一下哈：" & CHAR(10) & CHAR(10), "1.《抖音商业IP课》" & CHAR(10), "兑换码：", AG53, CHAR(10), "兑换码使用地址：https://appamvpb5mq9834.h5.xiaoeknow.com/p/t/v1/ecommerce/mkt/redeem_index" & CHAR(10) & CHAR(10), "2.《生财有术66个项目精选》" & CHAR(10), "兑换码：", AH53, CHAR(10), "使用方式：微信搜索小报童投递-点击开始阅读-点击生财有术项目精选即可" & CHAR(10) & CHAR(10), "3.《生财365问》" & CHAR(10), "兑换码：", AI53, CHAR(10), "使用方式：https://appamvpb5mq9834.h5.xiaoeknow.com/p/t/v1/ecommerce/mkt/redeem_index")
A54: =IF('微伴数据'!A51="","",'微伴数据'!A51) | B54: =IF('微伴数据'!B51="","",'微伴数据'!B51) | C54: =IF('微伴数据'!G51="","",'微伴数据'!G51) | D54: =IF('微伴数据'!D51="","",'微伴数据'!D51) | E54: =IF('微伴数据'!CR51="","",'微伴数据'!CR51) | F54: =IF('微伴数据'!CL51="","",'微伴数据'!CL51) | G54: B | H54: 建联 | I54: =VLOOKUP(A54,'Sheet9'!A:A,1,0) | J54: 我背景是硕士加有编程基础，想专注自媒体ip加ai | K54: =T54&CHAR(10)&U54&CHAR(10)&V54&CHAR(10)&Y54&CHAR(10)&Z54&CHAR(10)&AA54&CHAR(10)&AB54&CHAR(10)&AC54&CHAR(10)&AD54&CHAR(10)&AE54 | L54: =IFERROR(VLOOKUP(#REF!,'第一课直播'!D:L,9,0),IFERROR(VLOOKUP('第一课回放'!C:H,5,0),"未到课")) | M54: =IFERROR(VLOOKUP(#REF!,'第一课回放'!C:H,5,0),"0:00:00") | N54: =IFERROR(VLOOKUP(#REF!,'第二课直播'!D:L,9,0),"未到课") | S54: =IFERROR(VLOOKUP(A54,'微伴数据'!A:DB,12,0),"") | T54: =IFERROR(VLOOKUP(A54,'微伴数据'!A:DB,32,0),"") | U54: =IFERROR(VLOOKUP(A54,'微伴数据'!A:DC,81,0),"") | V54: =IFERROR(VLOOKUP(#REF!,'星橙地址'!A:V,9,0),"") | W54: =IFERROR(VLOOKUP(#REF!,'星橙地址'!A:V,10,0),"") | X54: =IFERROR(VLOOKUP(A54,'星云问卷'!A:O,8,0),"") | Y54: =IFERROR(VLOOKUP(A54,'星云问卷'!A:O,9,0),"") | Z54: =IFERROR(VLOOKUP(A54,'星云问卷'!A:O,10,0),"") | AA54: =IFERROR(VLOOKUP(A54,'星云问卷'!A:O,11,0),"") | AB54: =IFERROR(VLOOKUP(A54,'星云问卷'!A:O,12,0),"") | AC54: =IFERROR(VLOOKUP(A54,'星云问卷'!A:O,13,0),"") | AD54: =IFERROR(VLOOKUP(A54,'星云问卷'!A:O,14,0),"") | AE54: =IFERROR(VLOOKUP(A54,'星云问卷'!A:O,15,0),"") | AF54: =IFERROR(VLOOKUP(A54,'微伴数据'!A:DB,72,0),"") | AG54: 54CkF8tt | AH54: https://xiaobot.net/invitation/e845f-a2566-e5a0a-153a2/ | AI54: 6duM9U3N | AL54: =CONCATENATE( " 我把体验营用户专属福利给你发一下哈：" & CHAR(10) & CHAR(10), "1.《抖音商业IP课》" & CHAR(10), "兑换码：", AG54, CHAR(10), "兑换码使用地址：https://appamvpb5mq9834.h5.xiaoeknow.com/p/t/v1/ecommerce/mkt/redeem_index" & CHAR(10) & CHAR(10), "2.《生财有术66个项目精选》" & CHAR(10), "兑换码：", AH54, CHAR(10), "使用方式：微信搜索小报童投递-点击开始阅读-点击生财有术项目精选即可" & CHAR(10) & CHAR(10), "3.《生财365问》" & CHAR(10), "兑换码：", AI54, CHAR(10), "使用方式：https://appamvpb5mq9834.h5.xiaoeknow.com/p/t/v1/ecommerce/mkt/redeem_index")
A55: =IF('微伴数据'!A52="","",'微伴数据'!A52) | B55: =IF('微伴数据'!B52="","",'微伴数据'!B52) | C55: =IF('微伴数据'!G52="","",'微伴数据'!G52) | D55: =IF('微伴数据'!D52="","",'微伴数据'!D52) | E55: =IF('微伴数据'!CR52="","",'微伴数据'!CR52) | F55: =IF('微伴数据'!CL52="","",'微伴数据'!CL52) | G55: B | H55: 建联 | I55: =VLOOKUP(A55,'Sheet9'!A:A,1,0) | K55: =T55&CHAR(10)&U55&CHAR(10)&V55&CHAR(10)&Y55&CHAR(10)&Z55&CHAR(10)&AA55&CHAR(10)&AB55&CHAR(10)&AC55&CHAR(10)&AD55&CHAR(10)&AE55 | L55: =IFERROR(VLOOKUP(#REF!,'第一课直播'!D:L,9,0),IFERROR(VLOOKUP('第一课回放'!C:H,5,0),"未到课")) | M55: =IFERROR(VLOOKUP(#REF!,'第一课回放'!C:H,5,0),"0:00:00") | N55: =IFERROR(VLOOKUP(#REF!,'第二课直播'!D:L,9,0),"未到课") | P55: 🎁 作业模板： 星球链接：公众号小白到6个月流量主收益200W_V正式版 读后感：公众号运营策略随时代变迁。早期，内容为王，凭借热点内容赢得红利。中期，竞争加剧，强调精细化运营与IP打造。如今，则进入私域时代，通过全平台引流、视频号联动和社群精耕，实现高效变现。理解并适应这些变化，是从公众号中脱颖而出的关键。这是一个不断进化、充满挑战与机遇的领域。 | S55: =IFERROR(VLOOKUP(A55,'微伴数据'!A:DB,12,0),"") | T55: =IFERROR(VLOOKUP(A55,'微伴数据'!A:DB,32,0),"") | U55: =IFERROR(VLOOKUP(A55,'微伴数据'!A:DC,81,0),"") | V55: =IFERROR(VLOOKUP(#REF!,'星橙地址'!A:V,9,0),"") | W55: =IFERROR(VLOOKUP(#REF!,'星橙地址'!A:V,10,0),"") | X55: =IFERROR(VLOOKUP(A55,'星云问卷'!A:O,8,0),"") | Y55: =IFERROR(VLOOKUP(A55,'星云问卷'!A:O,9,0),"") | Z55: =IFERROR(VLOOKUP(A55,'星云问卷'!A:O,10,0),"") | AA55: =IFERROR(VLOOKUP(A55,'星云问卷'!A:O,11,0),"") | AB55: =IFERROR(VLOOKUP(A55,'星云问卷'!A:O,12,0),"") | AC55: =IFERROR(VLOOKUP(A55,'星云问卷'!A:O,13,0),"") | AD55: =IFERROR(VLOOKUP(A55,'星云问卷'!A:O,14,0),"") | AE55: =IFERROR(VLOOKUP(A55,'星云问卷'!A:O,15,0),"") | AF55: =IFERROR(VLOOKUP(A55,'微伴数据'!A:DB,72,0),"") | AG55: 54CkJnZ4 | AH55: https://xiaobot.net/invitation/972a8-3a1cd-ecb66-b398b/ | AI55: 6duNr675 | AL55: =CONCATENATE( " 我把体验营用户专属福利给你发一下哈：" & CHAR(10) & CHAR(10), "1.《抖音商业IP课》" & CHAR(10), "兑换码：", AG55, CHAR(10), "兑换码使用地址：https://appamvpb5mq9834.h5.xiaoeknow.com/p/t/v1/ecommerce/mkt/redeem_index" & CHAR(10) & CHAR(10), "2.《生财有术66个项目精选》" & CHAR(10), "兑换码：", AH55, CHAR(10), "使用方式：微信搜索小报童投递-点击开始阅读-点击生财有术项目精选即可" & CHAR(10) & CHAR(10), "3.《生财365问》" & CHAR(10), "兑换码：", AI55, CHAR(10), "使用方式：https://appamvpb5mq9834.h5.xiaoeknow.com/p/t/v1/ecommerce/mkt/redeem_index")
A56: =IF('微伴数据'!A53="","",'微伴数据'!A53) | B56: =IF('微伴数据'!B53="","",'微伴数据'!B53) | C56: =IF('微伴数据'!G53="","",'微伴数据'!G53) | D56: =IF('微伴数据'!D53="","",'微伴数据'!D53) | E56: =IF('微伴数据'!CR53="","",'微伴数据'!CR53) | F56: =IF('微伴数据'!CL53="","",'微伴数据'!CL53) | G56: A | H56: 建联 | I56: =VLOOKUP(A56,'Sheet9'!A:A,1,0) | K56: =T56&CHAR(10)&U56&CHAR(10)&V56&CHAR(10)&Y56&CHAR(10)&Z56&CHAR(10)&AA56&CHAR(10)&AB56&CHAR(10)&AC56&CHAR(10)&AD56&CHAR(10)&AE56 | L56: =IFERROR(VLOOKUP(#REF!,'第一课直播'!D:L,9,0),IFERROR(VLOOKUP('第一课回放'!C:H,5,0),"未到课")) | M56: =IFERROR(VLOOKUP(#REF!,'第一课回放'!C:H,5,0),"0:00:00") | N56: =IFERROR(VLOOKUP(#REF!,'第二课直播'!D:L,9,0),"未到课") | S56: =IFERROR(VLOOKUP(A56,'微伴数据'!A:DB,12,0),"") | T56: =IFERROR(VLOOKUP(A56,'微伴数据'!A:DB,32,0),"") | U56: =IFERROR(VLOOKUP(A56,'微伴数据'!A:DC,81,0),"") | V56: =IFERROR(VLOOKUP(#REF!,'星橙地址'!A:V,9,0),"") | W56: =IFERROR(VLOOKUP(#REF!,'星橙地址'!A:V,10,0),"") | X56: =IFERROR(VLOOKUP(A56,'星云问卷'!A:O,8,0),"") | Y56: =IFERROR(VLOOKUP(A56,'星云问卷'!A:O,9,0),"") | Z56: =IFERROR(VLOOKUP(A56,'星云问卷'!A:O,10,0),"") | AA56: =IFERROR(VLOOKUP(A56,'星云问卷'!A:O,11,0),"") | AB56: =IFERROR(VLOOKUP(A56,'星云问卷'!A:O,12,0),"") | AC56: =IFERROR(VLOOKUP(A56,'星云问卷'!A:O,13,0),"") | AD56: =IFERROR(VLOOKUP(A56,'星云问卷'!A:O,14,0),"") | AE56: =IFERROR(VLOOKUP(A56,'星云问卷'!A:O,15,0),"") | AF56: =IFERROR(VLOOKUP(A56,'微伴数据'!A:DB,72,0),"") | AL56: =CONCATENATE( " 我把体验营用户专属福利给你发一下哈：" & CHAR(10) & CHAR(10), "1.《抖音商业IP课》" & CHAR(10), "兑换码：", AG56, CHAR(10), "兑换码使用地址：https://appamvpb5mq9834.h5.xiaoeknow.com/p/t/v1/ecommerce/mkt/redeem_index" & CHAR(10) & CHAR(10), "2.《生财有术66个项目精选》" & CHAR(10), "兑换码：", AH56, CHAR(10), "使用方式：微信搜索小报童投递-点击开始阅读-点击生财有术项目精选即可" & CHAR(10) & CHAR(10), "3.《生财365问》" & CHAR(10), "兑换码：", AI56, CHAR(10), "使用方式：https://appamvpb5mq9834.h5.xiaoeknow.com/p/t/v1/ecommerce/mkt/redeem_index")
A57: =IF('微伴数据'!A54="","",'微伴数据'!A54) | B57: =IF('微伴数据'!B54="","",'微伴数据'!B54) | C57: =IF('微伴数据'!G54="","",'微伴数据'!G54) | D57: =IF('微伴数据'!D54="","",'微伴数据'!D54) | E57: =IF('微伴数据'!CR54="","",'微伴数据'!CR54) | F57: =IF('微伴数据'!CL54="","",'微伴数据'!CL54) | G57: A | H57: 建联 | I57: =VLOOKUP(A57,'Sheet9'!A:A,1,0) | J57: 简单介绍一下我自己：42岁，辞职状态。20年一直是销售相关岗位。目前想做情绪方面的内容，自己是个高敏感高感知力人群，抑郁自愈经历。想通过自媒体先下场尝试。 | K57: =T57&CHAR(10)&U57&CHAR(10)&V57&CHAR(10)&Y57&CHAR(10)&Z57&CHAR(10)&AA57&CHAR(10)&AB57&CHAR(10)&AC57&CHAR(10)&AD57&CHAR(10)&AE57 | L57: =IFERROR(VLOOKUP(#REF!,'第一课直播'!D:L,9,0),IFERROR(VLOOKUP('第一课回放'!C:H,5,0),"未到课")) | M57: =IFERROR(VLOOKUP(#REF!,'第一课回放'!C:H,5,0),"0:00:00") | N57: =IFERROR(VLOOKUP(#REF!,'第二课直播'!D:L,9,0),"未到课") | S57: =IFERROR(VLOOKUP(A57,'微伴数据'!A:DB,12,0),"") | T57: =IFERROR(VLOOKUP(A57,'微伴数据'!A:DB,32,0),"") | U57: =IFERROR(VLOOKUP(A57,'微伴数据'!A:DC,81,0),"") | V57: =IFERROR(VLOOKUP(#REF!,'星橙地址'!A:V,9,0),"") | W57: =IFERROR(VLOOKUP(#REF!,'星橙地址'!A:V,10,0),"") | X57: =IFERROR(VLOOKUP(A57,'星云问卷'!A:O,8,0),"") | Y57: =IFERROR(VLOOKUP(A57,'星云问卷'!A:O,9,0),"") | Z57: =IFERROR(VLOOKUP(A57,'星云问卷'!A:O,10,0),"") | AA57: =IFERROR(VLOOKUP(A57,'星云问卷'!A:O,11,0),"") | AB57: =IFERROR(VLOOKUP(A57,'星云问卷'!A:O,12,0),"") | AC57: =IFERROR(VLOOKUP(A57,'星云问卷'!A:O,13,0),"") | AD57: =IFERROR(VLOOKUP(A57,'星云问卷'!A:O,14,0),"") | AE57: =IFERROR(VLOOKUP(A57,'星云问卷'!A:O,15,0),"") | AF57: =IFERROR(VLOOKUP(A57,'微伴数据'!A:DB,72,0),"") | AL57: =CONCATENATE( " 我把体验营用户专属福利给你发一下哈：" & CHAR(10) & CHAR(10), "1.《抖音商业IP课》" & CHAR(10), "兑换码：", AG57, CHAR(10), "兑换码使用地址：https://appamvpb5mq9834.h5.xiaoeknow.com/p/t/v1/ecommerce/mkt/redeem_index" & CHAR(10) & CHAR(10), "2.《生财有术66个项目精选》" & CHAR(10), "兑换码：", AH57, CHAR(10), "使用方式：微信搜索小报童投递-点击开始阅读-点击生财有术项目精选即可" & CHAR(10) & CHAR(10), "3.《生财365问》" & CHAR(10), "兑换码：", AI57, CHAR(10), "使用方式：https://appamvpb5mq9834.h5.xiaoeknow.com/p/t/v1/ecommerce/mkt/redeem_index")
A58: =IF('微伴数据'!A55="","",'微伴数据'!A55) | B58: =IF('微伴数据'!B55="","",'微伴数据'!B55) | C58: =IF('微伴数据'!G55="","",'微伴数据'!G55) | D58: =IF('微伴数据'!D55="","",'微伴数据'!D55) | E58: =IF('微伴数据'!CR55="","",'微伴数据'!CR55) | F58: =IF('微伴数据'!CL55="","",'微伴数据'!CL55) | G58: B | H58: 建联 | I58: =VLOOKUP(A58,'Sheet9'!A:A,1,0) | K58: =T58&CHAR(10)&U58&CHAR(10)&V58&CHAR(10)&Y58&CHAR(10)&Z58&CHAR(10)&AA58&CHAR(10)&AB58&CHAR(10)&AC58&CHAR(10)&AD58&CHAR(10)&AE58 | L58: =IFERROR(VLOOKUP(#REF!,'第一课直播'!D:L,9,0),IFERROR(VLOOKUP('第一课回放'!C:H,5,0),"未到课")) | M58: =IFERROR(VLOOKUP(#REF!,'第一课回放'!C:H,5,0),"0:00:00") | N58: =IFERROR(VLOOKUP(#REF!,'第二课直播'!D:L,9,0),"未到课") | S58: =IFERROR(VLOOKUP(A58,'微伴数据'!A:DB,12,0),"") | T58: =IFERROR(VLOOKUP(A58,'微伴数据'!A:DB,32,0),"") | U58: =IFERROR(VLOOKUP(A58,'微伴数据'!A:DC,81,0),"") | V58: =IFERROR(VLOOKUP(#REF!,'星橙地址'!A:V,9,0),"") | W58: =IFERROR(VLOOKUP(#REF!,'星橙地址'!A:V,10,0),"") | X58: =IFERROR(VLOOKUP(A58,'星云问卷'!A:O,8,0),"") | Y58: =IFERROR(VLOOKUP(A58,'星云问卷'!A:O,9,0),"") | Z58: =IFERROR(VLOOKUP(A58,'星云问卷'!A:O,10,0),"") | AA58: =IFERROR(VLOOKUP(A58,'星云问卷'!A:O,11,0),"") | AB58: =IFERROR(VLOOKUP(A58,'星云问卷'!A:O,12,0),"") | AC58: =IFERROR(VLOOKUP(A58,'星云问卷'!A:O,13,0),"") | AD58: =IFERROR(VLOOKUP(A58,'星云问卷'!A:O,14,0),"") | AE58: =IFERROR(VLOOKUP(A58,'星云问卷'!A:O,15,0),"") | AF58: =IFERROR(VLOOKUP(A58,'微伴数据'!A:DB,72,0),"") | AG58: 5483AuhQ | AH58: https://xiaobot.net/invitation/3aef4-1e417-c1592-019f7/ | AI58: 6dhveNEA | AL58: =CONCATENATE( " 我把体验营用户专属福利给你发一下哈：" & CHAR(10) & CHAR(10), "1.《抖音商业IP课》" & CHAR(10), "兑换码：", AG58, CHAR(10), "兑换码使用地址：https://appamvpb5mq9834.h5.xiaoeknow.com/p/t/v1/ecommerce/mkt/redeem_index" & CHAR(10) & CHAR(10), "2.《生财有术66个项目精选》" & CHAR(10), "兑换码：", AH58, CHAR(10), "使用方式：微信搜索小报童投递-点击开始阅读-点击生财有术项目精选即可" & CHAR(10) & CHAR(10), "3.《生财365问》" & CHAR(10), "兑换码：", AI58, CHAR(10), "使用方式：https://appamvpb5mq9834.h5.xiaoeknow.com/p/t/v1/ecommerce/mkt/redeem_index")
A59: =IF('微伴数据'!A56="","",'微伴数据'!A56) | B59: =IF('微伴数据'!B56="","",'微伴数据'!B56) | C59: =IF('微伴数据'!G56="","",'微伴数据'!G56) | D59: =IF('微伴数据'!D56="","",'微伴数据'!D56) | E59: =IF('微伴数据'!CR56="","",'微伴数据'!CR56) | F59: =IF('微伴数据'!CL56="","",'微伴数据'!CL56) | G59: B | H59: 建联 | I59: =VLOOKUP(A59,'Sheet9'!A:A,1,0) | K59: =T59&CHAR(10)&U59&CHAR(10)&V59&CHAR(10)&Y59&CHAR(10)&Z59&CHAR(10)&AA59&CHAR(10)&AB59&CHAR(10)&AC59&CHAR(10)&AD59&CHAR(10)&AE59 | L59: =IFERROR(VLOOKUP(#REF!,'第一课直播'!D:L,9,0),IFERROR(VLOOKUP('第一课回放'!C:H,5,0),"未到课")) | M59: =IFERROR(VLOOKUP(#REF!,'第一课回放'!C:H,5,0),"0:00:00") | N59: =IFERROR(VLOOKUP(#REF!,'第二课直播'!D:L,9,0),"未到课") | S59: =IFERROR(VLOOKUP(A59,'微伴数据'!A:DB,12,0),"") | T59: =IFERROR(VLOOKUP(A59,'微伴数据'!A:DB,32,0),"") | U59: =IFERROR(VLOOKUP(A59,'微伴数据'!A:DC,81,0),"") | V59: =IFERROR(VLOOKUP(#REF!,'星橙地址'!A:V,9,0),"") | W59: =IFERROR(VLOOKUP(#REF!,'星橙地址'!A:V,10,0),"") | X59: =IFERROR(VLOOKUP(A59,'星云问卷'!A:O,8,0),"") | Y59: =IFERROR(VLOOKUP(A59,'星云问卷'!A:O,9,0),"") | Z59: =IFERROR(VLOOKUP(A59,'星云问卷'!A:O,10,0),"") | AA59: =IFERROR(VLOOKUP(A59,'星云问卷'!A:O,11,0),"") | AB59: =IFERROR(VLOOKUP(A59,'星云问卷'!A:O,12,0),"") | AC59: =IFERROR(VLOOKUP(A59,'星云问卷'!A:O,13,0),"") | AD59: =IFERROR(VLOOKUP(A59,'星云问卷'!A:O,14,0),"") | AE59: =IFERROR(VLOOKUP(A59,'星云问卷'!A:O,15,0),"") | AF59: =IFERROR(VLOOKUP(A59,'微伴数据'!A:DB,72,0),"") | AG59: 54AmEmMa | AH59: https://xiaobot.net/invitation/68649-0204c-48fb2-9f81f/ | AI59: 6dqbXncE | AL59: =CONCATENATE( " 我把体验营用户专属福利给你发一下哈：" & CHAR(10) & CHAR(10), "1.《抖音商业IP课》" & CHAR(10), "兑换码：", AG59, CHAR(10), "兑换码使用地址：https://appamvpb5mq9834.h5.xiaoeknow.com/p/t/v1/ecommerce/mkt/redeem_index" & CHAR(10) & CHAR(10), "2.《生财有术66个项目精选》" & CHAR(10), "兑换码：", AH59, CHAR(10), "使用方式：微信搜索小报童投递-点击开始阅读-点击生财有术项目精选即可" & CHAR(10) & CHAR(10), "3.《生财365问》" & CHAR(10), "兑换码：", AI59, CHAR(10), "使用方式：https://appamvpb5mq9834.h5.xiaoeknow.com/p/t/v1/ecommerce/mkt/redeem_index")
A60: =IF('微伴数据'!A57="","",'微伴数据'!A57) | B60: =IF('微伴数据'!B57="","",'微伴数据'!B57) | C60: =IF('微伴数据'!G57="","",'微伴数据'!G57) | D60: =IF('微伴数据'!D57="","",'微伴数据'!D57) | E60: =IF('微伴数据'!CR57="","",'微伴数据'!CR57) | F60: =IF('微伴数据'!CL57="","",'微伴数据'!CL57) | G60: A | H60: 建联 | I60: =VLOOKUP(A60,'Sheet9'!A:A,1,0) | K60: =T60&CHAR(10)&U60&CHAR(10)&V60&CHAR(10)&Y60&CHAR(10)&Z60&CHAR(10)&AA60&CHAR(10)&AB60&CHAR(10)&AC60&CHAR(10)&AD60&CHAR(10)&AE60 | L60: =IFERROR(VLOOKUP(#REF!,'第一课直播'!D:L,9,0),IFERROR(VLOOKUP('第一课回放'!C:H,5,0),"未到课")) | M60: =IFERROR(VLOOKUP(#REF!,'第一课回放'!C:H,5,0),"0:00:00") | N60: =IFERROR(VLOOKUP(#REF!,'第二课直播'!D:L,9,0),"未到课") | S60: =IFERROR(VLOOKUP(A60,'微伴数据'!A:DB,12,0),"") | T60: =IFERROR(VLOOKUP(A60,'微伴数据'!A:DB,32,0),"") | U60: =IFERROR(VLOOKUP(A60,'微伴数据'!A:DC,81,0),"") | V60: =IFERROR(VLOOKUP(#REF!,'星橙地址'!A:V,9,0),"") | W60: =IFERROR(VLOOKUP(#REF!,'星橙地址'!A:V,10,0),"") | X60: =IFERROR(VLOOKUP(A60,'星云问卷'!A:O,8,0),"") | Y60: =IFERROR(VLOOKUP(A60,'星云问卷'!A:O,9,0),"") | Z60: =IFERROR(VLOOKUP(A60,'星云问卷'!A:O,10,0),"") | AA60: =IFERROR(VLOOKUP(A60,'星云问卷'!A:O,11,0),"") | AB60: =IFERROR(VLOOKUP(A60,'星云问卷'!A:O,12,0),"") | AC60: =IFERROR(VLOOKUP(A60,'星云问卷'!A:O,13,0),"") | AD60: =IFERROR(VLOOKUP(A60,'星云问卷'!A:O,14,0),"") | AE60: =IFERROR(VLOOKUP(A60,'星云问卷'!A:O,15,0),"") | AF60: =IFERROR(VLOOKUP(A60,'微伴数据'!A:DB,72,0),"") | AG60: 54CkUt9b | AH60: https://xiaobot.net/invitation/4a5c8-c4cc8-b2d2e-40fbc/ | AI60: 6duNzEJ5 | AL60: =CONCATENATE( " 我把体验营用户专属福利给你发一下哈：" & CHAR(10) & CHAR(10), "1.《抖音商业IP课》" & CHAR(10), "兑换码：", AG60, CHAR(10), "兑换码使用地址：https://appamvpb5mq9834.h5.xiaoeknow.com/p/t/v1/ecommerce/mkt/redeem_index" & CHAR(10) & CHAR(10), "2.《生财有术66个项目精选》" & CHAR(10), "兑换码：", AH60, CHAR(10), "使用方式：微信搜索小报童投递-点击开始阅读-点击生财有术项目精选即可" & CHAR(10) & CHAR(10), "3.《生财365问》" & CHAR(10), "兑换码：", AI60, CHAR(10), "使用方式：https://appamvpb5mq9834.h5.xiaoeknow.com/p/t/v1/ecommerce/mkt/redeem_index")
A61: =IF('微伴数据'!A58="","",'微伴数据'!A58) | B61: =IF('微伴数据'!B58="","",'微伴数据'!B58) | C61: =IF('微伴数据'!G58="","",'微伴数据'!G58) | D61: =IF('微伴数据'!D58="","",'微伴数据'!D58) | E61: =IF('微伴数据'!CR58="","",'微伴数据'!CR58) | F61: =IF('微伴数据'!CL58="","",'微伴数据'!CL58) | G61: B | H61: 建联 | I61: =VLOOKUP(A61,'Sheet9'!A:A,1,0) | K61: =T61&CHAR(10)&U61&CHAR(10)&V61&CHAR(10)&Y61&CHAR(10)&Z61&CHAR(10)&AA61&CHAR(10)&AB61&CHAR(10)&AC61&CHAR(10)&AD61&CHAR(10)&AE61 | L61: =IFERROR(VLOOKUP(#REF!,'第一课直播'!D:L,9,0),IFERROR(VLOOKUP('第一课回放'!C:H,5,0),"未到课")) | M61: =IFERROR(VLOOKUP(#REF!,'第一课回放'!C:H,5,0),"0:00:00") | N61: =IFERROR(VLOOKUP(#REF!,'第二课直播'!D:L,9,0),"未到课") | S61: =IFERROR(VLOOKUP(A61,'微伴数据'!A:DB,12,0),"") | T61: =IFERROR(VLOOKUP(A61,'微伴数据'!A:DB,32,0),"") | U61: =IFERROR(VLOOKUP(A61,'微伴数据'!A:DC,81,0),"") | V61: =IFERROR(VLOOKUP(#REF!,'星橙地址'!A:V,9,0),"") | W61: =IFERROR(VLOOKUP(#REF!,'星橙地址'!A:V,10,0),"") | X61: =IFERROR(VLOOKUP(A61,'星云问卷'!A:O,8,0),"") | Y61: =IFERROR(VLOOKUP(A61,'星云问卷'!A:O,9,0),"") | Z61: =IFERROR(VLOOKUP(A61,'星云问卷'!A:O,10,0),"") | AA61: =IFERROR(VLOOKUP(A61,'星云问卷'!A:O,11,0),"") | AB61: =IFERROR(VLOOKUP(A61,'星云问卷'!A:O,12,0),"") | AC61: =IFERROR(VLOOKUP(A61,'星云问卷'!A:O,13,0),"") | AD61: =IFERROR(VLOOKUP(A61,'星云问卷'!A:O,14,0),"") | AE61: =IFERROR(VLOOKUP(A61,'星云问卷'!A:O,15,0),"") | AF61: =IFERROR(VLOOKUP(A61,'微伴数据'!A:DB,72,0),"") | AL61: =CONCATENATE( " 我把体验营用户专属福利给你发一下哈：" & CHAR(10) & CHAR(10), "1.《抖音商业IP课》" & CHAR(10), "兑换码：", AG61, CHAR(10), "兑换码使用地址：https://appamvpb5mq9834.h5.xiaoeknow.com/p/t/v1/ecommerce/mkt/redeem_index" & CHAR(10) & CHAR(10), "2.《生财有术66个项目精选》" & CHAR(10), "兑换码：", AH61, CHAR(10), "使用方式：微信搜索小报童投递-点击开始阅读-点击生财有术项目精选即可" & CHAR(10) & CHAR(10), "3.《生财365问》" & CHAR(10), "兑换码：", AI61, CHAR(10), "使用方式：https://appamvpb5mq9834.h5.xiaoeknow.com/p/t/v1/ecommerce/mkt/redeem_index")
A62: =IF('微伴数据'!A59="","",'微伴数据'!A59) | B62: =IF('微伴数据'!B59="","",'微伴数据'!B59) | C62: =IF('微伴数据'!G59="","",'微伴数据'!G59) | D62: =IF('微伴数据'!D59="","",'微伴数据'!D59) | E62: =IF('微伴数据'!CR59="","",'微伴数据'!CR59) | F62: =IF('微伴数据'!CL59="","",'微伴数据'!CL59) | G62: A | H62: 建联 | I62: =VLOOKUP(A62,'Sheet9'!A:A,1,0) | J62: 我现在有做视频号和小红书，主要是发视频，剪辑一部美剧，进行二创，有自己的翻译，背景音乐等，我本身是英语专八，想通过这部剧来后期卖自己的英语课程，剧中人文相关的周边，我只磕这一部美剧，所有后端产品都是和这部美剧直接相关。现在视频号粉丝6000+，小红书最近刚开始发，也1000+了，现在后端产品都还没上线，因为有一个顾虑，就是我这样算不算侵权，后续产品上线了有没有其他可能的隐患？小红书的笔记多次被判违规[捂脸] | K62: =T62&CHAR(10)&U62&CHAR(10)&V62&CHAR(10)&Y62&CHAR(10)&Z62&CHAR(10)&AA62&CHAR(10)&AB62&CHAR(10)&AC62&CHAR(10)&AD62&CHAR(10)&AE62 | L62: =IFERROR(VLOOKUP(#REF!,'第一课直播'!D:L,9,0),IFERROR(VLOOKUP('第一课回放'!C:H,5,0),"未到课")) | M62: =IFERROR(VLOOKUP(#REF!,'第一课回放'!C:H,5,0),"0:00:00") | N62: =IFERROR(VLOOKUP(#REF!,'第二课直播'!D:L,9,0),"未到课") | S62: =IFERROR(VLOOKUP(A62,'微伴数据'!A:DB,12,0),"") | T62: =IFERROR(VLOOKUP(A62,'微伴数据'!A:DB,32,0),"") | U62: =IFERROR(VLOOKUP(A62,'微伴数据'!A:DC,81,0),"") | V62: =IFERROR(VLOOKUP(#REF!,'星橙地址'!A:V,9,0),"") | W62: =IFERROR(VLOOKUP(#REF!,'星橙地址'!A:V,10,0),"") | X62: =IFERROR(VLOOKUP(A62,'星云问卷'!A:O,8,0),"") | Y62: =IFERROR(VLOOKUP(A62,'星云问卷'!A:O,9,0),"") | Z62: =IFERROR(VLOOKUP(A62,'星云问卷'!A:O,10,0),"") | AA62: =IFERROR(VLOOKUP(A62,'星云问卷'!A:O,11,0),"") | AB62: =IFERROR(VLOOKUP(A62,'星云问卷'!A:O,12,0),"") | AC62: =IFERROR(VLOOKUP(A62,'星云问卷'!A:O,13,0),"") | AD62: =IFERROR(VLOOKUP(A62,'星云问卷'!A:O,14,0),"") | AE62: =IFERROR(VLOOKUP(A62,'星云问卷'!A:O,15,0),"") | AF62: =IFERROR(VLOOKUP(A62,'微伴数据'!A:DB,72,0),"") | AL62: =CONCATENATE( " 我把体验营用户专属福利给你发一下哈：" & CHAR(10) & CHAR(10), "1.《抖音商业IP课》" & CHAR(10), "兑换码：", AG62, CHAR(10), "兑换码使用地址：https://appamvpb5mq9834.h5.xiaoeknow.com/p/t/v1/ecommerce/mkt/redeem_index" & CHAR(10) & CHAR(10), "2.《生财有术66个项目精选》" & CHAR(10), "兑换码：", AH62, CHAR(10), "使用方式：微信搜索小报童投递-点击开始阅读-点击生财有术项目精选即可" & CHAR(10) & CHAR(10), "3.《生财365问》" & CHAR(10), "兑换码：", AI62, CHAR(10), "使用方式：https://appamvpb5mq9834.h5.xiaoeknow.com/p/t/v1/ecommerce/mkt/redeem_index") | AO62: 纳入用户画像
A63: =IF('微伴数据'!A60="","",'微伴数据'!A60) | B63: =IF('微伴数据'!B60="","",'微伴数据'!B60) | C63: =IF('微伴数据'!G60="","",'微伴数据'!G60) | D63: =IF('微伴数据'!D60="","",'微伴数据'!D60) | E63: =IF('微伴数据'!CR60="","",'微伴数据'!CR60) | F63: =IF('微伴数据'!CL60="","",'微伴数据'!CL60) | G63: B | H63: 建联 | I63: =VLOOKUP(A63,'Sheet9'!A:A,1,0) | K63: =T63&CHAR(10)&U63&CHAR(10)&V63&CHAR(10)&Y63&CHAR(10)&Z63&CHAR(10)&AA63&CHAR(10)&AB63&CHAR(10)&AC63&CHAR(10)&AD63&CHAR(10)&AE63 | L63: =IFERROR(VLOOKUP(#REF!,'第一课直播'!D:L,9,0),IFERROR(VLOOKUP('第一课回放'!C:H,5,0),"未到课")) | M63: =IFERROR(VLOOKUP(#REF!,'第一课回放'!C:H,5,0),"0:00:00") | N63: =IFERROR(VLOOKUP(#REF!,'第二课直播'!D:L,9,0),"未到课") | S63: =IFERROR(VLOOKUP(A63,'微伴数据'!A:DB,12,0),"") | T63: =IFERROR(VLOOKUP(A63,'微伴数据'!A:DB,32,0),"") | U63: =IFERROR(VLOOKUP(A63,'微伴数据'!A:DC,81,0),"") | V63: =IFERROR(VLOOKUP(#REF!,'星橙地址'!A:V,9,0),"") | W63: =IFERROR(VLOOKUP(#REF!,'星橙地址'!A:V,10,0),"") | X63: =IFERROR(VLOOKUP(A63,'星云问卷'!A:O,8,0),"") | Y63: =IFERROR(VLOOKUP(A63,'星云问卷'!A:O,9,0),"") | Z63: =IFERROR(VLOOKUP(A63,'星云问卷'!A:O,10,0),"") | AA63: =IFERROR(VLOOKUP(A63,'星云问卷'!A:O,11,0),"") | AB63: =IFERROR(VLOOKUP(A63,'星云问卷'!A:O,12,0),"") | AC63: =IFERROR(VLOOKUP(A63,'星云问卷'!A:O,13,0),"") | AD63: =IFERROR(VLOOKUP(A63,'星云问卷'!A:O,14,0),"") | AE63: =IFERROR(VLOOKUP(A63,'星云问卷'!A:O,15,0),"") | AF63: =IFERROR(VLOOKUP(A63,'微伴数据'!A:DB,72,0),"") | AL63: =CONCATENATE( " 我把体验营用户专属福利给你发一下哈：" & CHAR(10) & CHAR(10), "1.《抖音商业IP课》" & CHAR(10), "兑换码：", AG63, CHAR(10), "兑换码使用地址：https://appamvpb5mq9834.h5.xiaoeknow.com/p/t/v1/ecommerce/mkt/redeem_index" & CHAR(10) & CHAR(10), "2.《生财有术66个项目精选》" & CHAR(10), "兑换码：", AH63, CHAR(10), "使用方式：微信搜索小报童投递-点击开始阅读-点击生财有术项目精选即可" & CHAR(10) & CHAR(10), "3.《生财365问》" & CHAR(10), "兑换码：", AI63, CHAR(10), "使用方式：https://appamvpb5mq9834.h5.xiaoeknow.com/p/t/v1/ecommerce/mkt/redeem_index")
A64: =IF('微伴数据'!A61="","",'微伴数据'!A61) | B64: =IF('微伴数据'!B61="","",'微伴数据'!B61) | C64: =IF('微伴数据'!G61="","",'微伴数据'!G61) | D64: =IF('微伴数据'!D61="","",'微伴数据'!D61) | E64: =IF('微伴数据'!CR61="","",'微伴数据'!CR61) | F64: =IF('微伴数据'!CL61="","",'微伴数据'!CL61) | G64: B | H64: 建联 | I64: =VLOOKUP(A64,'Sheet9'!A:A,1,0) | K64: =T64&CHAR(10)&U64&CHAR(10)&V64&CHAR(10)&Y64&CHAR(10)&Z64&CHAR(10)&AA64&CHAR(10)&AB64&CHAR(10)&AC64&CHAR(10)&AD64&CHAR(10)&AE64 | L64: =IFERROR(VLOOKUP(#REF!,'第一课直播'!D:L,9,0),IFERROR(VLOOKUP('第一课回放'!C:H,5,0),"未到课")) | M64: =IFERROR(VLOOKUP(#REF!,'第一课回放'!C:H,5,0),"0:00:00") | N64: =IFERROR(VLOOKUP(#REF!,'第二课直播'!D:L,9,0),"未到课") | S64: =IFERROR(VLOOKUP(A64,'微伴数据'!A:DB,12,0),"") | T64: =IFERROR(VLOOKUP(A64,'微伴数据'!A:DB,32,0),"") | U64: =IFERROR(VLOOKUP(A64,'微伴数据'!A:DC,81,0),"") | V64: =IFERROR(VLOOKUP(#REF!,'星橙地址'!A:V,9,0),"") | W64: =IFERROR(VLOOKUP(#REF!,'星橙地址'!A:V,10,0),"") | X64: =IFERROR(VLOOKUP(A64,'星云问卷'!A:O,8,0),"") | Y64: =IFERROR(VLOOKUP(A64,'星云问卷'!A:O,9,0),"") | Z64: =IFERROR(VLOOKUP(A64,'星云问卷'!A:O,10,0),"") | AA64: =IFERROR(VLOOKUP(A64,'星云问卷'!A:O,11,0),"") | AB64: =IFERROR(VLOOKUP(A64,'星云问卷'!A:O,12,0),"") | AC64: =IFERROR(VLOOKUP(A64,'星云问卷'!A:O,13,0),"") | AD64: =IFERROR(VLOOKUP(A64,'星云问卷'!A:O,14,0),"") | AE64: =IFERROR(VLOOKUP(A64,'星云问卷'!A:O,15,0),"") | AF64: =IFERROR(VLOOKUP(A64,'微伴数据'!A:DB,72,0),"") | AL64: =CONCATENATE( " 我把体验营用户专属福利给你发一下哈：" & CHAR(10) & CHAR(10), "1.《抖音商业IP课》" & CHAR(10), "兑换码：", AG64, CHAR(10), "兑换码使用地址：https://appamvpb5mq9834.h5.xiaoeknow.com/p/t/v1/ecommerce/mkt/redeem_index" & CHAR(10) & CHAR(10), "2.《生财有术66个项目精选》" & CHAR(10), "兑换码：", AH64, CHAR(10), "使用方式：微信搜索小报童投递-点击开始阅读-点击生财有术项目精选即可" & CHAR(10) & CHAR(10), "3.《生财365问》" & CHAR(10), "兑换码：", AI64, CHAR(10), "使用方式：https://appamvpb5mq9834.h5.xiaoeknow.com/p/t/v1/ecommerce/mkt/redeem_index")
A65: =IF('微伴数据'!A62="","",'微伴数据'!A62) | B65: =IF('微伴数据'!B62="","",'微伴数据'!B62) | C65: =IF('微伴数据'!G62="","",'微伴数据'!G62) | D65: =IF('微伴数据'!D62="","",'微伴数据'!D62) | E65: =IF('微伴数据'!CR62="","",'微伴数据'!CR62) | F65: =IF('微伴数据'!CL62="","",'微伴数据'!CL62) | G65: B | H65: 建联 | I65: =VLOOKUP(A65,'Sheet9'!A:A,1,0) | K65: =T65&CHAR(10)&U65&CHAR(10)&V65&CHAR(10)&Y65&CHAR(10)&Z65&CHAR(10)&AA65&CHAR(10)&AB65&CHAR(10)&AC65&CHAR(10)&AD65&CHAR(10)&AE65 | L65: =IFERROR(VLOOKUP(#REF!,'第一课直播'!D:L,9,0),IFERROR(VLOOKUP('第一课回放'!C:H,5,0),"未到课")) | M65: =IFERROR(VLOOKUP(#REF!,'第一课回放'!C:H,5,0),"0:00:00") | N65: =IFERROR(VLOOKUP(#REF!,'第二课直播'!D:L,9,0),"未到课") | S65: =IFERROR(VLOOKUP(A65,'微伴数据'!A:DB,12,0),"") | T65: =IFERROR(VLOOKUP(A65,'微伴数据'!A:DB,32,0),"") | U65: =IFERROR(VLOOKUP(A65,'微伴数据'!A:DC,81,0),"") | V65: =IFERROR(VLOOKUP(#REF!,'星橙地址'!A:V,9,0),"") | W65: =IFERROR(VLOOKUP(#REF!,'星橙地址'!A:V,10,0),"") | X65: =IFERROR(VLOOKUP(A65,'星云问卷'!A:O,8,0),"") | Y65: =IFERROR(VLOOKUP(A65,'星云问卷'!A:O,9,0),"") | Z65: =IFERROR(VLOOKUP(A65,'星云问卷'!A:O,10,0),"") | AA65: =IFERROR(VLOOKUP(A65,'星云问卷'!A:O,11,0),"") | AB65: =IFERROR(VLOOKUP(A65,'星云问卷'!A:O,12,0),"") | AC65: =IFERROR(VLOOKUP(A65,'星云问卷'!A:O,13,0),"") | AD65: =IFERROR(VLOOKUP(A65,'星云问卷'!A:O,14,0),"") | AE65: =IFERROR(VLOOKUP(A65,'星云问卷'!A:O,15,0),"") | AF65: =IFERROR(VLOOKUP(A65,'微伴数据'!A:DB,72,0),"") | AL65: =CONCATENATE( " 我把体验营用户专属福利给你发一下哈：" & CHAR(10) & CHAR(10), "1.《抖音商业IP课》" & CHAR(10), "兑换码：", AG65, CHAR(10), "兑换码使用地址：https://appamvpb5mq9834.h5.xiaoeknow.com/p/t/v1/ecommerce/mkt/redeem_index" & CHAR(10) & CHAR(10), "2.《生财有术66个项目精选》" & CHAR(10), "兑换码：", AH65, CHAR(10), "使用方式：微信搜索小报童投递-点击开始阅读-点击生财有术项目精选即可" & CHAR(10) & CHAR(10), "3.《生财365问》" & CHAR(10), "兑换码：", AI65, CHAR(10), "使用方式：https://appamvpb5mq9834.h5.xiaoeknow.com/p/t/v1/ecommerce/mkt/redeem_index")
A66: =IF('微伴数据'!A63="","",'微伴数据'!A63) | B66: =IF('微伴数据'!B63="","",'微伴数据'!B63) | C66: =IF('微伴数据'!G63="","",'微伴数据'!G63) | D66: =IF('微伴数据'!D63="","",'微伴数据'!D63) | E66: =IF('微伴数据'!CR63="","",'微伴数据'!CR63) | F66: =IF('微伴数据'!CL63="","",'微伴数据'!CL63) | G66: B | H66: 建联 | I66: =VLOOKUP(A66,'Sheet9'!A:A,1,0) | K66: =T66&CHAR(10)&U66&CHAR(10)&V66&CHAR(10)&Y66&CHAR(10)&Z66&CHAR(10)&AA66&CHAR(10)&AB66&CHAR(10)&AC66&CHAR(10)&AD66&CHAR(10)&AE66 | L66: =IFERROR(VLOOKUP(#REF!,'第一课直播'!D:L,9,0),IFERROR(VLOOKUP('第一课回放'!C:H,5,0),"未到课")) | M66: =IFERROR(VLOOKUP(#REF!,'第一课回放'!C:H,5,0),"0:00:00") | N66: =IFERROR(VLOOKUP(#REF!,'第二课直播'!D:L,9,0),"未到课") | S66: =IFERROR(VLOOKUP(A66,'微伴数据'!A:DB,12,0),"") | T66: =IFERROR(VLOOKUP(A66,'微伴数据'!A:DB,32,0),"") | U66: =IFERROR(VLOOKUP(A66,'微伴数据'!A:DC,81,0),"") | V66: =IFERROR(VLOOKUP(#REF!,'星橙地址'!A:V,9,0),"") | W66: =IFERROR(VLOOKUP(#REF!,'星橙地址'!A:V,10,0),"") | X66: =IFERROR(VLOOKUP(A66,'星云问卷'!A:O,8,0),"") | Y66: =IFERROR(VLOOKUP(A66,'星云问卷'!A:O,9,0),"") | Z66: =IFERROR(VLOOKUP(A66,'星云问卷'!A:O,10,0),"") | AA66: =IFERROR(VLOOKUP(A66,'星云问卷'!A:O,11,0),"") | AB66: =IFERROR(VLOOKUP(A66,'星云问卷'!A:O,12,0),"") | AC66: =IFERROR(VLOOKUP(A66,'星云问卷'!A:O,13,0),"") | AD66: =IFERROR(VLOOKUP(A66,'星云问卷'!A:O,14,0),"") | AE66: =IFERROR(VLOOKUP(A66,'星云问卷'!A:O,15,0),"") | AF66: =IFERROR(VLOOKUP(A66,'微伴数据'!A:DB,72,0),"") | AL66: =CONCATENATE( " 我把体验营用户专属福利给你发一下哈：" & CHAR(10) & CHAR(10), "1.《抖音商业IP课》" & CHAR(10), "兑换码：", AG66, CHAR(10), "兑换码使用地址：https://appamvpb5mq9834.h5.xiaoeknow.com/p/t/v1/ecommerce/mkt/redeem_index" & CHAR(10) & CHAR(10), "2.《生财有术66个项目精选》" & CHAR(10), "兑换码：", AH66, CHAR(10), "使用方式：微信搜索小报童投递-点击开始阅读-点击生财有术项目精选即可" & CHAR(10) & CHAR(10), "3.《生财365问》" & CHAR(10), "兑换码：", AI66, CHAR(10), "使用方式：https://appamvpb5mq9834.h5.xiaoeknow.com/p/t/v1/ecommerce/mkt/redeem_index")
A67: =IF('微伴数据'!A64="","",'微伴数据'!A64) | B67: =IF('微伴数据'!B64="","",'微伴数据'!B64) | C67: =IF('微伴数据'!G64="","",'微伴数据'!G64) | D67: =IF('微伴数据'!D64="","",'微伴数据'!D64) | E67: =IF('微伴数据'!CR64="","",'微伴数据'!CR64) | F67: =IF('微伴数据'!CL64="","",'微伴数据'!CL64) | G67: B | H67: 建联 | I67: =VLOOKUP(A67,'Sheet9'!A:A,1,0) | K67: =T67&CHAR(10)&U67&CHAR(10)&V67&CHAR(10)&Y67&CHAR(10)&Z67&CHAR(10)&AA67&CHAR(10)&AB67&CHAR(10)&AC67&CHAR(10)&AD67&CHAR(10)&AE67 | L67: =IFERROR(VLOOKUP(#REF!,'第一课直播'!D:L,9,0),IFERROR(VLOOKUP('第一课回放'!C:H,5,0),"未到课")) | M67: =IFERROR(VLOOKUP(#REF!,'第一课回放'!C:H,5,0),"0:00:00") | N67: =IFERROR(VLOOKUP(#REF!,'第二课直播'!D:L,9,0),"未到课") | S67: =IFERROR(VLOOKUP(A67,'微伴数据'!A:DB,12,0),"") | T67: =IFERROR(VLOOKUP(A67,'微伴数据'!A:DB,32,0),"") | U67: =IFERROR(VLOOKUP(A67,'微伴数据'!A:DC,81,0),"") | V67: =IFERROR(VLOOKUP(#REF!,'星橙地址'!A:V,9,0),"") | W67: =IFERROR(VLOOKUP(#REF!,'星橙地址'!A:V,10,0),"") | X67: =IFERROR(VLOOKUP(A67,'星云问卷'!A:O,8,0),"") | Y67: =IFERROR(VLOOKUP(A67,'星云问卷'!A:O,9,0),"") | Z67: =IFERROR(VLOOKUP(A67,'星云问卷'!A:O,10,0),"") | AA67: =IFERROR(VLOOKUP(A67,'星云问卷'!A:O,11,0),"") | AB67: =IFERROR(VLOOKUP(A67,'星云问卷'!A:O,12,0),"") | AC67: =IFERROR(VLOOKUP(A67,'星云问卷'!A:O,13,0),"") | AD67: =IFERROR(VLOOKUP(A67,'星云问卷'!A:O,14,0),"") | AE67: =IFERROR(VLOOKUP(A67,'星云问卷'!A:O,15,0),"") | AF67: =IFERROR(VLOOKUP(A67,'微伴数据'!A:DB,72,0),"") | AL67: =CONCATENATE( " 我把体验营用户专属福利给你发一下哈：" & CHAR(10) & CHAR(10), "1.《抖音商业IP课》" & CHAR(10), "兑换码：", AG67, CHAR(10), "兑换码使用地址：https://appamvpb5mq9834.h5.xiaoeknow.com/p/t/v1/ecommerce/mkt/redeem_index" & CHAR(10) & CHAR(10), "2.《生财有术66个项目精选》" & CHAR(10), "兑换码：", AH67, CHAR(10), "使用方式：微信搜索小报童投递-点击开始阅读-点击生财有术项目精选即可" & CHAR(10) & CHAR(10), "3.《生财365问》" & CHAR(10), "兑换码：", AI67, CHAR(10), "使用方式：https://appamvpb5mq9834.h5.xiaoeknow.com/p/t/v1/ecommerce/mkt/redeem_index")
A68: =IF('微伴数据'!A65="","",'微伴数据'!A65) | B68: =IF('微伴数据'!B65="","",'微伴数据'!B65) | C68: =IF('微伴数据'!G65="","",'微伴数据'!G65) | D68: =IF('微伴数据'!D65="","",'微伴数据'!D65) | E68: =IF('微伴数据'!CR65="","",'微伴数据'!CR65) | F68: =IF('微伴数据'!CL65="","",'微伴数据'!CL65) | G68: A | H68: 建联 | I68: =VLOOKUP(A68,'Sheet9'!A:A,1,0) | K68: =T68&CHAR(10)&U68&CHAR(10)&V68&CHAR(10)&Y68&CHAR(10)&Z68&CHAR(10)&AA68&CHAR(10)&AB68&CHAR(10)&AC68&CHAR(10)&AD68&CHAR(10)&AE68 | L68: =IFERROR(VLOOKUP(#REF!,'第一课直播'!D:L,9,0),IFERROR(VLOOKUP('第一课回放'!C:H,5,0),"未到课")) | M68: =IFERROR(VLOOKUP(#REF!,'第一课回放'!C:H,5,0),"0:00:00") | N68: =IFERROR(VLOOKUP(#REF!,'第二课直播'!D:L,9,0),"未到课") | S68: =IFERROR(VLOOKUP(A68,'微伴数据'!A:DB,12,0),"") | T68: =IFERROR(VLOOKUP(A68,'微伴数据'!A:DB,32,0),"") | U68: =IFERROR(VLOOKUP(A68,'微伴数据'!A:DC,81,0),"") | V68: =IFERROR(VLOOKUP(#REF!,'星橙地址'!A:V,9,0),"") | W68: =IFERROR(VLOOKUP(#REF!,'星橙地址'!A:V,10,0),"") | X68: =IFERROR(VLOOKUP(A68,'星云问卷'!A:O,8,0),"") | Y68: =IFERROR(VLOOKUP(A68,'星云问卷'!A:O,9,0),"") | Z68: =IFERROR(VLOOKUP(A68,'星云问卷'!A:O,10,0),"") | AA68: =IFERROR(VLOOKUP(A68,'星云问卷'!A:O,11,0),"") | AB68: =IFERROR(VLOOKUP(A68,'星云问卷'!A:O,12,0),"") | AC68: =IFERROR(VLOOKUP(A68,'星云问卷'!A:O,13,0),"") | AD68: =IFERROR(VLOOKUP(A68,'星云问卷'!A:O,14,0),"") | AE68: =IFERROR(VLOOKUP(A68,'星云问卷'!A:O,15,0),"") | AF68: =IFERROR(VLOOKUP(A68,'微伴数据'!A:DB,72,0),"") | AG68: 547jzkC9 | AH68: https://xiaobot.net/invitation/9a166-c9825-14415-d40a8/ | AI68: 6dhTUh3k | AL68: =CONCATENATE( " 我把体验营用户专属福利给你发一下哈：" & CHAR(10) & CHAR(10), "1.《抖音商业IP课》" & CHAR(10), "兑换码：", AG68, CHAR(10), "兑换码使用地址：https://appamvpb5mq9834.h5.xiaoeknow.com/p/t/v1/ecommerce/mkt/redeem_index" & CHAR(10) & CHAR(10), "2.《生财有术66个项目精选》" & CHAR(10), "兑换码：", AH68, CHAR(10), "使用方式：微信搜索小报童投递-点击开始阅读-点击生财有术项目精选即可" & CHAR(10) & CHAR(10), "3.《生财365问》" & CHAR(10), "兑换码：", AI68, CHAR(10), "使用方式：https://appamvpb5mq9834.h5.xiaoeknow.com/p/t/v1/ecommerce/mkt/redeem_index")
A69: =IF('微伴数据'!A66="","",'微伴数据'!A66) | B69: =IF('微伴数据'!B66="","",'微伴数据'!B66) | C69: =IF('微伴数据'!G66="","",'微伴数据'!G66) | D69: =IF('微伴数据'!D66="","",'微伴数据'!D66) | E69: =IF('微伴数据'!CR66="","",'微伴数据'!CR66) | F69: =IF('微伴数据'!CL66="","",'微伴数据'!CL66) | G69: B | H69: 建联 | I69: =VLOOKUP(A69,'Sheet9'!A:A,1,0) | K69: =T69&CHAR(10)&U69&CHAR(10)&V69&CHAR(10)&Y69&CHAR(10)&Z69&CHAR(10)&AA69&CHAR(10)&AB69&CHAR(10)&AC69&CHAR(10)&AD69&CHAR(10)&AE69 | L69: =IFERROR(VLOOKUP(#REF!,'第一课直播'!D:L,9,0),IFERROR(VLOOKUP('第一课回放'!C:H,5,0),"未到课")) | M69: =IFERROR(VLOOKUP(#REF!,'第一课回放'!C:H,5,0),"0:00:00") | N69: =IFERROR(VLOOKUP(#REF!,'第二课直播'!D:L,9,0),"未到课") | S69: =IFERROR(VLOOKUP(A69,'微伴数据'!A:DB,12,0),"") | T69: =IFERROR(VLOOKUP(A69,'微伴数据'!A:DB,32,0),"") | U69: =IFERROR(VLOOKUP(A69,'微伴数据'!A:DC,81,0),"") | V69: =IFERROR(VLOOKUP(#REF!,'星橙地址'!A:V,9,0),"") | W69: =IFERROR(VLOOKUP(#REF!,'星橙地址'!A:V,10,0),"") | X69: =IFERROR(VLOOKUP(A69,'星云问卷'!A:O,8,0),"") | Y69: =IFERROR(VLOOKUP(A69,'星云问卷'!A:O,9,0),"") | Z69: =IFERROR(VLOOKUP(A69,'星云问卷'!A:O,10,0),"") | AA69: =IFERROR(VLOOKUP(A69,'星云问卷'!A:O,11,0),"") | AB69: =IFERROR(VLOOKUP(A69,'星云问卷'!A:O,12,0),"") | AC69: =IFERROR(VLOOKUP(A69,'星云问卷'!A:O,13,0),"") | AD69: =IFERROR(VLOOKUP(A69,'星云问卷'!A:O,14,0),"") | AE69: =IFERROR(VLOOKUP(A69,'星云问卷'!A:O,15,0),"") | AF69: =IFERROR(VLOOKUP(A69,'微伴数据'!A:DB,72,0),"") | AG69: 54AeCCcQ | AH69: https://xiaobot.net/invitation/9ae8f-88c6e-5db2b-7a60a/ | AI69: 6dqVAvPP | AL69: =CONCATENATE( " 我把体验营用户专属福利给你发一下哈：" & CHAR(10) & CHAR(10), "1.《抖音商业IP课》" & CHAR(10), "兑换码：", AG69, CHAR(10), "兑换码使用地址：https://appamvpb5mq9834.h5.xiaoeknow.com/p/t/v1/ecommerce/mkt/redeem_index" & CHAR(10) & CHAR(10), "2.《生财有术66个项目精选》" & CHAR(10), "兑换码：", AH69, CHAR(10), "使用方式：微信搜索小报童投递-点击开始阅读-点击生财有术项目精选即可" & CHAR(10) & CHAR(10), "3.《生财365问》" & CHAR(10), "兑换码：", AI69, CHAR(10), "使用方式：https://appamvpb5mq9834.h5.xiaoeknow.com/p/t/v1/ecommerce/mkt/redeem_index")
A70: =IF('微伴数据'!A67="","",'微伴数据'!A67) | B70: =IF('微伴数据'!B67="","",'微伴数据'!B67) | C70: =IF('微伴数据'!G67="","",'微伴数据'!G67) | D70: =IF('微伴数据'!D67="","",'微伴数据'!D67) | E70: =IF('微伴数据'!CR67="","",'微伴数据'!CR67) | F70: =IF('微伴数据'!CL67="","",'微伴数据'!CL67) | G70: A | H70: 建联 | I70: =VLOOKUP(A70,'Sheet9'!A:A,1,0) | K70: =T70&CHAR(10)&U70&CHAR(10)&V70&CHAR(10)&Y70&CHAR(10)&Z70&CHAR(10)&AA70&CHAR(10)&AB70&CHAR(10)&AC70&CHAR(10)&AD70&CHAR(10)&AE70 | L70: =IFERROR(VLOOKUP(#REF!,'第一课直播'!D:L,9,0),IFERROR(VLOOKUP('第一课回放'!C:H,5,0),"未到课")) | M70: =IFERROR(VLOOKUP(#REF!,'第一课回放'!C:H,5,0),"0:00:00") | N70: =IFERROR(VLOOKUP(#REF!,'第二课直播'!D:L,9,0),"未到课") | S70: =IFERROR(VLOOKUP(A70,'微伴数据'!A:DB,12,0),"") | T70: =IFERROR(VLOOKUP(A70,'微伴数据'!A:DB,32,0),"") | U70: =IFERROR(VLOOKUP(A70,'微伴数据'!A:DC,81,0),"") | V70: =IFERROR(VLOOKUP(#REF!,'星橙地址'!A:V,9,0),"") | W70: =IFERROR(VLOOKUP(#REF!,'星橙地址'!A:V,10,0),"") | X70: =IFERROR(VLOOKUP(A70,'星云问卷'!A:O,8,0),"") | Y70: =IFERROR(VLOOKUP(A70,'星云问卷'!A:O,9,0),"") | Z70: =IFERROR(VLOOKUP(A70,'星云问卷'!A:O,10,0),"") | AA70: =IFERROR(VLOOKUP(A70,'星云问卷'!A:O,11,0),"") | AB70: =IFERROR(VLOOKUP(A70,'星云问卷'!A:O,12,0),"") | AC70: =IFERROR(VLOOKUP(A70,'星云问卷'!A:O,13,0),"") | AD70: =IFERROR(VLOOKUP(A70,'星云问卷'!A:O,14,0),"") | AE70: =IFERROR(VLOOKUP(A70,'星云问卷'!A:O,15,0),"") | AF70: =IFERROR(VLOOKUP(A70,'微伴数据'!A:DB,72,0),"") | AG70: 54AewVwb | AH70: https://xiaobot.net/invitation/91566-dd81f-8c8e0-c9912/ | AI70: 6dqVKgpt | AL70: =CONCATENATE( " 我把体验营用户专属福利给你发一下哈：" & CHAR(10) & CHAR(10), "1.《抖音商业IP课》" & CHAR(10), "兑换码：", AG70, CHAR(10), "兑换码使用地址：https://appamvpb5mq9834.h5.xiaoeknow.com/p/t/v1/ecommerce/mkt/redeem_index" & CHAR(10) & CHAR(10), "2.《生财有术66个项目精选》" & CHAR(10), "兑换码：", AH70, CHAR(10), "使用方式：微信搜索小报童投递-点击开始阅读-点击生财有术项目精选即可" & CHAR(10) & CHAR(10), "3.《生财365问》" & CHAR(10), "兑换码：", AI70, CHAR(10), "使用方式：https://appamvpb5mq9834.h5.xiaoeknow.com/p/t/v1/ecommerce/mkt/redeem_index") | AO70: 纳入用户画像
A71: =IF('微伴数据'!A68="","",'微伴数据'!A68) | B71: =IF('微伴数据'!B68="","",'微伴数据'!B68) | C71: =IF('微伴数据'!G68="","",'微伴数据'!G68) | D71: =IF('微伴数据'!D68="","",'微伴数据'!D68) | E71: =IF('微伴数据'!CR68="","",'微伴数据'!CR68) | F71: =IF('微伴数据'!CL68="","",'微伴数据'!CL68) | G71: A | H71: 建联 | I71: =VLOOKUP(A71,'Sheet9'!A:A,1,0) | K71: =T71&CHAR(10)&U71&CHAR(10)&V71&CHAR(10)&Y71&CHAR(10)&Z71&CHAR(10)&AA71&CHAR(10)&AB71&CHAR(10)&AC71&CHAR(10)&AD71&CHAR(10)&AE71 | L71: =IFERROR(VLOOKUP(#REF!,'第一课直播'!D:L,9,0),IFERROR(VLOOKUP('第一课回放'!C:H,5,0),"未到课")) | M71: =IFERROR(VLOOKUP(#REF!,'第一课回放'!C:H,5,0),"0:00:00") | N71: =IFERROR(VLOOKUP(#REF!,'第二课直播'!D:L,9,0),"未到课") | S71: =IFERROR(VLOOKUP(A71,'微伴数据'!A:DB,12,0),"") | T71: =IFERROR(VLOOKUP(A71,'微伴数据'!A:DB,32,0),"") | U71: =IFERROR(VLOOKUP(A71,'微伴数据'!A:DC,81,0),"") | V71: =IFERROR(VLOOKUP(#REF!,'星橙地址'!A:V,9,0),"") | W71: =IFERROR(VLOOKUP(#REF!,'星橙地址'!A:V,10,0),"") | X71: =IFERROR(VLOOKUP(A71,'星云问卷'!A:O,8,0),"") | Y71: =IFERROR(VLOOKUP(A71,'星云问卷'!A:O,9,0),"") | Z71: =IFERROR(VLOOKUP(A71,'星云问卷'!A:O,10,0),"") | AA71: =IFERROR(VLOOKUP(A71,'星云问卷'!A:O,11,0),"") | AB71: =IFERROR(VLOOKUP(A71,'星云问卷'!A:O,12,0),"") | AC71: =IFERROR(VLOOKUP(A71,'星云问卷'!A:O,13,0),"") | AD71: =IFERROR(VLOOKUP(A71,'星云问卷'!A:O,14,0),"") | AE71: =IFERROR(VLOOKUP(A71,'星云问卷'!A:O,15,0),"") | AF71: =IFERROR(VLOOKUP(A71,'微伴数据'!A:DB,72,0),"") | AL71: =CONCATENATE( " 我把体验营用户专属福利给你发一下哈：" & CHAR(10) & CHAR(10), "1.《抖音商业IP课》" & CHAR(10), "兑换码：", AG71, CHAR(10), "兑换码使用地址：https://appamvpb5mq9834.h5.xiaoeknow.com/p/t/v1/ecommerce/mkt/redeem_index" & CHAR(10) & CHAR(10), "2.《生财有术66个项目精选》" & CHAR(10), "兑换码：", AH71, CHAR(10), "使用方式：微信搜索小报童投递-点击开始阅读-点击生财有术项目精选即可" & CHAR(10) & CHAR(10), "3.《生财365问》" & CHAR(10), "兑换码：", AI71, CHAR(10), "使用方式：https://appamvpb5mq9834.h5.xiaoeknow.com/p/t/v1/ecommerce/mkt/redeem_index")
A72: =IF('微伴数据'!A69="","",'微伴数据'!A69) | B72: =IF('微伴数据'!B69="","",'微伴数据'!B69) | C72: =IF('微伴数据'!G69="","",'微伴数据'!G69) | D72: =IF('微伴数据'!D69="","",'微伴数据'!D69) | E72: =IF('微伴数据'!CR69="","",'微伴数据'!CR69) | F72: =IF('微伴数据'!CL69="","",'微伴数据'!CL69) | G72: A | H72: 建联 | I72: =VLOOKUP(A72,'Sheet9'!A:A,1,0) | K72: =T72&CHAR(10)&U72&CHAR(10)&V72&CHAR(10)&Y72&CHAR(10)&Z72&CHAR(10)&AA72&CHAR(10)&AB72&CHAR(10)&AC72&CHAR(10)&AD72&CHAR(10)&AE72 | L72: =IFERROR(VLOOKUP(#REF!,'第一课直播'!D:L,9,0),IFERROR(VLOOKUP('第一课回放'!C:H,5,0),"未到课")) | M72: =IFERROR(VLOOKUP(#REF!,'第一课回放'!C:H,5,0),"0:00:00") | N72: =IFERROR(VLOOKUP(#REF!,'第二课直播'!D:L,9,0),"未到课") | S72: =IFERROR(VLOOKUP(A72,'微伴数据'!A:DB,12,0),"") | T72: =IFERROR(VLOOKUP(A72,'微伴数据'!A:DB,32,0),"") | U72: =IFERROR(VLOOKUP(A72,'微伴数据'!A:DC,81,0),"") | V72: =IFERROR(VLOOKUP(#REF!,'星橙地址'!A:V,9,0),"") | W72: =IFERROR(VLOOKUP(#REF!,'星橙地址'!A:V,10,0),"") | X72: =IFERROR(VLOOKUP(A72,'星云问卷'!A:O,8,0),"") | Y72: =IFERROR(VLOOKUP(A72,'星云问卷'!A:O,9,0),"") | Z72: =IFERROR(VLOOKUP(A72,'星云问卷'!A:O,10,0),"") | AA72: =IFERROR(VLOOKUP(A72,'星云问卷'!A:O,11,0),"") | AB72: =IFERROR(VLOOKUP(A72,'星云问卷'!A:O,12,0),"") | AC72: =IFERROR(VLOOKUP(A72,'星云问卷'!A:O,13,0),"") | AD72: =IFERROR(VLOOKUP(A72,'星云问卷'!A:O,14,0),"") | AE72: =IFERROR(VLOOKUP(A72,'星云问卷'!A:O,15,0),"") | AF72: =IFERROR(VLOOKUP(A72,'微伴数据'!A:DB,72,0),"") | AG72: 547kFrVt | AH72: https://xiaobot.net/invitation/b1550-c68ef-b2009-056b1/ | AI72: 6dhUmBdD | AL72: =CONCATENATE( " 我把体验营用户专属福利给你发一下哈：" & CHAR(10) & CHAR(10), "1.《抖音商业IP课》" & CHAR(10), "兑换码：", AG72, CHAR(10), "兑换码使用地址：https://appamvpb5mq9834.h5.xiaoeknow.com/p/t/v1/ecommerce/mkt/redeem_index" & CHAR(10) & CHAR(10), "2.《生财有术66个项目精选》" & CHAR(10), "兑换码：", AH72, CHAR(10), "使用方式：微信搜索小报童投递-点击开始阅读-点击生财有术项目精选即可" & CHAR(10) & CHAR(10), "3.《生财365问》" & CHAR(10), "兑换码：", AI72, CHAR(10), "使用方式：https://appamvpb5mq9834.h5.xiaoeknow.com/p/t/v1/ecommerce/mkt/redeem_index")
A73: =IF('微伴数据'!A70="","",'微伴数据'!A70) | B73: =IF('微伴数据'!B70="","",'微伴数据'!B70) | C73: =IF('微伴数据'!G70="","",'微伴数据'!G70) | D73: =IF('微伴数据'!D70="","",'微伴数据'!D70) | E73: =IF('微伴数据'!CR70="","",'微伴数据'!CR70) | F73: =IF('微伴数据'!CL70="","",'微伴数据'!CL70) | G73: B | H73: 建联 | I73: =VLOOKUP(A73,'Sheet9'!A:A,1,0) | K73: =T73&CHAR(10)&U73&CHAR(10)&V73&CHAR(10)&Y73&CHAR(10)&Z73&CHAR(10)&AA73&CHAR(10)&AB73&CHAR(10)&AC73&CHAR(10)&AD73&CHAR(10)&AE73 | L73: =IFERROR(VLOOKUP(#REF!,'第一课直播'!D:L,9,0),IFERROR(VLOOKUP('第一课回放'!C:H,5,0),"未到课")) | M73: =IFERROR(VLOOKUP(#REF!,'第一课回放'!C:H,5,0),"0:00:00") | N73: =IFERROR(VLOOKUP(#REF!,'第二课直播'!D:L,9,0),"未到课") | S73: =IFERROR(VLOOKUP(A73,'微伴数据'!A:DB,12,0),"") | T73: =IFERROR(VLOOKUP(A73,'微伴数据'!A:DB,32,0),"") | U73: =IFERROR(VLOOKUP(A73,'微伴数据'!A:DC,81,0),"") | V73: =IFERROR(VLOOKUP(#REF!,'星橙地址'!A:V,9,0),"") | W73: =IFERROR(VLOOKUP(#REF!,'星橙地址'!A:V,10,0),"") | X73: =IFERROR(VLOOKUP(A73,'星云问卷'!A:O,8,0),"") | Y73: =IFERROR(VLOOKUP(A73,'星云问卷'!A:O,9,0),"") | Z73: =IFERROR(VLOOKUP(A73,'星云问卷'!A:O,10,0),"") | AA73: =IFERROR(VLOOKUP(A73,'星云问卷'!A:O,11,0),"") | AB73: =IFERROR(VLOOKUP(A73,'星云问卷'!A:O,12,0),"") | AC73: =IFERROR(VLOOKUP(A73,'星云问卷'!A:O,13,0),"") | AD73: =IFERROR(VLOOKUP(A73,'星云问卷'!A:O,14,0),"") | AE73: =IFERROR(VLOOKUP(A73,'星云问卷'!A:O,15,0),"") | AF73: =IFERROR(VLOOKUP(A73,'微伴数据'!A:DB,72,0),"") | AL73: =CONCATENATE( " 我把体验营用户专属福利给你发一下哈：" & CHAR(10) & CHAR(10), "1.《抖音商业IP课》" & CHAR(10), "兑换码：", AG73, CHAR(10), "兑换码使用地址：https://appamvpb5mq9834.h5.xiaoeknow.com/p/t/v1/ecommerce/mkt/redeem_index" & CHAR(10) & CHAR(10), "2.《生财有术66个项目精选》" & CHAR(10), "兑换码：", AH73, CHAR(10), "使用方式：微信搜索小报童投递-点击开始阅读-点击生财有术项目精选即可" & CHAR(10) & CHAR(10), "3.《生财365问》" & CHAR(10), "兑换码：", AI73, CHAR(10), "使用方式：https://appamvpb5mq9834.h5.xiaoeknow.com/p/t/v1/ecommerce/mkt/redeem_index")
A74: =IF('微伴数据'!A71="","",'微伴数据'!A71) | B74: =IF('微伴数据'!B71="","",'微伴数据'!B71) | C74: =IF('微伴数据'!G71="","",'微伴数据'!G71) | D74: =IF('微伴数据'!D71="","",'微伴数据'!D71) | E74: =IF('微伴数据'!CR71="","",'微伴数据'!CR71) | F74: =IF('微伴数据'!CL71="","",'微伴数据'!CL71) | G74: S | H74: 建联 | I74: =VLOOKUP(A74,'Sheet9'!A:A,1,0) | K74: =T74&CHAR(10)&U74&CHAR(10)&V74&CHAR(10)&Y74&CHAR(10)&Z74&CHAR(10)&AA74&CHAR(10)&AB74&CHAR(10)&AC74&CHAR(10)&AD74&CHAR(10)&AE74 | L74: =IFERROR(VLOOKUP(#REF!,'第一课直播'!D:L,9,0),IFERROR(VLOOKUP('第一课回放'!C:H,5,0),"未到课")) | M74: =IFERROR(VLOOKUP(#REF!,'第一课回放'!C:H,5,0),"0:00:00") | N74: =IFERROR(VLOOKUP(#REF!,'第二课直播'!D:L,9,0),"未到课") | S74: =IFERROR(VLOOKUP(A74,'微伴数据'!A:DB,12,0),"") | T74: =IFERROR(VLOOKUP(A74,'微伴数据'!A:DB,32,0),"") | U74: =IFERROR(VLOOKUP(A74,'微伴数据'!A:DC,81,0),"") | V74: =IFERROR(VLOOKUP(#REF!,'星橙地址'!A:V,9,0),"") | W74: =IFERROR(VLOOKUP(#REF!,'星橙地址'!A:V,10,0),"") | X74: =IFERROR(VLOOKUP(A74,'星云问卷'!A:O,8,0),"") | Y74: =IFERROR(VLOOKUP(A74,'星云问卷'!A:O,9,0),"") | Z74: =IFERROR(VLOOKUP(A74,'星云问卷'!A:O,10,0),"") | AA74: =IFERROR(VLOOKUP(A74,'星云问卷'!A:O,11,0),"") | AB74: =IFERROR(VLOOKUP(A74,'星云问卷'!A:O,12,0),"") | AC74: =IFERROR(VLOOKUP(A74,'星云问卷'!A:O,13,0),"") | AD74: =IFERROR(VLOOKUP(A74,'星云问卷'!A:O,14,0),"") | AE74: =IFERROR(VLOOKUP(A74,'星云问卷'!A:O,15,0),"") | AF74: =IFERROR(VLOOKUP(A74,'微伴数据'!A:DB,72,0),"") | AL74: =CONCATENATE( " 我把体验营用户专属福利给你发一下哈：" & CHAR(10) & CHAR(10), "1.《抖音商业IP课》" & CHAR(10), "兑换码：", AG74, CHAR(10), "兑换码使用地址：https://appamvpb5mq9834.h5.xiaoeknow.com/p/t/v1/ecommerce/mkt/redeem_index" & CHAR(10) & CHAR(10), "2.《生财有术66个项目精选》" & CHAR(10), "兑换码：", AH74, CHAR(10), "使用方式：微信搜索小报童投递-点击开始阅读-点击生财有术项目精选即可" & CHAR(10) & CHAR(10), "3.《生财365问》" & CHAR(10), "兑换码：", AI74, CHAR(10), "使用方式：https://appamvpb5mq9834.h5.xiaoeknow.com/p/t/v1/ecommerce/mkt/redeem_index")
A75: =IF('微伴数据'!A72="","",'微伴数据'!A72) | B75: =IF('微伴数据'!B72="","",'微伴数据'!B72) | C75: =IF('微伴数据'!G72="","",'微伴数据'!G72) | D75: =IF('微伴数据'!D72="","",'微伴数据'!D72) | E75: =IF('微伴数据'!CR72="","",'微伴数据'!CR72) | F75: =IF('微伴数据'!CL72="","",'微伴数据'!CL72) | G75: S | H75: 建联 | I75: =VLOOKUP(A75,'Sheet9'!A:A,1,0) | K75: =T75&CHAR(10)&U75&CHAR(10)&V75&CHAR(10)&Y75&CHAR(10)&Z75&CHAR(10)&AA75&CHAR(10)&AB75&CHAR(10)&AC75&CHAR(10)&AD75&CHAR(10)&AE75 | L75: =IF('微伴数据'!L72="","",'微伴数据'!L72) | M75: =IFERROR(VLOOKUP(#REF!,'第一课回放'!C:H,5,0),"0:00:00") | N75: =IFERROR(VLOOKUP(#REF!,'第二课直播'!D:L,9,0),"未到课") | S75: =IFERROR(VLOOKUP(A75,'微伴数据'!A:DB,12,0),"") | T75: =IFERROR(VLOOKUP(A75,'微伴数据'!A:DB,32,0),"") | U75: =IFERROR(VLOOKUP(A75,'微伴数据'!A:DC,81,0),"") | V75: =IFERROR(VLOOKUP(#REF!,'星橙地址'!A:V,9,0),"") | W75: =IFERROR(VLOOKUP(#REF!,'星橙地址'!A:V,10,0),"") | X75: =IFERROR(VLOOKUP(A75,'星云问卷'!A:O,8,0),"") | Y75: =IFERROR(VLOOKUP(A75,'星云问卷'!A:O,9,0),"") | Z75: =IFERROR(VLOOKUP(A75,'星云问卷'!A:O,10,0),"") | AA75: =IFERROR(VLOOKUP(A75,'星云问卷'!A:O,11,0),"") | AB75: =IFERROR(VLOOKUP(A75,'星云问卷'!A:O,12,0),"") | AC75: =IFERROR(VLOOKUP(A75,'星云问卷'!A:O,13,0),"") | AD75: =IFERROR(VLOOKUP(A75,'星云问卷'!A:O,14,0),"") | AE75: =IFERROR(VLOOKUP(A75,'星云问卷'!A:O,15,0),"") | AF75: =IFERROR(VLOOKUP(A75,'微伴数据'!A:DB,72,0),"") | AL75: =CONCATENATE( " 我把体验营用户专属福利给你发一下哈：" & CHAR(10) & CHAR(10), "1.《抖音商业IP课》" & CHAR(10), "兑换码：", AG75, CHAR(10), "兑换码使用地址：https://appamvpb5mq9834.h5.xiaoeknow.com/p/t/v1/ecommerce/mkt/redeem_index" & CHAR(10) & CHAR(10), "2.《生财有术66个项目精选》" & CHAR(10), "兑换码：", AH75, CHAR(10), "使用方式：微信搜索小报童投递-点击开始阅读-点击生财有术项目精选即可" & CHAR(10) & CHAR(10), "3.《生财365问》" & CHAR(10), "兑换码：", AI75, CHAR(10), "使用方式：https://appamvpb5mq9834.h5.xiaoeknow.com/p/t/v1/ecommerce/mkt/redeem_index")
A76: =IF('微伴数据'!A73="","",'微伴数据'!A73) | B76: =IF('微伴数据'!B73="","",'微伴数据'!B73) | C76: =IF('微伴数据'!G73="","",'微伴数据'!G73) | D76: =IF('微伴数据'!D73="","",'微伴数据'!D73) | E76: =IF('微伴数据'!CR73="","",'微伴数据'!CR73) | F76: =IF('微伴数据'!CL73="","",'微伴数据'!CL73) | G76: B | H76: 建联 | I76: =VLOOKUP(A76,'Sheet9'!A:A,1,0) | K76: =T76&CHAR(10)&U76&CHAR(10)&V76&CHAR(10)&Y76&CHAR(10)&Z76&CHAR(10)&AA76&CHAR(10)&AB76&CHAR(10)&AC76&CHAR(10)&AD76&CHAR(10)&AE76 | L76: =IF('微伴数据'!L73="","",'微伴数据'!L73) | M76: =IFERROR(VLOOKUP(#REF!,'第一课回放'!C:H,5,0),"0:00:00") | N76: =IFERROR(VLOOKUP(#REF!,'第二课直播'!D:L,9,0),"未到课") | S76: =IFERROR(VLOOKUP(A76,'微伴数据'!A:DB,12,0),"") | T76: =IFERROR(VLOOKUP(A76,'微伴数据'!A:DB,32,0),"") | U76: =IFERROR(VLOOKUP(A76,'微伴数据'!A:DC,81,0),"") | V76: =IFERROR(VLOOKUP(#REF!,'星橙地址'!A:V,9,0),"") | W76: =IFERROR(VLOOKUP(#REF!,'星橙地址'!A:V,10,0),"") | X76: =IFERROR(VLOOKUP(A76,'星云问卷'!A:O,8,0),"") | Y76: =IFERROR(VLOOKUP(A76,'星云问卷'!A:O,9,0),"") | Z76: =IFERROR(VLOOKUP(A76,'星云问卷'!A:O,10,0),"") | AA76: =IFERROR(VLOOKUP(A76,'星云问卷'!A:O,11,0),"") | AB76: =IFERROR(VLOOKUP(A76,'星云问卷'!A:O,12,0),"") | AC76: =IFERROR(VLOOKUP(A76,'星云问卷'!A:O,13,0),"") | AD76: =IFERROR(VLOOKUP(A76,'星云问卷'!A:O,14,0),"") | AE76: =IFERROR(VLOOKUP(A76,'星云问卷'!A:O,15,0),"") | AF76: =IFERROR(VLOOKUP(A76,'微伴数据'!A:DB,72,0),"") | AG76: 54AxMYWm | AH76: https://xiaobot.net/invitation/94b9d-7be64-8838d-5064d/ | AI76: 6dqxyZnR | AL76: =CONCATENATE( " 我把体验营用户专属福利给你发一下哈：" & CHAR(10) & CHAR(10), "1.《抖音商业IP课》" & CHAR(10), "兑换码：", AG76, CHAR(10), "兑换码使用地址：https://appamvpb5mq9834.h5.xiaoeknow.com/p/t/v1/ecommerce/mkt/redeem_index" & CHAR(10) & CHAR(10), "2.《生财有术66个项目精选》" & CHAR(10), "兑换码：", AH76, CHAR(10), "使用方式：微信搜索小报童投递-点击开始阅读-点击生财有术项目精选即可" & CHAR(10) & CHAR(10), "3.《生财365问》" & CHAR(10), "兑换码：", AI76, CHAR(10), "使用方式：https://appamvpb5mq9834.h5.xiaoeknow.com/p/t/v1/ecommerce/mkt/redeem_index")
A77: =IF('微伴数据'!A74="","",'微伴数据'!A74) | B77: =IF('微伴数据'!B74="","",'微伴数据'!B74) | C77: =IF('微伴数据'!G74="","",'微伴数据'!G74) | D77: =IF('微伴数据'!D74="","",'微伴数据'!D74) | E77: =IF('微伴数据'!CR74="","",'微伴数据'!CR74) | F77: =IF('微伴数据'!CL74="","",'微伴数据'!CL74) | G77: A | H77: 建联 | I77: =VLOOKUP(A77,'Sheet9'!A:A,1,0) | K77: =T77&CHAR(10)&U77&CHAR(10)&V77&CHAR(10)&Y77&CHAR(10)&Z77&CHAR(10)&AA77&CHAR(10)&AB77&CHAR(10)&AC77&CHAR(10)&AD77&CHAR(10)&AE77 | L77: =IF('微伴数据'!L74="","",'微伴数据'!L74) | M77: =IFERROR(VLOOKUP(#REF!,'第一课回放'!C:H,5,0),"0:00:00") | N77: =IFERROR(VLOOKUP(#REF!,'第二课直播'!D:L,9,0),"未到课") | O77: 听课感受： 这次生财训练营的直播干货满满，彻底刷新了我对赚钱这件事的理解。原来赚钱不是碰运气，而是要顺应规则——无论是公司、平台还是社会的规则，摸透了才能更轻松地有所收获。直播里反复强调的“输出”让我很受触动，用作业倒逼自己深度思考，不仅能提升能力，还能留下成长痕迹，甚至获得认可和奖励，这可比单纯听课有效多了。 四大财富来源的分析也很透彻：打工不能只做机械重复的工作，得提升稀缺性和影响力；副业不是随便找兼职，而是要为创业积累资源；创业要从信息差起步，逐步学会团队管理和做局；投资则更考验判断。四个“差距”的说法点醒了我，自己和别人的差距可能就藏在信息获取、认知深度、执行力度和资源储备里。而赚钱三板斧“流量、运营、产品”和成长四阶段，更是给出了清晰的行动路径，让我知道该从哪里入手，如何一步步进阶。 最后那句“不要用现在的生活想象未来”让我警醒，不能满足于眼前的稳定，得提前为未来的风险做准备。这次直播让我明白，赚钱是可以通过学习掌握的技能，接下来我会认真完成作业，紧跟课程节奏，努力提升自己的赚钱能力，不再被动地被生活推着走。 | S77: =IFERROR(VLOOKUP(A77,'微伴数据'!A:DB,12,0),"") | T77: =IFERROR(VLOOKUP(A77,'微伴数据'!A:DB,32,0),"") | U77: =IFERROR(VLOOKUP(A77,'微伴数据'!A:DC,81,0),"") | V77: =IFERROR(VLOOKUP(#REF!,'星橙地址'!A:V,9,0),"") | W77: =IFERROR(VLOOKUP(#REF!,'星橙地址'!A:V,10,0),"") | X77: =IFERROR(VLOOKUP(A77,'星云问卷'!A:O,8,0),"") | Y77: =IFERROR(VLOOKUP(A77,'星云问卷'!A:O,9,0),"") | Z77: =IFERROR(VLOOKUP(A77,'星云问卷'!A:O,10,0),"") | AA77: =IFERROR(VLOOKUP(A77,'星云问卷'!A:O,11,0),"") | AB77: =IFERROR(VLOOKUP(A77,'星云问卷'!A:O,12,0),"") | AC77: =IFERROR(VLOOKUP(A77,'星云问卷'!A:O,13,0),"") | AD77: =IFERROR(VLOOKUP(A77,'星云问卷'!A:O,14,0),"") | AE77: =IFERROR(VLOOKUP(A77,'星云问卷'!A:O,15,0),"") | AF77: =IFERROR(VLOOKUP(A77,'微伴数据'!A:DB,72,0),"") | AG77: 547Ww39r | AH77: https://xiaobot.net/invitation/a55d0-02f88-90ef9-f1b10/ | AI77: 6dh542zu | AL77: =CONCATENATE( " 我把体验营用户专属福利给你发一下哈：" & CHAR(10) & CHAR(10), "1.《抖音商业IP课》" & CHAR(10), "兑换码：", AG77, CHAR(10), "兑换码使用地址：https://appamvpb5mq9834.h5.xiaoeknow.com/p/t/v1/ecommerce/mkt/redeem_index" & CHAR(10) & CHAR(10), "2.《生财有术66个项目精选》" & CHAR(10), "兑换码：", AH77, CHAR(10), "使用方式：微信搜索小报童投递-点击开始阅读-点击生财有术项目精选即可" & CHAR(10) & CHAR(10), "3.《生财365问》" & CHAR(10), "兑换码：", AI77, CHAR(10), "使用方式：https://appamvpb5mq9834.h5.xiaoeknow.com/p/t/v1/ecommerce/mkt/redeem_index")
A78: =IF('微伴数据'!A75="","",'微伴数据'!A75) | B78: =IF('微伴数据'!B75="","",'微伴数据'!B75) | C78: =IF('微伴数据'!G75="","",'微伴数据'!G75) | D78: =IF('微伴数据'!D75="","",'微伴数据'!D75) | E78: =IF('微伴数据'!CR75="","",'微伴数据'!CR75) | F78: =IF('微伴数据'!CL75="","",'微伴数据'!CL75) | G78: B | H78: 建联 | I78: =VLOOKUP(A78,'Sheet9'!A:A,1,0) | K78: =T78&CHAR(10)&U78&CHAR(10)&V78&CHAR(10)&Y78&CHAR(10)&Z78&CHAR(10)&AA78&CHAR(10)&AB78&CHAR(10)&AC78&CHAR(10)&AD78&CHAR(10)&AE78 | L78: =IF('微伴数据'!L75="","",'微伴数据'!L75) | M78: =IFERROR(VLOOKUP(#REF!,'第一课回放'!C:H,5,0),"0:00:00") | N78: =IFERROR(VLOOKUP(#REF!,'第二课直播'!D:L,9,0),"未到课") | S78: =IFERROR(VLOOKUP(A78,'微伴数据'!A:DB,12,0),"") | T78: =IFERROR(VLOOKUP(A78,'微伴数据'!A:DB,32,0),"") | U78: =IFERROR(VLOOKUP(A78,'微伴数据'!A:DC,81,0),"") | V78: =IFERROR(VLOOKUP(#REF!,'星橙地址'!A:V,9,0),"") | W78: =IFERROR(VLOOKUP(#REF!,'星橙地址'!A:V,10,0),"") | X78: =IFERROR(VLOOKUP(A78,'星云问卷'!A:O,8,0),"") | Y78: =IFERROR(VLOOKUP(A78,'星云问卷'!A:O,9,0),"") | Z78: =IFERROR(VLOOKUP(A78,'星云问卷'!A:O,10,0),"") | AA78: =IFERROR(VLOOKUP(A78,'星云问卷'!A:O,11,0),"") | AB78: =IFERROR(VLOOKUP(A78,'星云问卷'!A:O,12,0),"") | AC78: =IFERROR(VLOOKUP(A78,'星云问卷'!A:O,13,0),"") | AD78: =IFERROR(VLOOKUP(A78,'星云问卷'!A:O,14,0),"") | AE78: =IFERROR(VLOOKUP(A78,'星云问卷'!A:O,15,0),"") | AF78: =IFERROR(VLOOKUP(A78,'微伴数据'!A:DB,72,0),"") | AG78: 54As8K9h | AH78: https://xiaobot.net/invitation/885de-8f08f-d63dc-7f2b6/ | AI78: 6dqk9sbN | AL78: =CONCATENATE( " 我把体验营用户专属福利给你发一下哈：" & CHAR(10) & CHAR(10), "1.《抖音商业IP课》" & CHAR(10), "兑换码：", AG78, CHAR(10), "兑换码使用地址：https://appamvpb5mq9834.h5.xiaoeknow.com/p/t/v1/ecommerce/mkt/redeem_index" & CHAR(10) & CHAR(10), "2.《生财有术66个项目精选》" & CHAR(10), "兑换码：", AH78, CHAR(10), "使用方式：微信搜索小报童投递-点击开始阅读-点击生财有术项目精选即可" & CHAR(10) & CHAR(10), "3.《生财365问》" & CHAR(10), "兑换码：", AI78, CHAR(10), "使用方式：https://appamvpb5mq9834.h5.xiaoeknow.com/p/t/v1/ecommerce/mkt/redeem_index")
A79: =IF('微伴数据'!A76="","",'微伴数据'!A76) | B79: =IF('微伴数据'!B76="","",'微伴数据'!B76) | C79: =IF('微伴数据'!G76="","",'微伴数据'!G76) | D79: =IF('微伴数据'!D76="","",'微伴数据'!D76) | E79: =IF('微伴数据'!CR76="","",'微伴数据'!CR76) | F79: =IF('微伴数据'!CL76="","",'微伴数据'!CL76) | G79: B | H79: 建联 | I79: =VLOOKUP(A79,'Sheet9'!A:A,1,0) | K79: =T79&CHAR(10)&U79&CHAR(10)&V79&CHAR(10)&Y79&CHAR(10)&Z79&CHAR(10)&AA79&CHAR(10)&AB79&CHAR(10)&AC79&CHAR(10)&AD79&CHAR(10)&AE79 | L79: =IF('微伴数据'!L76="","",'微伴数据'!L76) | M79: =IFERROR(VLOOKUP(#REF!,'第一课回放'!C:H,5,0),"0:00:00") | N79: =IFERROR(VLOOKUP(#REF!,'第二课直播'!D:L,9,0),"未到课") | S79: =IFERROR(VLOOKUP(A79,'微伴数据'!A:DB,12,0),"") | T79: =IFERROR(VLOOKUP(A79,'微伴数据'!A:DB,32,0),"") | U79: =IFERROR(VLOOKUP(A79,'微伴数据'!A:DC,81,0),"") | V79: =IFERROR(VLOOKUP(#REF!,'星橙地址'!A:V,9,0),"") | W79: =IFERROR(VLOOKUP(#REF!,'星橙地址'!A:V,10,0),"") | X79: =IFERROR(VLOOKUP(A79,'星云问卷'!A:O,8,0),"") | Y79: =IFERROR(VLOOKUP(A79,'星云问卷'!A:O,9,0),"") | Z79: =IFERROR(VLOOKUP(A79,'星云问卷'!A:O,10,0),"") | AA79: =IFERROR(VLOOKUP(A79,'星云问卷'!A:O,11,0),"") | AB79: =IFERROR(VLOOKUP(A79,'星云问卷'!A:O,12,0),"") | AC79: =IFERROR(VLOOKUP(A79,'星云问卷'!A:O,13,0),"") | AD79: =IFERROR(VLOOKUP(A79,'星云问卷'!A:O,14,0),"") | AE79: =IFERROR(VLOOKUP(A79,'星云问卷'!A:O,15,0),"") | AF79: =IFERROR(VLOOKUP(A79,'微伴数据'!A:DB,72,0),"") | AL79: =CONCATENATE( " 我把体验营用户专属福利给你发一下哈：" & CHAR(10) & CHAR(10), "1.《抖音商业IP课》" & CHAR(10), "兑换码：", AG79, CHAR(10), "兑换码使用地址：https://appamvpb5mq9834.h5.xiaoeknow.com/p/t/v1/ecommerce/mkt/redeem_index" & CHAR(10) & CHAR(10), "2.《生财有术66个项目精选》" & CHAR(10), "兑换码：", AH79, CHAR(10), "使用方式：微信搜索小报童投递-点击开始阅读-点击生财有术项目精选即可" & CHAR(10) & CHAR(10), "3.《生财365问》" & CHAR(10), "兑换码：", AI79, CHAR(10), "使用方式：https://appamvpb5mq9834.h5.xiaoeknow.com/p/t/v1/ecommerce/mkt/redeem_index")
A80: =IF('微伴数据'!A77="","",'微伴数据'!A77) | B80: =IF('微伴数据'!B77="","",'微伴数据'!B77) | C80: =IF('微伴数据'!G77="","",'微伴数据'!G77) | D80: =IF('微伴数据'!D77="","",'微伴数据'!D77) | E80: =IF('微伴数据'!CR77="","",'微伴数据'!CR77) | F80: =IF('微伴数据'!CL77="","",'微伴数据'!CL77) | G80: A | H80: 建联 | I80: =VLOOKUP(A80,'Sheet9'!A:A,1,0) | K80: =T80&CHAR(10)&U80&CHAR(10)&V80&CHAR(10)&Y80&CHAR(10)&Z80&CHAR(10)&AA80&CHAR(10)&AB80&CHAR(10)&AC80&CHAR(10)&AD80&CHAR(10)&AE80 | L80: =IF('微伴数据'!L77="","",'微伴数据'!L77) | M80: =IFERROR(VLOOKUP(#REF!,'第一课回放'!C:H,5,0),"0:00:00") | N80: =IFERROR(VLOOKUP(#REF!,'第二课直播'!D:L,9,0),"未到课") | S80: =IFERROR(VLOOKUP(A80,'微伴数据'!A:DB,12,0),"") | T80: =IFERROR(VLOOKUP(A80,'微伴数据'!A:DB,32,0),"") | U80: =IFERROR(VLOOKUP(A80,'微伴数据'!A:DC,81,0),"") | V80: =IFERROR(VLOOKUP(#REF!,'星橙地址'!A:V,9,0),"") | W80: =IFERROR(VLOOKUP(#REF!,'星橙地址'!A:V,10,0),"") | X80: =IFERROR(VLOOKUP(A80,'星云问卷'!A:O,8,0),"") | Y80: =IFERROR(VLOOKUP(A80,'星云问卷'!A:O,9,0),"") | Z80: =IFERROR(VLOOKUP(A80,'星云问卷'!A:O,10,0),"") | AA80: =IFERROR(VLOOKUP(A80,'星云问卷'!A:O,11,0),"") | AB80: =IFERROR(VLOOKUP(A80,'星云问卷'!A:O,12,0),"") | AC80: =IFERROR(VLOOKUP(A80,'星云问卷'!A:O,13,0),"") | AD80: =IFERROR(VLOOKUP(A80,'星云问卷'!A:O,14,0),"") | AE80: =IFERROR(VLOOKUP(A80,'星云问卷'!A:O,15,0),"") | AF80: =IFERROR(VLOOKUP(A80,'微伴数据'!A:DB,72,0),"") | AL80: =CONCATENATE( " 我把体验营用户专属福利给你发一下哈：" & CHAR(10) & CHAR(10), "1.《抖音商业IP课》" & CHAR(10), "兑换码：", AG80, CHAR(10), "兑换码使用地址：https://appamvpb5mq9834.h5.xiaoeknow.com/p/t/v1/ecommerce/mkt/redeem_index" & CHAR(10) & CHAR(10), "2.《生财有术66个项目精选》" & CHAR(10), "兑换码：", AH80, CHAR(10), "使用方式：微信搜索小报童投递-点击开始阅读-点击生财有术项目精选即可" & CHAR(10) & CHAR(10), "3.《生财365问》" & CHAR(10), "兑换码：", AI80, CHAR(10), "使用方式：https://appamvpb5mq9834.h5.xiaoeknow.com/p/t/v1/ecommerce/mkt/redeem_index")
A81: =IF('微伴数据'!A78="","",'微伴数据'!A78) | B81: =IF('微伴数据'!B78="","",'微伴数据'!B78) | C81: =IF('微伴数据'!G78="","",'微伴数据'!G78) | D81: =IF('微伴数据'!D78="","",'微伴数据'!D78) | E81: =IF('微伴数据'!CR78="","",'微伴数据'!CR78) | F81: =IF('微伴数据'!CL78="","",'微伴数据'!CL78) | G81: A | H81: 建联 | I81: =VLOOKUP(A81,'Sheet9'!A:A,1,0) | K81: =T81&CHAR(10)&U81&CHAR(10)&V81&CHAR(10)&Y81&CHAR(10)&Z81&CHAR(10)&AA81&CHAR(10)&AB81&CHAR(10)&AC81&CHAR(10)&AD81&CHAR(10)&AE81 | L81: =IF('微伴数据'!L78="","",'微伴数据'!L78) | M81: =IFERROR(VLOOKUP(#REF!,'第一课回放'!C:H,5,0),"0:00:00") | N81: =IFERROR(VLOOKUP(#REF!,'第二课直播'!D:L,9,0),"未到课") | S81: =IFERROR(VLOOKUP(A81,'微伴数据'!A:DB,12,0),"") | T81: =IFERROR(VLOOKUP(A81,'微伴数据'!A:DB,32,0),"") | U81: =IFERROR(VLOOKUP(A81,'微伴数据'!A:DC,81,0),"") | V81: =IFERROR(VLOOKUP(#REF!,'星橙地址'!A:V,9,0),"") | W81: =IFERROR(VLOOKUP(#REF!,'星橙地址'!A:V,10,0),"") | X81: =IFERROR(VLOOKUP(A81,'星云问卷'!A:O,8,0),"") | Y81: =IFERROR(VLOOKUP(A81,'星云问卷'!A:O,9,0),"") | Z81: =IFERROR(VLOOKUP(A81,'星云问卷'!A:O,10,0),"") | AA81: =IFERROR(VLOOKUP(A81,'星云问卷'!A:O,11,0),"") | AB81: =IFERROR(VLOOKUP(A81,'星云问卷'!A:O,12,0),"") | AC81: =IFERROR(VLOOKUP(A81,'星云问卷'!A:O,13,0),"") | AD81: =IFERROR(VLOOKUP(A81,'星云问卷'!A:O,14,0),"") | AE81: =IFERROR(VLOOKUP(A81,'星云问卷'!A:O,15,0),"") | AF81: =IFERROR(VLOOKUP(A81,'微伴数据'!A:DB,72,0),"") | AL81: =CONCATENATE( " 我把体验营用户专属福利给你发一下哈：" & CHAR(10) & CHAR(10), "1.《抖音商业IP课》" & CHAR(10), "兑换码：", AG81, CHAR(10), "兑换码使用地址：https://appamvpb5mq9834.h5.xiaoeknow.com/p/t/v1/ecommerce/mkt/redeem_index" & CHAR(10) & CHAR(10), "2.《生财有术66个项目精选》" & CHAR(10), "兑换码：", AH81, CHAR(10), "使用方式：微信搜索小报童投递-点击开始阅读-点击生财有术项目精选即可" & CHAR(10) & CHAR(10), "3.《生财365问》" & CHAR(10), "兑换码：", AI81, CHAR(10), "使用方式：https://appamvpb5mq9834.h5.xiaoeknow.com/p/t/v1/ecommerce/mkt/redeem_index")
A82: =IF('微伴数据'!A79="","",'微伴数据'!A79) | B82: =IF('微伴数据'!B79="","",'微伴数据'!B79) | C82: =IF('微伴数据'!G79="","",'微伴数据'!G79) | D82: =IF('微伴数据'!D79="","",'微伴数据'!D79) | E82: =IF('微伴数据'!CR79="","",'微伴数据'!CR79) | F82: =IF('微伴数据'!CL79="","",'微伴数据'!CL79) | G82: S | H82: 建联 | I82: =VLOOKUP(A82,'Sheet9'!A:A,1,0) | K82: =T82&CHAR(10)&U82&CHAR(10)&V82&CHAR(10)&Y82&CHAR(10)&Z82&CHAR(10)&AA82&CHAR(10)&AB82&CHAR(10)&AC82&CHAR(10)&AD82&CHAR(10)&AE82 | L82: =IF('微伴数据'!L79="","",'微伴数据'!L79) | M82: =IFERROR(VLOOKUP(#REF!,'第一课回放'!C:H,5,0),"0:00:00") | N82: =IFERROR(VLOOKUP(#REF!,'第二课直播'!D:L,9,0),"未到课") | S82: =IFERROR(VLOOKUP(A82,'微伴数据'!A:DB,12,0),"") | T82: =IFERROR(VLOOKUP(A82,'微伴数据'!A:DB,32,0),"") | U82: =IFERROR(VLOOKUP(A82,'微伴数据'!A:DC,81,0),"") | V82: =IFERROR(VLOOKUP(#REF!,'星橙地址'!A:V,9,0),"") | W82: =IFERROR(VLOOKUP(#REF!,'星橙地址'!A:V,10,0),"") | X82: =IFERROR(VLOOKUP(A82,'星云问卷'!A:O,8,0),"") | Y82: =IFERROR(VLOOKUP(A82,'星云问卷'!A:O,9,0),"") | Z82: =IFERROR(VLOOKUP(A82,'星云问卷'!A:O,10,0),"") | AA82: =IFERROR(VLOOKUP(A82,'星云问卷'!A:O,11,0),"") | AB82: =IFERROR(VLOOKUP(A82,'星云问卷'!A:O,12,0),"") | AC82: =IFERROR(VLOOKUP(A82,'星云问卷'!A:O,13,0),"") | AD82: =IFERROR(VLOOKUP(A82,'星云问卷'!A:O,14,0),"") | AE82: =IFERROR(VLOOKUP(A82,'星云问卷'!A:O,15,0),"") | AF82: =IFERROR(VLOOKUP(A82,'微伴数据'!A:DB,72,0),"") | AG82: 54AgJrB3 | AH82: https://xiaobot.net/invitation/54915-6979b-026b7-2560e/ | AI82: 6dqVPxP7 | AL82: =CONCATENATE( " 我把体验营用户专属福利给你发一下哈：" & CHAR(10) & CHAR(10), "1.《抖音商业IP课》" & CHAR(10), "兑换码：", AG82, CHAR(10), "兑换码使用地址：https://appamvpb5mq9834.h5.xiaoeknow.com/p/t/v1/ecommerce/mkt/redeem_index" & CHAR(10) & CHAR(10), "2.《生财有术66个项目精选》" & CHAR(10), "兑换码：", AH82, CHAR(10), "使用方式：微信搜索小报童投递-点击开始阅读-点击生财有术项目精选即可" & CHAR(10) & CHAR(10), "3.《生财365问》" & CHAR(10), "兑换码：", AI82, CHAR(10), "使用方式：https://appamvpb5mq9834.h5.xiaoeknow.com/p/t/v1/ecommerce/mkt/redeem_index")
A83: =IF('微伴数据'!A80="","",'微伴数据'!A80) | B83: =IF('微伴数据'!B80="","",'微伴数据'!B80) | C83: =IF('微伴数据'!G80="","",'微伴数据'!G80) | D83: =IF('微伴数据'!D80="","",'微伴数据'!D80) | E83: =IF('微伴数据'!CR80="","",'微伴数据'!CR80) | F83: =IF('微伴数据'!CL80="","",'微伴数据'!CL80) | G83: B | H83: 建联 | I83: =VLOOKUP(A83,'Sheet9'!A:A,1,0) | K83: =T83&CHAR(10)&U83&CHAR(10)&V83&CHAR(10)&Y83&CHAR(10)&Z83&CHAR(10)&AA83&CHAR(10)&AB83&CHAR(10)&AC83&CHAR(10)&AD83&CHAR(10)&AE83 | L83: =IF('微伴数据'!L80="","",'微伴数据'!L80) | M83: =IFERROR(VLOOKUP(#REF!,'第一课回放'!C:H,5,0),"0:00:00") | N83: =IFERROR(VLOOKUP(#REF!,'第二课直播'!D:L,9,0),"未到课") | S83: =IFERROR(VLOOKUP(A83,'微伴数据'!A:DB,12,0),"") | T83: =IFERROR(VLOOKUP(A83,'微伴数据'!A:DB,32,0),"") | U83: =IFERROR(VLOOKUP(A83,'微伴数据'!A:DC,81,0),"") | V83: =IFERROR(VLOOKUP(#REF!,'星橙地址'!A:V,9,0),"") | W83: =IFERROR(VLOOKUP(#REF!,'星橙地址'!A:V,10,0),"") | X83: =IFERROR(VLOOKUP(A83,'星云问卷'!A:O,8,0),"") | Y83: =IFERROR(VLOOKUP(A83,'星云问卷'!A:O,9,0),"") | Z83: =IFERROR(VLOOKUP(A83,'星云问卷'!A:O,10,0),"") | AA83: =IFERROR(VLOOKUP(A83,'星云问卷'!A:O,11,0),"") | AB83: =IFERROR(VLOOKUP(A83,'星云问卷'!A:O,12,0),"") | AC83: =IFERROR(VLOOKUP(A83,'星云问卷'!A:O,13,0),"") | AD83: =IFERROR(VLOOKUP(A83,'星云问卷'!A:O,14,0),"") | AE83: =IFERROR(VLOOKUP(A83,'星云问卷'!A:O,15,0),"") | AF83: =IFERROR(VLOOKUP(A83,'微伴数据'!A:DB,72,0),"") | AL83: =CONCATENATE( " 我把体验营用户专属福利给你发一下哈：" & CHAR(10) & CHAR(10), "1.《抖音商业IP课》" & CHAR(10), "兑换码：", AG83, CHAR(10), "兑换码使用地址：https://appamvpb5mq9834.h5.xiaoeknow.com/p/t/v1/ecommerce/mkt/redeem_index" & CHAR(10) & CHAR(10), "2.《生财有术66个项目精选》" & CHAR(10), "兑换码：", AH83, CHAR(10), "使用方式：微信搜索小报童投递-点击开始阅读-点击生财有术项目精选即可" & CHAR(10) & CHAR(10), "3.《生财365问》" & CHAR(10), "兑换码：", AI83, CHAR(10), "使用方式：https://appamvpb5mq9834.h5.xiaoeknow.com/p/t/v1/ecommerce/mkt/redeem_index")
A84: =IF('微伴数据'!A81="","",'微伴数据'!A81) | B84: =IF('微伴数据'!B81="","",'微伴数据'!B81) | C84: =IF('微伴数据'!G81="","",'微伴数据'!G81) | D84: =IF('微伴数据'!D81="","",'微伴数据'!D81) | E84: =IF('微伴数据'!CR81="","",'微伴数据'!CR81) | F84: =IF('微伴数据'!CL81="","",'微伴数据'!CL81) | G84: B | H84: 建联 | I84: =VLOOKUP(A84,'Sheet9'!A:A,1,0) | K84: =T84&CHAR(10)&U84&CHAR(10)&V84&CHAR(10)&Y84&CHAR(10)&Z84&CHAR(10)&AA84&CHAR(10)&AB84&CHAR(10)&AC84&CHAR(10)&AD84&CHAR(10)&AE84 | L84: =IF('微伴数据'!L81="","",'微伴数据'!L81) | M84: =IFERROR(VLOOKUP(#REF!,'第一课回放'!C:H,5,0),"0:00:00") | N84: =IFERROR(VLOOKUP(#REF!,'第二课直播'!D:L,9,0),"未到课") | O84: 星球标题：13天开通YouTube YPP，从0到1月入过万的自动化实操记录 星球链接：https://t.zsxq.com/pRqyL 读后感：读完整篇文章第一个收获就是先去干，干出一个小的方向在不断的优化，作者在接触YPP之前也不断的做些项目，从他身上我反思到了我的问题，作者会选择自己感兴趣的项目做，我的感悟就是只要兴趣是最好的老师，才会有不断的执行力和心力去支撑自己度过前期的冷启动期，这点是我要学习的，之前我做项目单纯看哪个项目赚钱和简单，但现在想想，认知还是不到位，因为这是一个多维度的事情，单一维度去看肯定看不全全貌；第二个反思的点就是，作者的拆分能力很强，具体的细节和小的方向很清晰，这点我的感悟就是，每天做明天的计划总是太概括，而不是具体到哪一个点上，和反馈的方向不够清晰，导致迟迟看不到结果，度不过项目的冷启动期，导致自己怀疑、不自信，行动力迟缓，要把每个细节和小方向弄清晰，然后先把这些做好，下一个方向自然而然就出现了，这点也是导致我自己做项目不成功的因素之一；第三个反思的点就是作者的整体全局方向很明了，也就对应了反思的第二点，单单有小的方向不够，要保证大的方向是有正反馈的，小的方向是辅助大方向实现的，而不是本末倒置的；第四个反思的点就是，自己的执行力还是不够，总会想一些没用的，而作者执行力很强，单单测试就花费很多，而自己却连自己制定的计划都完不成，这点是我要加强和努力的；最后呢，我会深刻的认识到自己的问题并一一解决，同时作者的做事态度和方法是我要不断学习精进的，下一步的计划，就是把YPP这个项目作为冷启动项目来做，先精细干个半年，没效果再说 | S84: =IFERROR(VLOOKUP(A84,'微伴数据'!A:DB,12,0),"") | T84: =IFERROR(VLOOKUP(A84,'微伴数据'!A:DB,32,0),"") | U84: =IFERROR(VLOOKUP(A84,'微伴数据'!A:DC,81,0),"") | V84: =IFERROR(VLOOKUP(#REF!,'星橙地址'!A:V,9,0),"") | W84: =IFERROR(VLOOKUP(#REF!,'星橙地址'!A:V,10,0),"") | X84: =IFERROR(VLOOKUP(A84,'星云问卷'!A:O,8,0),"") | Y84: =IFERROR(VLOOKUP(A84,'星云问卷'!A:O,9,0),"") | Z84: =IFERROR(VLOOKUP(A84,'星云问卷'!A:O,10,0),"") | AA84: =IFERROR(VLOOKUP(A84,'星云问卷'!A:O,11,0),"") | AB84: =IFERROR(VLOOKUP(A84,'星云问卷'!A:O,12,0),"") | AC84: =IFERROR(VLOOKUP(A84,'星云问卷'!A:O,13,0),"") | AD84: =IFERROR(VLOOKUP(A84,'星云问卷'!A:O,14,0),"") | AE84: =IFERROR(VLOOKUP(A84,'星云问卷'!A:O,15,0),"") | AF84: =IFERROR(VLOOKUP(A84,'微伴数据'!A:DB,72,0),"") | AL84: =CONCATENATE( " 我把体验营用户专属福利给你发一下哈：" & CHAR(10) & CHAR(10), "1.《抖音商业IP课》" & CHAR(10), "兑换码：", AG84, CHAR(10), "兑换码使用地址：https://appamvpb5mq9834.h5.xiaoeknow.com/p/t/v1/ecommerce/mkt/redeem_index" & CHAR(10) & CHAR(10), "2.《生财有术66个项目精选》" & CHAR(10), "兑换码：", AH84, CHAR(10), "使用方式：微信搜索小报童投递-点击开始阅读-点击生财有术项目精选即可" & CHAR(10) & CHAR(10), "3.《生财365问》" & CHAR(10), "兑换码：", AI84, CHAR(10), "使用方式：https://appamvpb5mq9834.h5.xiaoeknow.com/p/t/v1/ecommerce/mkt/redeem_index")
A85: =IF('微伴数据'!A82="","",'微伴数据'!A82) | B85: =IF('微伴数据'!B82="","",'微伴数据'!B82) | C85: =IF('微伴数据'!G82="","",'微伴数据'!G82) | D85: =IF('微伴数据'!D82="","",'微伴数据'!D82) | E85: =IF('微伴数据'!CR82="","",'微伴数据'!CR82) | F85: =IF('微伴数据'!CL82="","",'微伴数据'!CL82) | G85: B | H85: 建联 | I85: =VLOOKUP(A85,'Sheet9'!A:A,1,0) | K85: =T85&CHAR(10)&U85&CHAR(10)&V85&CHAR(10)&Y85&CHAR(10)&Z85&CHAR(10)&AA85&CHAR(10)&AB85&CHAR(10)&AC85&CHAR(10)&AD85&CHAR(10)&AE85 | L85: =IF('微伴数据'!L82="","",'微伴数据'!L82) | M85: =IFERROR(VLOOKUP(#REF!,'第一课回放'!C:H,5,0),"0:00:00") | N85: =IFERROR(VLOOKUP(#REF!,'第二课直播'!D:L,9,0),"未到课") | S85: =IFERROR(VLOOKUP(A85,'微伴数据'!A:DB,12,0),"") | T85: =IFERROR(VLOOKUP(A85,'微伴数据'!A:DB,32,0),"") | U85: =IFERROR(VLOOKUP(A85,'微伴数据'!A:DC,81,0),"") | V85: =IFERROR(VLOOKUP(#REF!,'星橙地址'!A:V,9,0),"") | W85: =IFERROR(VLOOKUP(#REF!,'星橙地址'!A:V,10,0),"") | X85: =IFERROR(VLOOKUP(A85,'星云问卷'!A:O,8,0),"") | Y85: =IFERROR(VLOOKUP(A85,'星云问卷'!A:O,9,0),"") | Z85: =IFERROR(VLOOKUP(A85,'星云问卷'!A:O,10,0),"") | AA85: =IFERROR(VLOOKUP(A85,'星云问卷'!A:O,11,0),"") | AB85: =IFERROR(VLOOKUP(A85,'星云问卷'!A:O,12,0),"") | AC85: =IFERROR(VLOOKUP(A85,'星云问卷'!A:O,13,0),"") | AD85: =IFERROR(VLOOKUP(A85,'星云问卷'!A:O,14,0),"") | AE85: =IFERROR(VLOOKUP(A85,'星云问卷'!A:O,15,0),"") | AF85: =IFERROR(VLOOKUP(A85,'微伴数据'!A:DB,72,0),"") | AL85: =CONCATENATE( " 我把体验营用户专属福利给你发一下哈：" & CHAR(10) & CHAR(10), "1.《抖音商业IP课》" & CHAR(10), "兑换码：", AG85, CHAR(10), "兑换码使用地址：https://appamvpb5mq9834.h5.xiaoeknow.com/p/t/v1/ecommerce/mkt/redeem_index" & CHAR(10) & CHAR(10), "2.《生财有术66个项目精选》" & CHAR(10), "兑换码：", AH85, CHAR(10), "使用方式：微信搜索小报童投递-点击开始阅读-点击生财有术项目精选即可" & CHAR(10) & CHAR(10), "3.《生财365问》" & CHAR(10), "兑换码：", AI85, CHAR(10), "使用方式：https://appamvpb5mq9834.h5.xiaoeknow.com/p/t/v1/ecommerce/mkt/redeem_index")
A86: =IF('微伴数据'!A83="","",'微伴数据'!A83) | B86: =IF('微伴数据'!B83="","",'微伴数据'!B83) | C86: =IF('微伴数据'!G83="","",'微伴数据'!G83) | D86: =IF('微伴数据'!D83="","",'微伴数据'!D83) | E86: =IF('微伴数据'!CR83="","",'微伴数据'!CR83) | F86: =IF('微伴数据'!CL83="","",'微伴数据'!CL83) | G86: B | H86: 建联 | I86: =VLOOKUP(A86,'Sheet9'!A:A,1,0) | K86: =T86&CHAR(10)&U86&CHAR(10)&V86&CHAR(10)&Y86&CHAR(10)&Z86&CHAR(10)&AA86&CHAR(10)&AB86&CHAR(10)&AC86&CHAR(10)&AD86&CHAR(10)&AE86 | L86: =IF('微伴数据'!L83="","",'微伴数据'!L83) | M86: =IFERROR(VLOOKUP(#REF!,'第一课回放'!C:H,5,0),"0:00:00") | N86: =IFERROR(VLOOKUP(#REF!,'第二课直播'!D:L,9,0),"未到课") | S86: =IFERROR(VLOOKUP(A86,'微伴数据'!A:DB,12,0),"") | T86: =IFERROR(VLOOKUP(A86,'微伴数据'!A:DB,32,0),"") | U86: =IFERROR(VLOOKUP(A86,'微伴数据'!A:DC,81,0),"") | V86: =IFERROR(VLOOKUP(#REF!,'星橙地址'!A:V,9,0),"") | W86: =IFERROR(VLOOKUP(#REF!,'星橙地址'!A:V,10,0),"") | X86: =IFERROR(VLOOKUP(A86,'星云问卷'!A:O,8,0),"") | Y86: =IFERROR(VLOOKUP(A86,'星云问卷'!A:O,9,0),"") | Z86: =IFERROR(VLOOKUP(A86,'星云问卷'!A:O,10,0),"") | AA86: =IFERROR(VLOOKUP(A86,'星云问卷'!A:O,11,0),"") | AB86: =IFERROR(VLOOKUP(A86,'星云问卷'!A:O,12,0),"") | AC86: =IFERROR(VLOOKUP(A86,'星云问卷'!A:O,13,0),"") | AD86: =IFERROR(VLOOKUP(A86,'星云问卷'!A:O,14,0),"") | AE86: =IFERROR(VLOOKUP(A86,'星云问卷'!A:O,15,0),"") | AF86: =IFERROR(VLOOKUP(A86,'微伴数据'!A:DB,72,0),"") | AG86: 54Ah6Eh2 | AH86: https://xiaobot.net/invitation/35930-a5cfc-e760a-16b9b/ | AI86: 6dqVU3ck | AL86: =CONCATENATE( " 我把体验营用户专属福利给你发一下哈：" & CHAR(10) & CHAR(10), "1.《抖音商业IP课》" & CHAR(10), "兑换码：", AG86, CHAR(10), "兑换码使用地址：https://appamvpb5mq9834.h5.xiaoeknow.com/p/t/v1/ecommerce/mkt/redeem_index" & CHAR(10) & CHAR(10), "2.《生财有术66个项目精选》" & CHAR(10), "兑换码：", AH86, CHAR(10), "使用方式：微信搜索小报童投递-点击开始阅读-点击生财有术项目精选即可" & CHAR(10) & CHAR(10), "3.《生财365问》" & CHAR(10), "兑换码：", AI86, CHAR(10), "使用方式：https://appamvpb5mq9834.h5.xiaoeknow.com/p/t/v1/ecommerce/mkt/redeem_index")
A87: =IF('微伴数据'!A84="","",'微伴数据'!A84) | B87: =IF('微伴数据'!B84="","",'微伴数据'!B84) | C87: =IF('微伴数据'!G84="","",'微伴数据'!G84) | D87: =IF('微伴数据'!D84="","",'微伴数据'!D84) | E87: =IF('微伴数据'!CR84="","",'微伴数据'!CR84) | F87: =IF('微伴数据'!CL84="","",'微伴数据'!CL84) | G87: S | H87: 已成交 | I87: =VLOOKUP(A87,'Sheet9'!A:A,1,0) | J87: 一是项目，也想学习迭代下新的认知 | K87: =T87&CHAR(10)&U87&CHAR(10)&V87&CHAR(10)&Y87&CHAR(10)&Z87&CHAR(10)&AA87&CHAR(10)&AB87&CHAR(10)&AC87&CHAR(10)&AD87&CHAR(10)&AE87 | L87: =IF('微伴数据'!L84="","",'微伴数据'!L84) | M87: =IFERROR(VLOOKUP(#REF!,'第一课回放'!C:H,5,0),"0:00:00") | N87: =IFERROR(VLOOKUP(#REF!,'第二课直播'!D:L,9,0),"未到课") | S87: =IFERROR(VLOOKUP(A87,'微伴数据'!A:DB,12,0),"") | T87: =IFERROR(VLOOKUP(A87,'微伴数据'!A:DB,32,0),"") | U87: =IFERROR(VLOOKUP(A87,'微伴数据'!A:DC,81,0),"") | V87: =IFERROR(VLOOKUP(#REF!,'星橙地址'!A:V,9,0),"") | W87: =IFERROR(VLOOKUP(#REF!,'星橙地址'!A:V,10,0),"") | X87: =IFERROR(VLOOKUP(A87,'星云问卷'!A:O,8,0),"") | Y87: =IFERROR(VLOOKUP(A87,'星云问卷'!A:O,9,0),"") | Z87: =IFERROR(VLOOKUP(A87,'星云问卷'!A:O,10,0),"") | AA87: =IFERROR(VLOOKUP(A87,'星云问卷'!A:O,11,0),"") | AB87: =IFERROR(VLOOKUP(A87,'星云问卷'!A:O,12,0),"") | AC87: =IFERROR(VLOOKUP(A87,'星云问卷'!A:O,13,0),"") | AD87: =IFERROR(VLOOKUP(A87,'星云问卷'!A:O,14,0),"") | AE87: =IFERROR(VLOOKUP(A87,'星云问卷'!A:O,15,0),"") | AF87: =IFERROR(VLOOKUP(A87,'微伴数据'!A:DB,72,0),"") | AG87: 54DDFqYy | AH87: https://xiaobot.net/invitation/1cd11-757b7-22f48-354ba | AI87: 6dvEQ2a2 | AL87: =CONCATENATE( " 我把体验营用户专属福利给你发一下哈：" & CHAR(10) & CHAR(10), "1.《抖音商业IP课》" & CHAR(10), "兑换码：", AG87, CHAR(10), "兑换码使用地址：https://appamvpb5mq9834.h5.xiaoeknow.com/p/t/v1/ecommerce/mkt/redeem_index" & CHAR(10) & CHAR(10), "2.《生财有术66个项目精选》" & CHAR(10), "兑换码：", AH87, CHAR(10), "使用方式：微信搜索小报童投递-点击开始阅读-点击生财有术项目精选即可" & CHAR(10) & CHAR(10), "3.《生财365问》" & CHAR(10), "兑换码：", AI87, CHAR(10), "使用方式：https://appamvpb5mq9834.h5.xiaoeknow.com/p/t/v1/ecommerce/mkt/redeem_index")
A88: =IF('微伴数据'!A85="","",'微伴数据'!A85) | B88: =IF('微伴数据'!B85="","",'微伴数据'!B85) | C88: =IF('微伴数据'!G85="","",'微伴数据'!G85) | D88: =IF('微伴数据'!D85="","",'微伴数据'!D85) | E88: =IF('微伴数据'!CR85="","",'微伴数据'!CR85) | F88: =IF('微伴数据'!CL85="","",'微伴数据'!CL85) | G88: A | H88: 建联 | I88: =VLOOKUP(A88,'Sheet9'!A:A,1,0) | K88: =T88&CHAR(10)&U88&CHAR(10)&V88&CHAR(10)&Y88&CHAR(10)&Z88&CHAR(10)&AA88&CHAR(10)&AB88&CHAR(10)&AC88&CHAR(10)&AD88&CHAR(10)&AE88 | L88: =IF('微伴数据'!L85="","",'微伴数据'!L85) | M88: =IFERROR(VLOOKUP(#REF!,'第一课回放'!C:H,5,0),"0:00:00") | N88: =IFERROR(VLOOKUP(#REF!,'第二课直播'!D:L,9,0),"未到课") | S88: =IFERROR(VLOOKUP(A88,'微伴数据'!A:DB,12,0),"") | T88: =IFERROR(VLOOKUP(A88,'微伴数据'!A:DB,32,0),"") | U88: =IFERROR(VLOOKUP(A88,'微伴数据'!A:DC,81,0),"") | V88: =IFERROR(VLOOKUP(#REF!,'星橙地址'!A:V,9,0),"") | W88: =IFERROR(VLOOKUP(#REF!,'星橙地址'!A:V,10,0),"") | X88: =IFERROR(VLOOKUP(A88,'星云问卷'!A:O,8,0),"") | Y88: =IFERROR(VLOOKUP(A88,'星云问卷'!A:O,9,0),"") | Z88: =IFERROR(VLOOKUP(A88,'星云问卷'!A:O,10,0),"") | AA88: =IFERROR(VLOOKUP(A88,'星云问卷'!A:O,11,0),"") | AB88: =IFERROR(VLOOKUP(A88,'星云问卷'!A:O,12,0),"") | AC88: =IFERROR(VLOOKUP(A88,'星云问卷'!A:O,13,0),"") | AD88: =IFERROR(VLOOKUP(A88,'星云问卷'!A:O,14,0),"") | AE88: =IFERROR(VLOOKUP(A88,'星云问卷'!A:O,15,0),"") | AF88: =IFERROR(VLOOKUP(A88,'微伴数据'!A:DB,72,0),"") | AG88: 54CkcgNW | AH88: https://xiaobot.net/invitation/d4336-36bab-89d72-a6c2d/ | AI88: 6duPr6A7 | AL88: =CONCATENATE( " 我把体验营用户专属福利给你发一下哈：" & CHAR(10) & CHAR(10), "1.《抖音商业IP课》" & CHAR(10), "兑换码：", AG88, CHAR(10), "兑换码使用地址：https://appamvpb5mq9834.h5.xiaoeknow.com/p/t/v1/ecommerce/mkt/redeem_index" & CHAR(10) & CHAR(10), "2.《生财有术66个项目精选》" & CHAR(10), "兑换码：", AH88, CHAR(10), "使用方式：微信搜索小报童投递-点击开始阅读-点击生财有术项目精选即可" & CHAR(10) & CHAR(10), "3.《生财365问》" & CHAR(10), "兑换码：", AI88, CHAR(10), "使用方式：https://appamvpb5mq9834.h5.xiaoeknow.com/p/t/v1/ecommerce/mkt/redeem_index")
A89: =IF('微伴数据'!A86="","",'微伴数据'!A86) | B89: =IF('微伴数据'!B86="","",'微伴数据'!B86) | C89: =IF('微伴数据'!G86="","",'微伴数据'!G86) | D89: =IF('微伴数据'!D86="","",'微伴数据'!D86) | E89: =IF('微伴数据'!CR86="","",'微伴数据'!CR86) | F89: =IF('微伴数据'!CL86="","",'微伴数据'!CL86) | G89: B | H89: 建联 | I89: =VLOOKUP(A89,'Sheet9'!A:A,1,0) | K89: =T89&CHAR(10)&U89&CHAR(10)&V89&CHAR(10)&Y89&CHAR(10)&Z89&CHAR(10)&AA89&CHAR(10)&AB89&CHAR(10)&AC89&CHAR(10)&AD89&CHAR(10)&AE89 | L89: =IF('微伴数据'!L86="","",'微伴数据'!L86) | M89: =IFERROR(VLOOKUP(#REF!,'第一课回放'!C:H,5,0),"0:00:00") | N89: =IFERROR(VLOOKUP(#REF!,'第二课直播'!D:L,9,0),"未到课") | S89: =IFERROR(VLOOKUP(A89,'微伴数据'!A:DB,12,0),"") | T89: =IFERROR(VLOOKUP(A89,'微伴数据'!A:DB,32,0),"") | U89: =IFERROR(VLOOKUP(A89,'微伴数据'!A:DC,81,0),"") | V89: =IFERROR(VLOOKUP(#REF!,'星橙地址'!A:V,9,0),"") | W89: =IFERROR(VLOOKUP(#REF!,'星橙地址'!A:V,10,0),"") | X89: =IFERROR(VLOOKUP(A89,'星云问卷'!A:O,8,0),"") | Y89: =IFERROR(VLOOKUP(A89,'星云问卷'!A:O,9,0),"") | Z89: =IFERROR(VLOOKUP(A89,'星云问卷'!A:O,10,0),"") | AA89: =IFERROR(VLOOKUP(A89,'星云问卷'!A:O,11,0),"") | AB89: =IFERROR(VLOOKUP(A89,'星云问卷'!A:O,12,0),"") | AC89: =IFERROR(VLOOKUP(A89,'星云问卷'!A:O,13,0),"") | AD89: =IFERROR(VLOOKUP(A89,'星云问卷'!A:O,14,0),"") | AE89: =IFERROR(VLOOKUP(A89,'星云问卷'!A:O,15,0),"") | AF89: =IFERROR(VLOOKUP(A89,'微伴数据'!A:DB,72,0),"") | AL89: =CONCATENATE( " 我把体验营用户专属福利给你发一下哈：" & CHAR(10) & CHAR(10), "1.《抖音商业IP课》" & CHAR(10), "兑换码：", AG89, CHAR(10), "兑换码使用地址：https://appamvpb5mq9834.h5.xiaoeknow.com/p/t/v1/ecommerce/mkt/redeem_index" & CHAR(10) & CHAR(10), "2.《生财有术66个项目精选》" & CHAR(10), "兑换码：", AH89, CHAR(10), "使用方式：微信搜索小报童投递-点击开始阅读-点击生财有术项目精选即可" & CHAR(10) & CHAR(10), "3.《生财365问》" & CHAR(10), "兑换码：", AI89, CHAR(10), "使用方式：https://appamvpb5mq9834.h5.xiaoeknow.com/p/t/v1/ecommerce/mkt/redeem_index")
A90: =IF('微伴数据'!A87="","",'微伴数据'!A87) | B90: =IF('微伴数据'!B87="","",'微伴数据'!B87) | C90: =IF('微伴数据'!G87="","",'微伴数据'!G87) | D90: =IF('微伴数据'!D87="","",'微伴数据'!D87) | E90: =IF('微伴数据'!CR87="","",'微伴数据'!CR87) | F90: =IF('微伴数据'!CL87="","",'微伴数据'!CL87) | G90: B | H90: 建联 | I90: =VLOOKUP(A90,'Sheet9'!A:A,1,0) | K90: =T90&CHAR(10)&U90&CHAR(10)&V90&CHAR(10)&Y90&CHAR(10)&Z90&CHAR(10)&AA90&CHAR(10)&AB90&CHAR(10)&AC90&CHAR(10)&AD90&CHAR(10)&AE90 | L90: =IF('微伴数据'!L87="","",'微伴数据'!L87) | M90: =IFERROR(VLOOKUP(#REF!,'第一课回放'!C:H,5,0),"0:00:00") | N90: =IFERROR(VLOOKUP(#REF!,'第二课直播'!D:L,9,0),"未到课") | S90: =IFERROR(VLOOKUP(A90,'微伴数据'!A:DB,12,0),"") | T90: =IFERROR(VLOOKUP(A90,'微伴数据'!A:DB,32,0),"") | U90: =IFERROR(VLOOKUP(A90,'微伴数据'!A:DC,81,0),"") | V90: =IFERROR(VLOOKUP(#REF!,'星橙地址'!A:V,9,0),"") | W90: =IFERROR(VLOOKUP(#REF!,'星橙地址'!A:V,10,0),"") | X90: =IFERROR(VLOOKUP(A90,'星云问卷'!A:O,8,0),"") | Y90: =IFERROR(VLOOKUP(A90,'星云问卷'!A:O,9,0),"") | Z90: =IFERROR(VLOOKUP(A90,'星云问卷'!A:O,10,0),"") | AA90: =IFERROR(VLOOKUP(A90,'星云问卷'!A:O,11,0),"") | AB90: =IFERROR(VLOOKUP(A90,'星云问卷'!A:O,12,0),"") | AC90: =IFERROR(VLOOKUP(A90,'星云问卷'!A:O,13,0),"") | AD90: =IFERROR(VLOOKUP(A90,'星云问卷'!A:O,14,0),"") | AE90: =IFERROR(VLOOKUP(A90,'星云问卷'!A:O,15,0),"") | AF90: =IFERROR(VLOOKUP(A90,'微伴数据'!A:DB,72,0),"") | AL90: =CONCATENATE( " 我把体验营用户专属福利给你发一下哈：" & CHAR(10) & CHAR(10), "1.《抖音商业IP课》" & CHAR(10), "兑换码：", AG90, CHAR(10), "兑换码使用地址：https://appamvpb5mq9834.h5.xiaoeknow.com/p/t/v1/ecommerce/mkt/redeem_index" & CHAR(10) & CHAR(10), "2.《生财有术66个项目精选》" & CHAR(10), "兑换码：", AH90, CHAR(10), "使用方式：微信搜索小报童投递-点击开始阅读-点击生财有术项目精选即可" & CHAR(10) & CHAR(10), "3.《生财365问》" & CHAR(10), "兑换码：", AI90, CHAR(10), "使用方式：https://appamvpb5mq9834.h5.xiaoeknow.com/p/t/v1/ecommerce/mkt/redeem_index")
A91: =IF('微伴数据'!A88="","",'微伴数据'!A88) | B91: =IF('微伴数据'!B88="","",'微伴数据'!B88) | C91: =IF('微伴数据'!G88="","",'微伴数据'!G88) | D91: =IF('微伴数据'!D88="","",'微伴数据'!D88) | E91: =IF('微伴数据'!CR88="","",'微伴数据'!CR88) | F91: =IF('微伴数据'!CL88="","",'微伴数据'!CL88) | G91: B | H91: 建联 | I91: =VLOOKUP(A91,'Sheet9'!A:A,1,0) | K91: =T91&CHAR(10)&U91&CHAR(10)&V91&CHAR(10)&Y91&CHAR(10)&Z91&CHAR(10)&AA91&CHAR(10)&AB91&CHAR(10)&AC91&CHAR(10)&AD91&CHAR(10)&AE91 | L91: =IF('微伴数据'!L88="","",'微伴数据'!L88) | M91: =IFERROR(VLOOKUP(#REF!,'第一课回放'!C:H,5,0),"0:00:00") | N91: =IFERROR(VLOOKUP(#REF!,'第二课直播'!D:L,9,0),"未到课") | S91: =IFERROR(VLOOKUP(A91,'微伴数据'!A:DB,12,0),"") | T91: =IFERROR(VLOOKUP(A91,'微伴数据'!A:DB,32,0),"") | U91: =IFERROR(VLOOKUP(A91,'微伴数据'!A:DC,81,0),"") | V91: =IFERROR(VLOOKUP(#REF!,'星橙地址'!A:V,9,0),"") | W91: =IFERROR(VLOOKUP(#REF!,'星橙地址'!A:V,10,0),"") | X91: =IFERROR(VLOOKUP(A91,'星云问卷'!A:O,8,0),"") | Y91: =IFERROR(VLOOKUP(A91,'星云问卷'!A:O,9,0),"") | Z91: =IFERROR(VLOOKUP(A91,'星云问卷'!A:O,10,0),"") | AA91: =IFERROR(VLOOKUP(A91,'星云问卷'!A:O,11,0),"") | AB91: =IFERROR(VLOOKUP(A91,'星云问卷'!A:O,12,0),"") | AC91: =IFERROR(VLOOKUP(A91,'星云问卷'!A:O,13,0),"") | AD91: =IFERROR(VLOOKUP(A91,'星云问卷'!A:O,14,0),"") | AE91: =IFERROR(VLOOKUP(A91,'星云问卷'!A:O,15,0),"") | AF91: =IFERROR(VLOOKUP(A91,'微伴数据'!A:DB,72,0),"") | AL91: =CONCATENATE( " 我把体验营用户专属福利给你发一下哈：" & CHAR(10) & CHAR(10), "1.《抖音商业IP课》" & CHAR(10), "兑换码：", AG91, CHAR(10), "兑换码使用地址：https://appamvpb5mq9834.h5.xiaoeknow.com/p/t/v1/ecommerce/mkt/redeem_index" & CHAR(10) & CHAR(10), "2.《生财有术66个项目精选》" & CHAR(10), "兑换码：", AH91, CHAR(10), "使用方式：微信搜索小报童投递-点击开始阅读-点击生财有术项目精选即可" & CHAR(10) & CHAR(10), "3.《生财365问》" & CHAR(10), "兑换码：", AI91, CHAR(10), "使用方式：https://appamvpb5mq9834.h5.xiaoeknow.com/p/t/v1/ecommerce/mkt/redeem_index")
A92: =IF('微伴数据'!A89="","",'微伴数据'!A89) | B92: =IF('微伴数据'!B89="","",'微伴数据'!B89) | C92: =IF('微伴数据'!G89="","",'微伴数据'!G89) | D92: =IF('微伴数据'!D89="","",'微伴数据'!D89) | E92: =IF('微伴数据'!CR89="","",'微伴数据'!CR89) | F92: =IF('微伴数据'!CL89="","",'微伴数据'!CL89) | G92: B | H92: 建联 | I92: =VLOOKUP(A92,'Sheet9'!A:A,1,0) | K92: =T92&CHAR(10)&U92&CHAR(10)&V92&CHAR(10)&Y92&CHAR(10)&Z92&CHAR(10)&AA92&CHAR(10)&AB92&CHAR(10)&AC92&CHAR(10)&AD92&CHAR(10)&AE92 | L92: =IF('微伴数据'!L89="","",'微伴数据'!L89) | M92: =IFERROR(VLOOKUP(#REF!,'第一课回放'!C:H,5,0),"0:00:00") | N92: =IFERROR(VLOOKUP(#REF!,'第二课直播'!D:L,9,0),"未到课") | S92: =IFERROR(VLOOKUP(A92,'微伴数据'!A:DB,12,0),"") | T92: =IFERROR(VLOOKUP(A92,'微伴数据'!A:DB,32,0),"") | U92: =IFERROR(VLOOKUP(A92,'微伴数据'!A:DC,81,0),"") | V92: =IFERROR(VLOOKUP(#REF!,'星橙地址'!A:V,9,0),"") | W92: =IFERROR(VLOOKUP(#REF!,'星橙地址'!A:V,10,0),"") | X92: =IFERROR(VLOOKUP(A92,'星云问卷'!A:O,8,0),"") | Y92: =IFERROR(VLOOKUP(A92,'星云问卷'!A:O,9,0),"") | Z92: =IFERROR(VLOOKUP(A92,'星云问卷'!A:O,10,0),"") | AA92: =IFERROR(VLOOKUP(A92,'星云问卷'!A:O,11,0),"") | AB92: =IFERROR(VLOOKUP(A92,'星云问卷'!A:O,12,0),"") | AC92: =IFERROR(VLOOKUP(A92,'星云问卷'!A:O,13,0),"") | AD92: =IFERROR(VLOOKUP(A92,'星云问卷'!A:O,14,0),"") | AE92: =IFERROR(VLOOKUP(A92,'星云问卷'!A:O,15,0),"") | AF92: =IFERROR(VLOOKUP(A92,'微伴数据'!A:DB,72,0),"") | AL92: =CONCATENATE( " 我把体验营用户专属福利给你发一下哈：" & CHAR(10) & CHAR(10), "1.《抖音商业IP课》" & CHAR(10), "兑换码：", AG92, CHAR(10), "兑换码使用地址：https://appamvpb5mq9834.h5.xiaoeknow.com/p/t/v1/ecommerce/mkt/redeem_index" & CHAR(10) & CHAR(10), "2.《生财有术66个项目精选》" & CHAR(10), "兑换码：", AH92, CHAR(10), "使用方式：微信搜索小报童投递-点击开始阅读-点击生财有术项目精选即可" & CHAR(10) & CHAR(10), "3.《生财365问》" & CHAR(10), "兑换码：", AI92, CHAR(10), "使用方式：https://appamvpb5mq9834.h5.xiaoeknow.com/p/t/v1/ecommerce/mkt/redeem_index")
A93: =IF('微伴数据'!A90="","",'微伴数据'!A90) | B93: =IF('微伴数据'!B90="","",'微伴数据'!B90) | C93: =IF('微伴数据'!G90="","",'微伴数据'!G90) | D93: =IF('微伴数据'!D90="","",'微伴数据'!D90) | E93: =IF('微伴数据'!CR90="","",'微伴数据'!CR90) | F93: =IF('微伴数据'!CL90="","",'微伴数据'!CL90) | G93: B | H93: 建联 | I93: =VLOOKUP(A93,'Sheet9'!A:A,1,0) | K93: =T93&CHAR(10)&U93&CHAR(10)&V93&CHAR(10)&Y93&CHAR(10)&Z93&CHAR(10)&AA93&CHAR(10)&AB93&CHAR(10)&AC93&CHAR(10)&AD93&CHAR(10)&AE93 | L93: =IF('微伴数据'!L90="","",'微伴数据'!L90) | M93: =IFERROR(VLOOKUP(#REF!,'第一课回放'!C:H,5,0),"0:00:00") | N93: =IFERROR(VLOOKUP(#REF!,'第二课直播'!D:L,9,0),"未到课") | S93: =IFERROR(VLOOKUP(A93,'微伴数据'!A:DB,12,0),"") | T93: =IFERROR(VLOOKUP(A93,'微伴数据'!A:DB,32,0),"") | U93: =IFERROR(VLOOKUP(A93,'微伴数据'!A:DC,81,0),"") | V93: =IFERROR(VLOOKUP(#REF!,'星橙地址'!A:V,9,0),"") | W93: =IFERROR(VLOOKUP(#REF!,'星橙地址'!A:V,10,0),"") | X93: =IFERROR(VLOOKUP(A93,'星云问卷'!A:O,8,0),"") | Y93: =IFERROR(VLOOKUP(A93,'星云问卷'!A:O,9,0),"") | Z93: =IFERROR(VLOOKUP(A93,'星云问卷'!A:O,10,0),"") | AA93: =IFERROR(VLOOKUP(A93,'星云问卷'!A:O,11,0),"") | AB93: =IFERROR(VLOOKUP(A93,'星云问卷'!A:O,12,0),"") | AC93: =IFERROR(VLOOKUP(A93,'星云问卷'!A:O,13,0),"") | AD93: =IFERROR(VLOOKUP(A93,'星云问卷'!A:O,14,0),"") | AE93: =IFERROR(VLOOKUP(A93,'星云问卷'!A:O,15,0),"") | AF93: =IFERROR(VLOOKUP(A93,'微伴数据'!A:DB,72,0),"") | AG93: 54BDQYm4 | AH93: https://xiaobot.net/invitation/e4a33-02716-674a2-42d1f/ | AI93: 6drMFvw5 | AL93: =CONCATENATE( " 我把体验营用户专属福利给你发一下哈：" & CHAR(10) & CHAR(10), "1.《抖音商业IP课》" & CHAR(10), "兑换码：", AG93, CHAR(10), "兑换码使用地址：https://appamvpb5mq9834.h5.xiaoeknow.com/p/t/v1/ecommerce/mkt/redeem_index" & CHAR(10) & CHAR(10), "2.《生财有术66个项目精选》" & CHAR(10), "兑换码：", AH93, CHAR(10), "使用方式：微信搜索小报童投递-点击开始阅读-点击生财有术项目精选即可" & CHAR(10) & CHAR(10), "3.《生财365问》" & CHAR(10), "兑换码：", AI93, CHAR(10), "使用方式：https://appamvpb5mq9834.h5.xiaoeknow.com/p/t/v1/ecommerce/mkt/redeem_index")
A94: =IF('微伴数据'!A91="","",'微伴数据'!A91) | B94: =IF('微伴数据'!B91="","",'微伴数据'!B91) | C94: =IF('微伴数据'!G91="","",'微伴数据'!G91) | D94: =IF('微伴数据'!D91="","",'微伴数据'!D91) | E94: =IF('微伴数据'!CR91="","",'微伴数据'!CR91) | F94: =IF('微伴数据'!CL91="","",'微伴数据'!CL91) | G94: A | H94: 建联 | I94: =VLOOKUP(A94,'Sheet9'!A:A,1,0) | K94: =T94&CHAR(10)&U94&CHAR(10)&V94&CHAR(10)&Y94&CHAR(10)&Z94&CHAR(10)&AA94&CHAR(10)&AB94&CHAR(10)&AC94&CHAR(10)&AD94&CHAR(10)&AE94 | L94: =IF('微伴数据'!L91="","",'微伴数据'!L91) | M94: =IFERROR(VLOOKUP(#REF!,'第一课回放'!C:H,5,0),"0:00:00") | N94: =IFERROR(VLOOKUP(#REF!,'第二课直播'!D:L,9,0),"未到课") | S94: =IFERROR(VLOOKUP(A94,'微伴数据'!A:DB,12,0),"") | T94: =IFERROR(VLOOKUP(A94,'微伴数据'!A:DB,32,0),"") | U94: =IFERROR(VLOOKUP(A94,'微伴数据'!A:DC,81,0),"") | V94: =IFERROR(VLOOKUP(#REF!,'星橙地址'!A:V,9,0),"") | W94: =IFERROR(VLOOKUP(#REF!,'星橙地址'!A:V,10,0),"") | X94: =IFERROR(VLOOKUP(A94,'星云问卷'!A:O,8,0),"") | Y94: =IFERROR(VLOOKUP(A94,'星云问卷'!A:O,9,0),"") | Z94: =IFERROR(VLOOKUP(A94,'星云问卷'!A:O,10,0),"") | AA94: =IFERROR(VLOOKUP(A94,'星云问卷'!A:O,11,0),"") | AB94: =IFERROR(VLOOKUP(A94,'星云问卷'!A:O,12,0),"") | AC94: =IFERROR(VLOOKUP(A94,'星云问卷'!A:O,13,0),"") | AD94: =IFERROR(VLOOKUP(A94,'星云问卷'!A:O,14,0),"") | AE94: =IFERROR(VLOOKUP(A94,'星云问卷'!A:O,15,0),"") | AF94: =IFERROR(VLOOKUP(A94,'微伴数据'!A:DB,72,0),"") | AL94: =CONCATENATE( " 我把体验营用户专属福利给你发一下哈：" & CHAR(10) & CHAR(10), "1.《抖音商业IP课》" & CHAR(10), "兑换码：", AG94, CHAR(10), "兑换码使用地址：https://appamvpb5mq9834.h5.xiaoeknow.com/p/t/v1/ecommerce/mkt/redeem_index" & CHAR(10) & CHAR(10), "2.《生财有术66个项目精选》" & CHAR(10), "兑换码：", AH94, CHAR(10), "使用方式：微信搜索小报童投递-点击开始阅读-点击生财有术项目精选即可" & CHAR(10) & CHAR(10), "3.《生财365问》" & CHAR(10), "兑换码：", AI94, CHAR(10), "使用方式：https://appamvpb5mq9834.h5.xiaoeknow.com/p/t/v1/ecommerce/mkt/redeem_index")
A95: =IF('微伴数据'!A92="","",'微伴数据'!A92) | B95: =IF('微伴数据'!B92="","",'微伴数据'!B92) | C95: =IF('微伴数据'!G92="","",'微伴数据'!G92) | D95: =IF('微伴数据'!D92="","",'微伴数据'!D92) | E95: =IF('微伴数据'!CR92="","",'微伴数据'!CR92) | F95: =IF('微伴数据'!CL92="","",'微伴数据'!CL92) | G95: A | H95: 建联 | I95: =VLOOKUP(A95,'Sheet9'!A:A,1,0) | K95: =T95&CHAR(10)&U95&CHAR(10)&V95&CHAR(10)&Y95&CHAR(10)&Z95&CHAR(10)&AA95&CHAR(10)&AB95&CHAR(10)&AC95&CHAR(10)&AD95&CHAR(10)&AE95 | L95: =IF('微伴数据'!L92="","",'微伴数据'!L92) | M95: =IFERROR(VLOOKUP(#REF!,'第一课回放'!C:H,5,0),"0:00:00") | N95: =IFERROR(VLOOKUP(#REF!,'第二课直播'!D:L,9,0),"未到课") | O95: https://scys.com/activity/landing/5528?tabIndex=0读后感：太详细了，平台用心了。照着弄傻白甜也能搞出来东西。想拿到结果，技术真的不是最重要的一环，创意点子需求才重要。“一个简陋的粗糙的有持续收入的网页，胜过华丽的完美的没营收的网站”，学习了，感谢。 | S95: =IFERROR(VLOOKUP(A95,'微伴数据'!A:DB,12,0),"") | T95: =IFERROR(VLOOKUP(A95,'微伴数据'!A:DB,32,0),"") | U95: =IFERROR(VLOOKUP(A95,'微伴数据'!A:DC,81,0),"") | V95: =IFERROR(VLOOKUP(#REF!,'星橙地址'!A:V,9,0),"") | W95: =IFERROR(VLOOKUP(#REF!,'星橙地址'!A:V,10,0),"") | X95: 深圳 | Y95: 程序员 | Z95: 工作4-8年 | AA95: 年收入7-12万 | AB95: 做过项目或正在做项目，但没有拿到结果或是不聚焦 | AC95: 没有 | AD95: 公众号 | AE95: 小红书项目指导 | AF95: =IFERROR(VLOOKUP(A95,'微伴数据'!A:DB,72,0),"") | AL95: =CONCATENATE( " 我把体验营用户专属福利给你发一下哈：" & CHAR(10) & CHAR(10), "1.《抖音商业IP课》" & CHAR(10), "兑换码：", AG95, CHAR(10), "兑换码使用地址：https://appamvpb5mq9834.h5.xiaoeknow.com/p/t/v1/ecommerce/mkt/redeem_index" & CHAR(10) & CHAR(10), "2.《生财有术66个项目精选》" & CHAR(10), "兑换码：", AH95, CHAR(10), "使用方式：微信搜索小报童投递-点击开始阅读-点击生财有术项目精选即可" & CHAR(10) & CHAR(10), "3.《生财365问》" & CHAR(10), "兑换码：", AI95, CHAR(10), "使用方式：https://appamvpb5mq9834.h5.xiaoeknow.com/p/t/v1/ecommerce/mkt/redeem_index") | AO95: 纳入用户画像
A96: =IF('微伴数据'!A93="","",'微伴数据'!A93) | B96: =IF('微伴数据'!B93="","",'微伴数据'!B93) | C96: =IF('微伴数据'!G93="","",'微伴数据'!G93) | D96: =IF('微伴数据'!D93="","",'微伴数据'!D93) | E96: =IF('微伴数据'!CR93="","",'微伴数据'!CR93) | F96: =IF('微伴数据'!CL93="","",'微伴数据'!CL93) | G96: B | H96: 建联 | I96: =VLOOKUP(A96,'Sheet9'!A:A,1,0) | K96: =T96&CHAR(10)&U96&CHAR(10)&V96&CHAR(10)&Y96&CHAR(10)&Z96&CHAR(10)&AA96&CHAR(10)&AB96&CHAR(10)&AC96&CHAR(10)&AD96&CHAR(10)&AE96 | L96: =IF('微伴数据'!L93="","",'微伴数据'!L93) | M96: =IFERROR(VLOOKUP(#REF!,'第一课回放'!C:H,5,0),"0:00:00") | N96: =IFERROR(VLOOKUP(#REF!,'第二课直播'!D:L,9,0),"未到课") | S96: =IFERROR(VLOOKUP(A96,'微伴数据'!A:DB,12,0),"") | T96: =IFERROR(VLOOKUP(A96,'微伴数据'!A:DB,32,0),"") | U96: =IFERROR(VLOOKUP(A96,'微伴数据'!A:DC,81,0),"") | V96: =IFERROR(VLOOKUP(#REF!,'星橙地址'!A:V,9,0),"") | W96: =IFERROR(VLOOKUP(#REF!,'星橙地址'!A:V,10,0),"") | X96: =IFERROR(VLOOKUP(A96,'星云问卷'!A:O,8,0),"") | Y96: =IFERROR(VLOOKUP(A96,'星云问卷'!A:O,9,0),"") | Z96: =IFERROR(VLOOKUP(A96,'星云问卷'!A:O,10,0),"") | AA96: =IFERROR(VLOOKUP(A96,'星云问卷'!A:O,11,0),"") | AB96: =IFERROR(VLOOKUP(A96,'星云问卷'!A:O,12,0),"") | AC96: =IFERROR(VLOOKUP(A96,'星云问卷'!A:O,13,0),"") | AD96: =IFERROR(VLOOKUP(A96,'星云问卷'!A:O,14,0),"") | AE96: =IFERROR(VLOOKUP(A96,'星云问卷'!A:O,15,0),"") | AF96: =IFERROR(VLOOKUP(A96,'微伴数据'!A:DB,72,0),"") | AL96: =CONCATENATE( " 我把体验营用户专属福利给你发一下哈：" & CHAR(10) & CHAR(10), "1.《抖音商业IP课》" & CHAR(10), "兑换码：", AG96, CHAR(10), "兑换码使用地址：https://appamvpb5mq9834.h5.xiaoeknow.com/p/t/v1/ecommerce/mkt/redeem_index" & CHAR(10) & CHAR(10), "2.《生财有术66个项目精选》" & CHAR(10), "兑换码：", AH96, CHAR(10), "使用方式：微信搜索小报童投递-点击开始阅读-点击生财有术项目精选即可" & CHAR(10) & CHAR(10), "3.《生财365问》" & CHAR(10), "兑换码：", AI96, CHAR(10), "使用方式：https://appamvpb5mq9834.h5.xiaoeknow.com/p/t/v1/ecommerce/mkt/redeem_index")
A97: =IF('微伴数据'!A94="","",'微伴数据'!A94) | B97: =IF('微伴数据'!B94="","",'微伴数据'!B94) | C97: =IF('微伴数据'!G94="","",'微伴数据'!G94) | D97: =IF('微伴数据'!D94="","",'微伴数据'!D94) | E97: =IF('微伴数据'!CR94="","",'微伴数据'!CR94) | F97: =IF('微伴数据'!CL94="","",'微伴数据'!CL94) | G97: S | H97: 建联 | I97: =VLOOKUP(A97,'Sheet9'!A:A,1,0) | K97: =T97&CHAR(10)&U97&CHAR(10)&V97&CHAR(10)&Y97&CHAR(10)&Z97&CHAR(10)&AA97&CHAR(10)&AB97&CHAR(10)&AC97&CHAR(10)&AD97&CHAR(10)&AE97 | L97: =IF('微伴数据'!L94="","",'微伴数据'!L94) | M97: =IFERROR(VLOOKUP(#REF!,'第一课回放'!C:H,5,0),"0:00:00") | N97: =IFERROR(VLOOKUP(#REF!,'第二课直播'!D:L,9,0),"未到课") | S97: =IFERROR(VLOOKUP(A97,'微伴数据'!A:DB,12,0),"") | T97: =IFERROR(VLOOKUP(A97,'微伴数据'!A:DB,32,0),"") | U97: =IFERROR(VLOOKUP(A97,'微伴数据'!A:DC,81,0),"") | V97: =IFERROR(VLOOKUP(#REF!,'星橙地址'!A:V,9,0),"") | W97: =IFERROR(VLOOKUP(#REF!,'星橙地址'!A:V,10,0),"") | X97: =IFERROR(VLOOKUP(A97,'星云问卷'!A:O,8,0),"") | Y97: =IFERROR(VLOOKUP(A97,'星云问卷'!A:O,9,0),"") | Z97: =IFERROR(VLOOKUP(A97,'星云问卷'!A:O,10,0),"") | AA97: =IFERROR(VLOOKUP(A97,'星云问卷'!A:O,11,0),"") | AB97: =IFERROR(VLOOKUP(A97,'星云问卷'!A:O,12,0),"") | AC97: =IFERROR(VLOOKUP(A97,'星云问卷'!A:O,13,0),"") | AD97: =IFERROR(VLOOKUP(A97,'星云问卷'!A:O,14,0),"") | AE97: =IFERROR(VLOOKUP(A97,'星云问卷'!A:O,15,0),"") | AF97: =IFERROR(VLOOKUP(A97,'微伴数据'!A:DB,72,0),"") | AL97: =CONCATENATE( " 我把体验营用户专属福利给你发一下哈：" & CHAR(10) & CHAR(10), "1.《抖音商业IP课》" & CHAR(10), "兑换码：", AG97, CHAR(10), "兑换码使用地址：https://appamvpb5mq9834.h5.xiaoeknow.com/p/t/v1/ecommerce/mkt/redeem_index" & CHAR(10) & CHAR(10), "2.《生财有术66个项目精选》" & CHAR(10), "兑换码：", AH97, CHAR(10), "使用方式：微信搜索小报童投递-点击开始阅读-点击生财有术项目精选即可" & CHAR(10) & CHAR(10), "3.《生财365问》" & CHAR(10), "兑换码：", AI97, CHAR(10), "使用方式：https://appamvpb5mq9834.h5.xiaoeknow.com/p/t/v1/ecommerce/mkt/redeem_index")
A98: =IF('微伴数据'!A95="","",'微伴数据'!A95) | B98: =IF('微伴数据'!B95="","",'微伴数据'!B95) | C98: =IF('微伴数据'!G95="","",'微伴数据'!G95) | D98: =IF('微伴数据'!D95="","",'微伴数据'!D95) | E98: =IF('微伴数据'!CR95="","",'微伴数据'!CR95) | F98: =IF('微伴数据'!CL95="","",'微伴数据'!CL95) | G98: A | H98: 建联 | I98: =VLOOKUP(A98,'Sheet9'!A:A,1,0) | K98: =T98&CHAR(10)&U98&CHAR(10)&V98&CHAR(10)&Y98&CHAR(10)&Z98&CHAR(10)&AA98&CHAR(10)&AB98&CHAR(10)&AC98&CHAR(10)&AD98&CHAR(10)&AE98 | L98: =IF('微伴数据'!L95="","",'微伴数据'!L95) | M98: =IFERROR(VLOOKUP(#REF!,'第一课回放'!C:H,5,0),"0:00:00") | N98: =IFERROR(VLOOKUP(#REF!,'第二课直播'!D:L,9,0),"未到课") | S98: =IFERROR(VLOOKUP(A98,'微伴数据'!A:DB,12,0),"") | T98: =IFERROR(VLOOKUP(A98,'微伴数据'!A:DB,32,0),"") | U98: =IFERROR(VLOOKUP(A98,'微伴数据'!A:DC,81,0),"") | V98: =IFERROR(VLOOKUP(#REF!,'星橙地址'!A:V,9,0),"") | W98: =IFERROR(VLOOKUP(#REF!,'星橙地址'!A:V,10,0),"") | X98: =IFERROR(VLOOKUP(A98,'星云问卷'!A:O,8,0),"") | Y98: =IFERROR(VLOOKUP(A98,'星云问卷'!A:O,9,0),"") | Z98: =IFERROR(VLOOKUP(A98,'星云问卷'!A:O,10,0),"") | AA98: =IFERROR(VLOOKUP(A98,'星云问卷'!A:O,11,0),"") | AB98: =IFERROR(VLOOKUP(A98,'星云问卷'!A:O,12,0),"") | AC98: =IFERROR(VLOOKUP(A98,'星云问卷'!A:O,13,0),"") | AD98: =IFERROR(VLOOKUP(A98,'星云问卷'!A:O,14,0),"") | AE98: =IFERROR(VLOOKUP(A98,'星云问卷'!A:O,15,0),"") | AF98: =IFERROR(VLOOKUP(A98,'微伴数据'!A:DB,72,0),"") | AG98: 54Ah7xbf | AH98: https://xiaobot.net/invitation/365f7-38b8b-0d2fe-f0282/ | AI98: 6dqWJ5zU | AL98: =CONCATENATE( " 我把体验营用户专属福利给你发一下哈：" & CHAR(10) & CHAR(10), "1.《抖音商业IP课》" & CHAR(10), "兑换码：", AG98, CHAR(10), "兑换码使用地址：https://appamvpb5mq9834.h5.xiaoeknow.com/p/t/v1/ecommerce/mkt/redeem_index" & CHAR(10) & CHAR(10), "2.《生财有术66个项目精选》" & CHAR(10), "兑换码：", AH98, CHAR(10), "使用方式：微信搜索小报童投递-点击开始阅读-点击生财有术项目精选即可" & CHAR(10) & CHAR(10), "3.《生财365问》" & CHAR(10), "兑换码：", AI98, CHAR(10), "使用方式：https://appamvpb5mq9834.h5.xiaoeknow.com/p/t/v1/ecommerce/mkt/redeem_index")
A99: =IF('微伴数据'!A96="","",'微伴数据'!A96) | B99: =IF('微伴数据'!B96="","",'微伴数据'!B96) | C99: =IF('微伴数据'!G96="","",'微伴数据'!G96) | D99: =IF('微伴数据'!D96="","",'微伴数据'!D96) | E99: =IF('微伴数据'!CR96="","",'微伴数据'!CR96) | F99: =IF('微伴数据'!CL96="","",'微伴数据'!CL96) | G99: B | H99: 建联 | I99: =VLOOKUP(A99,'Sheet9'!A:A,1,0) | K99: =T99&CHAR(10)&U99&CHAR(10)&V99&CHAR(10)&Y99&CHAR(10)&Z99&CHAR(10)&AA99&CHAR(10)&AB99&CHAR(10)&AC99&CHAR(10)&AD99&CHAR(10)&AE99 | L99: =IF('微伴数据'!L96="","",'微伴数据'!L96) | M99: =IFERROR(VLOOKUP(#REF!,'第一课回放'!C:H,5,0),"0:00:00") | N99: =IFERROR(VLOOKUP(#REF!,'第二课直播'!D:L,9,0),"未到课") | S99: =IFERROR(VLOOKUP(A99,'微伴数据'!A:DB,12,0),"") | T99: =IFERROR(VLOOKUP(A99,'微伴数据'!A:DB,32,0),"") | U99: =IFERROR(VLOOKUP(A99,'微伴数据'!A:DC,81,0),"") | V99: =IFERROR(VLOOKUP(#REF!,'星橙地址'!A:V,9,0),"") | W99: =IFERROR(VLOOKUP(#REF!,'星橙地址'!A:V,10,0),"") | X99: =IFERROR(VLOOKUP(A99,'星云问卷'!A:O,8,0),"") | Y99: =IFERROR(VLOOKUP(A99,'星云问卷'!A:O,9,0),"") | Z99: =IFERROR(VLOOKUP(A99,'星云问卷'!A:O,10,0),"") | AA99: =IFERROR(VLOOKUP(A99,'星云问卷'!A:O,11,0),"") | AB99: =IFERROR(VLOOKUP(A99,'星云问卷'!A:O,12,0),"") | AC99: =IFERROR(VLOOKUP(A99,'星云问卷'!A:O,13,0),"") | AD99: =IFERROR(VLOOKUP(A99,'星云问卷'!A:O,14,0),"") | AE99: =IFERROR(VLOOKUP(A99,'星云问卷'!A:O,15,0),"") | AF99: =IFERROR(VLOOKUP(A99,'微伴数据'!A:DB,72,0),"") | AL99: =CONCATENATE( " 我把体验营用户专属福利给你发一下哈：" & CHAR(10) & CHAR(10), "1.《抖音商业IP课》" & CHAR(10), "兑换码：", AG99, CHAR(10), "兑换码使用地址：https://appamvpb5mq9834.h5.xiaoeknow.com/p/t/v1/ecommerce/mkt/redeem_index" & CHAR(10) & CHAR(10), "2.《生财有术66个项目精选》" & CHAR(10), "兑换码：", AH99, CHAR(10), "使用方式：微信搜索小报童投递-点击开始阅读-点击生财有术项目精选即可" & CHAR(10) & CHAR(10), "3.《生财365问》" & CHAR(10), "兑换码：", AI99, CHAR(10), "使用方式：https://appamvpb5mq9834.h5.xiaoeknow.com/p/t/v1/ecommerce/mkt/redeem_index")
A100: =IF('微伴数据'!A97="","",'微伴数据'!A97) | B100: =IF('微伴数据'!B97="","",'微伴数据'!B97) | C100: =IF('微伴数据'!G97="","",'微伴数据'!G97) | D100: =IF('微伴数据'!D97="","",'微伴数据'!D97) | E100: =IF('微伴数据'!CR97="","",'微伴数据'!CR97) | F100: =IF('微伴数据'!CL97="","",'微伴数据'!CL97) | G100: B | H100: 建联 | I100: =VLOOKUP(A100,'Sheet9'!A:A,1,0) | K100: =T100&CHAR(10)&U100&CHAR(10)&V100&CHAR(10)&Y100&CHAR(10)&Z100&CHAR(10)&AA100&CHAR(10)&AB100&CHAR(10)&AC100&CHAR(10)&AD100&CHAR(10)&AE100 | L100: =IF('微伴数据'!L97="","",'微伴数据'!L97) | M100: =IFERROR(VLOOKUP(#REF!,'第一课回放'!C:H,5,0),"0:00:00") | N100: =IFERROR(VLOOKUP(#REF!,'第二课直播'!D:L,9,0),"未到课") | O100: 星球标题：AI内容变现单月10W的底层逻辑：AI能力，定位，流量，变现，AI编程放大 星球链接：AI内容变现单月10W的底层逻辑：AI能力，定位，流量，变现，AI编程放大 读后感：AI时代，我们每个人都应该学会使用AI来帮助我们，熟练几个AI工具，现在做AI真正赚钱的是那些懂AI应用场景的人，利用AI的能力加上你的专业认知，才能创造真正的价值。不要给AI设限，它比我们想象的要懂得多，能做的也要多得多，但有一点，AI无法帮我们链接资源。 | S100: =IFERROR(VLOOKUP(A100,'微伴数据'!A:DB,12,0),"") | T100: =IFERROR(VLOOKUP(A100,'微伴数据'!A:DB,32,0),"") | U100: =IFERROR(VLOOKUP(A100,'微伴数据'!A:DC,81,0),"") | V100: =IFERROR(VLOOKUP(#REF!,'星橙地址'!A:V,9,0),"") | W100: =IFERROR(VLOOKUP(#REF!,'星橙地址'!A:V,10,0),"") | X100: =IFERROR(VLOOKUP(A100,'星云问卷'!A:O,8,0),"") | Y100: =IFERROR(VLOOKUP(A100,'星云问卷'!A:O,9,0),"") | Z100: =IFERROR(VLOOKUP(A100,'星云问卷'!A:O,10,0),"") | AA100: =IFERROR(VLOOKUP(A100,'星云问卷'!A:O,11,0),"") | AB100: =IFERROR(VLOOKUP(A100,'星云问卷'!A:O,12,0),"") | AC100: =IFERROR(VLOOKUP(A100,'星云问卷'!A:O,13,0),"") | AD100: =IFERROR(VLOOKUP(A100,'星云问卷'!A:O,14,0),"") | AE100: =IFERROR(VLOOKUP(A100,'星云问卷'!A:O,15,0),"") | AF100: =IFERROR(VLOOKUP(A100,'微伴数据'!A:DB,72,0),"") | AL100: =CONCATENATE( " 我把体验营用户专属福利给你发一下哈：" & CHAR(10) & CHAR(10), "1.《抖音商业IP课》" & CHAR(10), "兑换码：", AG100, CHAR(10), "兑换码使用地址：https://appamvpb5mq9834.h5.xiaoeknow.com/p/t/v1/ecommerce/mkt/redeem_index" & CHAR(10) & CHAR(10), "2.《生财有术66个项目精选》" & CHAR(10), "兑换码：", AH100, CHAR(10), "使用方式：微信搜索小报童投递-点击开始阅读-点击生财有术项目精选即可" & CHAR(10) & CHAR(10), "3.《生财365问》" & CHAR(10), "兑换码：", AI100, CHAR(10), "使用方式：https://appamvpb5mq9834.h5.xiaoeknow.com/p/t/v1/ecommerce/mkt/redeem_index") | AO100: 纳入用户画像
...

Sheet 微伴数据
A1: 客户名称 | B1: 备注名 | C1: 客户描述 | D1: 流失状态 | E1: 流失时间 | F1: 企业名称 | G1: 所属客服 | H1: 客服所属部门 | I1: 客户评分 | J1: 客户积分 | K1: 个人标签 | L1: 企业标签 | M1: 客户状态 | N1: 添加时间 | O1: 最近沟通时间 | P1: 添加渠道 | Q1: 企微来源 | R1: unionid | S1: external_userid | T1: 标签 | U1: 职位 | V1: 企业 | W1: 描述 | X1: 城市/地区 | Y1: 详细地址 | Z1: QQ | AA1: 微博 | AB1: 生日 | AC1: 邮箱 | AD1: 年龄 | AE1: 电话 | AF1: 性别 | AG1: 时间 | AH1: 来源 | AI1: 标签组(328杭州AI大会) | AJ1: 标签组(深海圈专用) | AK1: 标签组(直播课件) | AL1: 标签组(生财AI宝典纸质版) | AM1: 标签组(0204直播文稿) | AN1: 标签组(0129直播) | AO1: 标签组(0124航海家大会) | AP1: 标签组(视频号直播) | AQ1: 标签组(交付组26年专用) | AR1: 标签组(B站好物) | AS1: 标签组(深海圈丨YouTube AI 视频) | AT1: 标签组(深海圈丨AI产品出海) | AU1: 标签组(双11) | AV1: 标签组(25年双11交付用) | AW1: 标签组(25年双十一激活) | AX1: 标签组(往期未续费) | AY1: 标签组(超级标超级术推送) | AZ1: 标签组(直播文稿) | BA1: 标签组(生财宝典共读营) | BB1: 标签组(0626直播文稿) | BC1: 标签组(生财宝典共读营进群) | BD1: 标签组(生财宝典共读营期数) | BE1: 标签组(0428临时标签) | BF1: 标签组(第九年新人承接) | BG1: 标签组(用户转移) | BH1: 标签组(25年418非会员触达) | BI1: 标签组(25年418专用) | BJ1: 标签组(直播用) | BK1: 标签组(触达相关) | BL1: 标签组(0221续费) | BM1: 标签组(续费相关) | BN1: 标签组(临时标签) | BO1: 标签组(0121精华共读) | BP1: 标签组(0117续费提醒) | BQ1: 标签组(标签化分流) | BR1: 标签组(转移客户) | BS1: 标签组(测试微伴批量) | BT1: 标签组(航海家见面会) | BU1: 标签组(鱼丸触达) | BV1: 标签组(测试0831) | BW1: 标签组(测试专用标签组) | BX1: 标签组(周边产品) | BY1: 标签组(航海家部门) | BZ1: 标签组(新人营第三期) | CA1: 标签组(航海家) | CB1: 标签组(第二期新人营邀请进群) | CC1: 标签组(新人营2期群邀请-霜仔) | CD1: 标签组(第八期) | CE1: 标签组(用户分销) | CF1: 标签组(用户分层) | CG1: 标签组(2024年非圈友召回测试) | CH1: 标签组(转化组群发) | CI1: 标签组(企微导流) | CJ1: 标签组(渠道来源4) | CK1: 标签组(渠道来源3) | CL1: 标签组(体验营用户进群情况) | CM1: 标签组(企微合集推送) | CN1: 标签组(渠道来源2) | CO1: 标签组(回复) | CP1: 标签组(体验营问卷) | CQ1: 标签组(用户) | CR1: 标签组(会员) | CS1: 标签组(用户质量) | CT1: 标签组(体验营期数) | CU1: 标签组(体验营类型) | CV1: 标签组(渠道来源) | CW1: 标签组(【搜索引擎】) | CX1: 标签组(【0415刀姐姐星球承接】) | CY1: 标签组(为友承接) | CZ1: 标签组(2023年) | DA1: 标签组(小报童) | DB1: 标签组(公众号) | DC1: 标签组(【直播承接】) | DD1: 标签组(企业微信名片) | DE1: 标签组(2022年418群发) | DF1: 标签组(圈友) | DG1: 标签组(非会员) | DH1: 标签组(渠道) | DI1: 标签组(共读营电子书) | DJ1: 标签组(生财课程) | DK1: 标签组(添加个微) | DL1: 标签组(日历音频) | DM1: 标签组(2022生财日历) | DN1: 标签组(小航海项目主题) | DO1: 标签组(往期体验营) | DP1: 标签组(生财活动) | DQ1: 标签组(城市) | DR1: 标签组(兴趣话题) | DS1: 标签组(伙伴猫系统标签) | DT1: 标签组(生财团队) | DU1: 标签组(生财团队)
A2: 上房揭瓦 | B2: 延期 问 【9】【9体117】 上房揭瓦 | C2: B0523_EC0C489D61DF8B3E32FF85487DA7DECC5194F219CF554649F1C4F9C615435A82_D2064 | D2: 未流失 | F2: 个人微信 | G2: 鱼丸115 | H2: 生财有术 | I2: 0 | J2: 0 | K2: - | L2: 【9进142】,问卷_已填,会员_7,【9体142】,全量数据（截止9.22）,【9体117】,渠道_公众号_文章导流(文末),【9进117】,10.28进群,用户_探索期 | M2: - | N2: 45868.825 | O2: - | P2: 通过渠道码 公众号-文章导流(文末)_周三 添加 | Q2: 扫描二维码 | R2: o917H0u7ixbta_T0uGk4GCU_mTRQ | S2: wmElzPCwAAVw2dDlKc7LCpRzMaL8TNTw | T2: - | W2: B0523_EC0C489D61DF8B3E32FF85487DA7DECC5194F219CF554649F1C4F9C615435A82_D2064 | AF2: 男 | AG2: - | AW2: 全量数据（截止9.22）,10.28进群 | CF2: 用户_探索期 | CL2: 【9进142】,【9进117】 | CP2: 问卷_已填 | CR2: 会员_7 | CT2: 【9体142】,【9体117】 | CV2: 渠道_公众号_文章导流(文末)
A3: 二往 | B3: 问 【9体120】 二往 | C3: B0523_A716330567DC133D8DD488DF3AE2B9315194F219CF554649F1C4F9C615435A82_D2064 | D3: 未流失 | F3: 个人微信 | G3: 鱼丸115 | H3: 生财有术 | I3: 0 | J3: 0 | K3: - | L3: 全量数据（截止9.22）,体验卡,问卷_已填,【9体142】,【9体120】,【9进142】,用户_新手期,渠道_用户分销_🌊达师姐 | M3: - | N3: 45889.686 | O3: - | P3: 其他渠道 | Q3: 扫描二维码 | R3: o917H0k79X6_5BZMZDOlfjD7pzNc | S3: wmElzPCwAA0th-3Ccl6zSumTFlOBa3WA | T3: - | W3: B0523_A716330567DC133D8DD488DF3AE2B9315194F219CF554649F1C4F9C615435A82_D2064 | AF3: 女 | AG3: - | AW3: 全量数据（截止9.22） | CE3: 渠道_用户分销_🌊达师姐 | CF3: 用户_新手期 | CL3: 【9进142】 | CP3: 问卷_已填 | CR3: 体验卡 | CT3: 【9体142】,【9体120】
A4: 晴朗 | B4: 延期【9体123】 晴朗 | C4: B0523_6E4308D8EF515D5867E423E6143E5A8B5194F219CF554649F1C4F9C615435A82_D2064 | D4: 未流失 | F4: 个人微信 | G4: 鱼丸115 | H4: 生财有术 | I4: 0 | J4: 0 | K4: - | L4: 全量数据（截止9.22）,【9进142】,【9体123】,体验营_直播,【9体142】,渠道_公众号_关注后+关键词 | M4: - | N4: 45915.677 | O4: - | P4: 通过渠道码 公众号-关注后参与+关键词回复 添加 | Q4: 扫描二维码 | R4: o917H0ms-PlSL-Pr9A4rAGlOJzlI | S4: wmElzPCwAAhod7KFnbBbG8x1qsAgJurg | T4: - | W4: B0523_6E4308D8EF515D5867E423E6143E5A8B5194F219CF554649F1C4F9C615435A82_D2064 | AF4: 女 | AG4: - | AW4: 全量数据（截止9.22） | CL4: 【9进142】 | CT4: 【9体123】,【9体142】 | CU4: 体验营_直播 | CV4: 渠道_公众号_关注后+关键词
A5: Dunye | B5: 【9体129】 Dunye | C5: B0523_D35D5B5111FDA300F949C7024F1FCFEA5194F219CF554649F1C4F9C615435A82_D2064 | D5: 未流失 | F5: 个人微信 | G5: 鱼丸115 | H5: 生财有术 | I5: 0 | J5: 0 | K5: - | L5: 渠道_公众号_文章导流(文末),【9体129】,【9体142】,129期常规群触达 | M5: - | N5: 45970.874 | O5: - | P5: 通过渠道码 公众号-文章导流(文末)_周一 添加 | Q5: 扫描二维码 | R5: o917H0ugr3ceDcrKDeAYouZEA-vs | S5: wmElzPCwAAxoGdwUKQGNsA54ZmUxjR8Q | T5: - | W5: B0523_D35D5B5111FDA300F949C7024F1FCFEA5194F219CF554649F1C4F9C615435A82_D2064 | AF5: 男 | AG5: - | BK5: 129期常规群触达 | CT5: 【9体129】,【9体142】 | CV5: 渠道_公众号_文章导流(文末)
A6: 👿LYLA | B6: 延期【9体135】 ?LYLA | C6: B0523_167E0D008799A4385097F77DD38990C85194F219CF554649F1C4F9C615435A82_D2064 | D6: 未流失 | F6: 个人微信 | G6: 鱼丸115 | H6: 生财有术 | I6: 0 | J6: 0 | K6: - | L6: 渠道_用户分销_李子慕,【9体142】,体验卡,【9体135】,【9进135】,135期常规群触达 | M6: - | N6: 46021.846 | O6: - | P6: 其他渠道 | Q6: 扫描二维码 | R6: o917H0uakQdZ_t7WJ2dtmYi1FaRY | S6: wmElzPCwAA2rQH-YrDlE8WTzKyP3aJNQ | T6: - | W6: B0523_167E0D008799A4385097F77DD38990C85194F219CF554649F1C4F9C615435A82_D2064 | AF6: 未知 | AG6: - | BK6: 135期常规群触达 | CE6: 渠道_用户分销_李子慕 | CL6: 【9进135】 | CR6: 体验卡 | CT6: 【9体142】,【9体135】
A7: 香叠小叠 | B7: 延期【9体141】 香叠小叠 | C7: B0523_67686947D4936EB85B6BC7DFBF9E956F5194F219CF554649F1C4F9C615435A82_D2064 | D7: 未流失 | F7: 个人微信 | G7: 鱼丸115 | H7: 生财有术 | I7: 0 | J7: 0 | K7: - | L7: 渠道_公众号_关注后+关键词,体验营_直播,【9体142】,体验卡 | M7: - | N7: 46063.537 | O7: - | P7: 通过渠道码 公众号-关注后参与+关键词回复 添加 | Q7: 扫描二维码 | R7: o917H0owZB6WAaKyZz7HkAKI5n3k | S7: wmElzPCwAAe1G-vID-TcCXDqAIRb9nYw | T7: - | W7: B0523_67686947D4936EB85B6BC7DFBF9E956F5194F219CF554649F1C4F9C615435A82_D2064 | AF7: 未知 | AG7: - | CR7: 体验卡 | CT7: 【9体142】 | CU7: 体验营_直播 | CV7: 渠道_公众号_关注后+关键词
A8: 热气腾腾 | B8: 延期 问 【9体141】 热气腾腾 | C8: B0523_639B4019C14D3538F9EF6EE9945E69445194F219CF554649F1C4F9C615435A82_D2064 | D8: 未流失 | F8: 个人微信 | G8: 鱼丸115 | H8: 生财有术 | I8: 0 | J8: 0 | K8: - | L8: 【9体141】,问卷_已填,用户_新手期,【9进141】,体验卡,渠道_公众号_文章导流(文末),【9体142】 | M8: - | N8: 46063.699 | O8: - | P8: 通过渠道码 公众号-文末导流—纯文字测试 添加 | Q8: 扫描二维码 | R8: o917H0k5c9qsXI1pc4krVG3C59yo | S8: wmElzPCwAAmbXhcYim-xsF389WrBLV_A | T8: - | W8: B0523_639B4019C14D3538F9EF6EE9945E69445194F219CF554649F1C4F9C615435A82_D2064 | AF8: 未知 | AG8: - | CF8: 用户_新手期 | CL8: 【9进141】 | CP8: 问卷_已填 | CR8: 体验卡 | CT8: 【9体141】,【9体142】 | CV8: 渠道_公众号_文章导流(文末)
A9: 燕子 | B9: 延期【9体141】 燕子 | C9: B0523_C3D26F91F06DE1317E617483DEE3CE185194F219CF554649F1C4F9C615435A82_D2064 | D9: 未流失 | F9: 个人微信 | G9: 鱼丸115 | H9: 生财有术 | I9: 0 | J9: 0 | K9: - | L9: 渠道_公众号_文章导流(文末),体验卡,【9体142】 | M9: - | N9: 46063.864 | O9: - | P9: 通过渠道码 公众号-文末导流—纯文字测试 添加 | Q9: 扫描二维码 | R9: o917H0mxkY8acS8qitsV3bs0t0DQ | S9: wmElzPCwAAdXpIm4F6vt4NhDrADR66EQ | T9: - | W9: B0523_C3D26F91F06DE1317E617483DEE3CE185194F219CF554649F1C4F9C615435A82_D2064 | AF9: 未知 | AG9: - | CR9: 体验卡 | CT9: 【9体142】 | CV9: 渠道_公众号_文章导流(文末)
A10: TNT瑶🐹 | B10: 延期【9体141】 TNT瑶? | C10: B0523_FD85C1361B6596936EDC35B027FB777F5194F219CF554649F1C4F9C615435A82_D2064 | D10: 未流失 | F10: 个人微信 | G10: 鱼丸115 | H10: 生财有术 | I10: 0 | J10: 0 | K10: - | L10: 体验卡,【9进142】,公众号_种草文,【9体142】 | M10: - | N10: 46065.444 | O10: - | P10: 通过渠道码 公众号_种草文 添加 | Q10: 扫描二维码 | R10: o917H0nLWOlStwV-0ekkZY0pGXs4 | S10: wmElzPCwAA4zK87QzrjBkWi4TvWvWQag | T10: - | W10: B0523_FD85C1361B6596936EDC35B027FB777F5194F219CF554649F1C4F9C615435A82_D2064 | AF10: 未知 | AG10: - | CJ10: 公众号_种草文 | CL10: 【9进142】 | CR10: 体验卡 | CT10: 【9体142】
A11: TaO·i | B11: 延期【9体141】 TaO·i | C11: B0523_A35619195CEBC4C8D52FE77173623E9D5194F219CF554649F1C4F9C615435A82_D2064 | D11: 未流失 | F11: 个人微信 | G11: 鱼丸115 | H11: 生财有术 | I11: 0 | J11: 0 | K11: - | L11: 渠道_公众号_文章导流(文末),体验卡,【9体142】 | M11: - | N11: 46065.756 | O11: - | P11: 通过渠道码 公众号-文末导流—纯文字测试 添加 | Q11: 扫描二维码 | R11: o917H0vItGbXgYnuKqD2gOvaBGCA | S11: wmElzPCwAAjrlm8Sr4VmVBIB7kXayEpw | T11: - | W11: B0523_A35619195CEBC4C8D52FE77173623E9D5194F219CF554649F1C4F9C615435A82_D2064 | AF11: 未知 | AG11: - | CR11: 体验卡 | CT11: 【9体142】 | CV11: 渠道_公众号_文章导流(文末)
A12: 高海博 | B12: 延期【9体141】 高海博 | C12: B0523_5DB0FA81C89F05F9540B39B13449F8DB5194F219CF554649F1C4F9C615435A82_D2064 | D12: 未流失 | F12: 个人微信 | G12: 鱼丸115 | H12: 生财有术 | I12: 0 | J12: 0 | K12: - | L12: 【9进142】,体验卡,【9体142】,渠道_用户分销_寒宇枫 | M12: - | N12: 46070 | O12: - | P12: 其他渠道 | Q12: 扫描二维码 | R12: o917H0gVHJXrG7M5NqrohQPl-y2k | S12: wmElzPCwAABmj3l7I4oHefFtIU3TD3jg | T12: - | W12: B0523_5DB0FA81C89F05F9540B39B13449F8DB5194F219CF554649F1C4F9C615435A82_D2064 | AF12: 未知 | AG12: - | CE12: 渠道_用户分销_寒宇枫 | CL12: 【9进142】 | CR12: 体验卡 | CT12: 【9体142】
A13: 不羁似风 | B13: 延期【9体141】 不羁似风 | C13: B0523_1C4D34D48DF584F3583727C798149B595194F219CF554649F1C4F9C615435A82_D2064 | D13: 未流失 | F13: 个人微信 | G13: 鱼丸115 | H13: 生财有术 | I13: 0 | J13: 0 | K13: - | L13: 【9体142】,渠道_公众号_菜单免费体验 | M13: - | N13: 46070.932 | O13: - | P13: 通过渠道码 公众号-菜单栏联系我们/免费体验营 添加 | Q13: 扫描二维码 | R13: o917H0vzr_2EDUm5UUjkyBLiffbQ | S13: wmElzPCwAAICRodCirKcFwhQYgNgR4Yg | T13: - | W13: B0523_1C4D34D48DF584F3583727C798149B595194F219CF554649F1C4F9C615435A82_D2064 | AF13: 未知 | AG13: - | CT13: 【9体142】 | CV13: 渠道_公众号_菜单免费体验
A14: 🍓 Sunshine | B14: 延期【9体141】 ? Sunshine | C14: B0523_6642DE7E5E05F3373406A21955F5481D5194F219CF554649F1C4F9C615435A82_D2064 | D14: 未流失 | F14: 个人微信 | G14: 鱼丸115 | H14: 生财有术 | I14: 0 | J14: 0 | K14: - | L14: 渠道_用户分销_李子慕,【9体142】,【9进141】,【9进142】,体验卡 | M14: - | N14: 46071.096 | O14: - | P14: 其他渠道 | Q14: 扫描二维码 | R14: o917H0q34bm9GgQBP2VALIs1llSo | S14: wmElzPCwAAT7UtYDwHXI9Ey8ziRXgtGg | T14: - | W14: B0523_6642DE7E5E05F3373406A21955F5481D5194F219CF554649F1C4F9C615435A82_D2064 | AF14: 未知 | AG14: - | CE14: 渠道_用户分销_李子慕 | CL14: 【9进141】,【9进142】 | CR14: 体验卡 | CT14: 【9体142】
A15: 老麦-纯钧 | B15: 延期【9体141】 老麦-纯钧 | C15: B0523_3AF3830CD16ADE8B2A1CB2A02577ECE45194F219CF554649F1C4F9C615435A82_D2064 | D15: 未流失 | F15: 个人微信 | G15: 鱼丸115 | H15: 生财有术 | I15: 0 | J15: 0 | K15: - | L15: 体验卡,【9体141】,【9体142】,渠道_公众号_文章导流(文末),【9进142】 | M15: - | N15: 46074.837 | O15: - | P15: 通过渠道码 公众号-文末导流—纯文字测试 添加 | Q15: 扫描二维码 | R15: o917H0ie9L72ew1IMTfEsqR4YZ1I | S15: wmElzPCwAAZAtpnYe_HB4qX1Za9sHgOg | T15: - | W15: B0523_3AF3830CD16ADE8B2A1CB2A02577ECE45194F219CF554649F1C4F9C615435A82_D2064 | AF15: 未知 | AG15: - | CL15: 【9进142】 | CR15: 体验卡 | CT15: 【9体141】,【9体142】 | CV15: 渠道_公众号_文章导流(文末)
A16: 🧼 | B16: 问 【9体142】 🧼 | D16: 已流失 | E16: 46080.642 | F16: 个人微信 | G16: 鱼丸115 | H16: 生财有术 | I16: 0 | J16: 0 | K16: - | L16: 体验营_直播,【9体142】,渠道_公众号_关注后+关键词,【9体124】,用户_新手期,【9体141】,问卷_已填 | M16: - | N16: 46076.441 | O16: - | P16: 通过渠道码 公众号-关注后参与+关键词回复 添加 | Q16: 扫描二维码 | R16: o917H0tnjGbYfw_aUmRd3jgzVzfs | S16: wmElzPCwAAMoxrjOvlKkHSOUI9_KLZZw | T16: - | W16: B0523_59A969DBA7725239AE8D144EFAF7F6CC5194F219CF554649F1C4F9C615435A82_D2064 | AF16: 未知 | AG16: - | CF16: 用户_新手期 | CP16: 问卷_已填 | CT16: 【9体142】,【9体124】,【9体141】 | CU16: 体验营_直播 | CV16: 渠道_公众号_关注后+关键词
A17: 王老九 | B17: 【9体142】 王老九 | C17: B0523_063AF9E9E4B2F702C69FA4D489A33F385194F219CF554649F1C4F9C615435A82_D2064 | D17: 未流失 | F17: 个人微信 | G17: 鱼丸115 | H17: 生财有术 | I17: 0 | J17: 0 | K17: - | L17: 【9进142】,【9体142】,渠道_公众号_文章导流(文末),体验卡 | M17: - | N17: 46077.739 | O17: - | P17: 通过渠道码 公众号-文末导流—纯文字测试 添加 | Q17: 扫描二维码 | R17: o917H0gMBCZlppm5PsbxI1QJyJMU | S17: wmElzPCwAAF1qxeuVldsz9o07NopvdQA | T17: - | W17: B0523_063AF9E9E4B2F702C69FA4D489A33F385194F219CF554649F1C4F9C615435A82_D2064 | AF17: 未知 | AG17: - | CL17: 【9进142】 | CR17: 体验卡 | CT17: 【9体142】 | CV17: 渠道_公众号_文章导流(文末)
A18: 莲藕 | B18: 问 【9体142】 莲藕 | C18: B0523_3C809662005E10F71FAD9C37BBE6933B5194F219CF554649F1C4F9C615435A82_D2064 | D18: 未流失 | F18: 个人微信 | G18: 鱼丸115 | H18: 生财有术 | I18: 0 | J18: 0 | K18: - | L18: 问卷_已填,【9体142】,用户_新手期,渠道_公众号_文章导流(文末) | M18: - | N18: 46077.757 | O18: - | P18: 通过渠道码 公众号-文末导流—纯文字测试 添加 | Q18: 扫描二维码 | R18: o917H0sDUpc1rRuWCVYi9pOJks5s | S18: wmElzPCwAAxVUyCUVUhwF0HSf_8HIJAg | T18: - | W18: B0523_3C809662005E10F71FAD9C37BBE6933B5194F219CF554649F1C4F9C615435A82_D2064 | AF18: 未知 | AG18: - | CF18: 用户_新手期 | CP18: 问卷_已填 | CT18: 【9体142】 | CV18: 渠道_公众号_文章导流(文末)
A19: 安静 | B19: 【9体142】 安静 | C19: B0523_2D184EDE55D56FC2533AD1164EE9DA355194F219CF554649F1C4F9C615435A82_D2064 | D19: 未流失 | F19: 个人微信 | G19: 鱼丸115 | H19: 生财有术 | I19: 0 | J19: 0 | K19: - | L19: 【9进142】,【9体142】 | M19: - | N19: 46077.792 | O19: - | P19: - | Q19: 名片分享 | R19: o917H0oT9MgvUfkJWsc2_h95qiU0 | S19: wmElzPCwAAMXoH63eU8RRjFwhuKyLpPA | T19: - | W19: B0523_2D184EDE55D56FC2533AD1164EE9DA355194F219CF554649F1C4F9C615435A82_D2064 | AF19: 未知 | AG19: - | CL19: 【9进142】 | CT19: 【9体142】
A20: Cedric.Sih | B20: 【9体142】 Cedric.Sih | C20: B0523_F1B300C07CDAB943857B96997D2B648E5194F219CF554649F1C4F9C615435A82_D2064 | D20: 未流失 | F20: 个人微信 | G20: 鱼丸115 | H20: 生财有术 | I20: 0 | J20: 0 | K20: - | L20: 【9进142】,渠道_公众号_菜单免费体验,【9体142】 | M20: - | N20: 46077.793 | O20: - | P20: 通过渠道码 公众号-菜单栏联系我们/免费体验营 添加 | Q20: 扫描二维码 | R20: o917H0iS70o9ORvDnNOzrrsFJT88 | S20: wmElzPCwAA7Lr6i7ZxVl8CSJ9f2w4fZw | T20: - | W20: B0523_F1B300C07CDAB943857B96997D2B648E5194F219CF554649F1C4F9C615435A82_D2064 | AF20: 未知 | AG20: - | CL20: 【9进142】 | CT20: 【9体142】 | CV20: 渠道_公众号_菜单免费体验
A21: 杨芷 | B21: 问 【9体142】 杨芷 | C21: B0523_9ACB15F6F8EDBB7B01E4FCB309DE1E6D5194F219CF554649F1C4F9C615435A82_D2064 | D21: 未流失 | F21: 个人微信 | G21: 鱼丸115 | H21: 生财有术 | I21: 0 | J21: 0 | K21: - | L21: 【9进142】,渠道_公众号_文章导流(文末),体验卡,【9体142】,问卷_已填,用户_新手期 | M21: - | N21: 46077.81 | O21: - | P21: 通过渠道码 公众号-文末导流—纯文字测试 添加 | Q21: 扫描二维码 | R21: o917H0kQUmJqGhvfdZ4GJ4PNLZmY | S21: wmElzPCwAAs0fCyxJAvKNZo3YJw6evhA | T21: - | W21: B0523_9ACB15F6F8EDBB7B01E4FCB309DE1E6D5194F219CF554649F1C4F9C615435A82_D2064 | AF21: 未知 | AG21: - | CF21: 用户_新手期 | CL21: 【9进142】 | CP21: 问卷_已填 | CR21: 体验卡 | CT21: 【9体142】 | CV21: 渠道_公众号_文章导流(文末)
A22: v | B22: 【9体142】 v | C22: B0523_30C6B9864F066F60C67018765F70C3365194F219CF554649F1C4F9C615435A82_D2064 | D22: 未流失 | F22: 个人微信 | G22: 鱼丸115 | H22: 生财有术 | I22: 0 | J22: 0 | K22: - | L22: 【9体142】,渠道_用户分销_远鹏 | M22: - | N22: 46077.82 | O22: - | P22: 其他渠道 | Q22: 扫描二维码 | R22: o917H0iDGX2mM1YMilW-8Twao-EY | S22: wmElzPCwAAzVuOjX57-pi9nrw4shbJCQ | T22: - | W22: B0523_30C6B9864F066F60C67018765F70C3365194F219CF554649F1C4F9C615435A82_D2064 | AF22: 未知 | AG22: - | CE22: 渠道_用户分销_远鹏 | CT22: 【9体142】
A23: 喵哆哩 | B23: 【9体142】 喵哆哩 | C23: B0523_4779F29A2C5D3591D4D352BBDDFBE1E65194F219CF554649F1C4F9C615435A82_D2064 | D23: 未流失 | F23: 个人微信 | G23: 鱼丸115 | H23: 生财有术 | I23: 0 | J23: 0 | K23: - | L23: 渠道_用户分销_啊吹(不二),体验卡,【9体142】 | M23: - | N23: 46077.827 | O23: - | P23: 其他渠道 | Q23: 扫描二维码 | R23: o917H0gk5z3MpuUetP61jASSUAow | S23: wmElzPCwAA6UImEPq5B6qC4gFotfL0OQ | T23: - | W23: B0523_4779F29A2C5D3591D4D352BBDDFBE1E65194F219CF554649F1C4F9C615435A82_D2064 | AF23: 未知 | AG23: - | CE23: 渠道_用户分销_啊吹(不二) | CR23: 体验卡 | CT23: 【9体142】
A24: 不堪 | B24: 问 【9体142】 不堪 | C24: B0523_9F211B89783B48C3322C32FEC59086055194F219CF554649F1C4F9C615435A82_D2064 | D24: 未流失 | F24: 个人微信 | G24: 鱼丸115 | H24: 生财有术 | I24: 0 | J24: 0 | K24: - | L24: 渠道_公众号_文章导流(文末),【9体142】,【9进142】,体验卡,用户_新手期,问卷_已填 | M24: - | N24: 46077.83 | O24: - | P24: 通过渠道码 公众号-文末导流—纯文字测试 添加 | Q24: 扫描二维码 | R24: o917H0nJ28kDBJcwBiytKAeCHeOc | S24: wmElzPCwAAbrawWan_J5xAvWlkIb9sRg | T24: - | W24: B0523_9F211B89783B48C3322C32FEC59086055194F219CF554649F1C4F9C615435A82_D2064 | AF24: 未知 | AG24: - | CF24: 用户_新手期 | CL24: 【9进142】 | CP24: 问卷_已填 | CR24: 体验卡 | CT24: 【9体142】 | CV24: 渠道_公众号_文章导流(文末)
A25: 淡安 | B25: 问 【9体142】 淡安 | C25: B0523_8DBDC5A571F4B77264099BED03C3658E5194F219CF554649F1C4F9C615435A82_D2064 | D25: 未流失 | F25: 个人微信 | G25: 鱼丸115 | H25: 生财有术 | I25: 0 | J25: 0 | K25: - | L25: 体验卡,问卷_已填,用户_增长期,【9体142】,体验营_直播,渠道_公众号_关注后+关键词 | M25: - | N25: 46077.835 | O25: - | P25: 通过渠道码 公众号-关注后参与+关键词回复 添加 | Q25: 扫描二维码 | R25: o917H0lQCo8KwL56wUj3G6G9bjtY | S25: wmElzPCwAAE_I6X7FgbePrlHh4S3G26w | T25: - | W25: B0523_8DBDC5A571F4B77264099BED03C3658E5194F219CF554649F1C4F9C615435A82_D2064 | AF25: 未知 | AG25: - | CF25: 用户_增长期 | CP25: 问卷_已填 | CR25: 体验卡 | CT25: 【9体142】 | CU25: 体验营_直播 | CV25: 渠道_公众号_关注后+关键词
A26: Y | B26: 【9体142】 Y | C26: B0523_4E1C6DB6108FBA7A56020EDA983123625194F219CF554649F1C4F9C615435A82_D2064 | D26: 未流失 | F26: 个人微信 | G26: 鱼丸115 | H26: 生财有术 | I26: 0 | J26: 0 | K26: - | L26: 【9体142】,渠道_抖音导流_程前 | M26: - | N26: 46077.838 | O26: - | P26: 其他渠道 | Q26: 通过获客链接添加 | R26: o917H0uAHB64LWs_KCdfHqPDvXyI | S26: wmElzPCwAAKEBLlEo-EDyJjqOpdWI7aw | T26: - | W26: B0523_4E1C6DB6108FBA7A56020EDA983123625194F219CF554649F1C4F9C615435A82_D2064 | AF26: 未知 | AG26: - | CT26: 【9体142】 | CV26: 渠道_抖音导流_程前
A27: 晏星 | B27: 【9体142】 晏星 | C27: B0523_57BE65352B6ADEFEB8076280284C58C35194F219CF554649F1C4F9C615435A82_D2064 | D27: 未流失 | F27: 个人微信 | G27: 鱼丸115 | H27: 生财有术 | I27: 0 | J27: 0 | K27: - | L27: 渠道_公众号_文章导流(文末),【9体142】 | M27: - | N27: 46077.848 | O27: - | P27: 通过渠道码 公众号-文末导流—纯文字测试 添加 | Q27: 扫描二维码 | R27: o917H0p3BPxCTIWWPbnsoDfxI14k | S27: wmElzPCwAAi1oxEkwQyz0hM932aDlzhw | T27: - | W27: B0523_57BE65352B6ADEFEB8076280284C58C35194F219CF554649F1C4F9C615435A82_D2064 | AF27: 未知 | AG27: - | CT27: 【9体142】 | CV27: 渠道_公众号_文章导流(文末)
A28: 阿i | B28: 【9体142】 阿i | C28: B0523_1F5C46B980201EB8D3B24E8E4495ADD95194F219CF554649F1C4F9C615435A82_D2064 | D28: 未流失 | F28: 个人微信 | G28: 鱼丸115 | H28: 生财有术 | I28: 0 | J28: 0 | K28: - | L28: 【9体142】,体验卡,渠道_公众号_文章导流(文末) | M28: - | N28: 46077.856 | O28: - | P28: 通过渠道码 公众号-文末导流—纯文字测试 添加 | Q28: 扫描二维码 | R28: o917H0sA0GtSOj3VBWW1fISY7OGc | S28: wmElzPCwAAG1oOMi2SbdzF66c29zv4ig | T28: - | W28: B0523_1F5C46B980201EB8D3B24E8E4495ADD95194F219CF554649F1C4F9C615435A82_D2064 | AF28: 未知 | AG28: - | CR28: 体验卡 | CT28: 【9体142】 | CV28: 渠道_公众号_文章导流(文末)
A29: 王若淇 | B29: 问 【9体142】 王若淇 | C29: B0523_7500DC0E9B50350E58A1BD42C130CCF55194F219CF554649F1C4F9C615435A82_D2064 | D29: 未流失 | F29: 个人微信 | G29: 鱼丸115 | H29: 生财有术 | I29: 0 | J29: 0 | K29: - | L29: 【9体142】,体验营_直播,体验卡,问卷_已填,渠道_公众号_关注后+关键词,用户_增长期,【9进142】 | M29: - | N29: 46077.867 | O29: - | P29: 通过渠道码 公众号-关注后参与+关键词回复 添加 | Q29: 扫描二维码 | R29: o917H0v3MoLgy6rIyDHq7qYBiLws | S29: wmElzPCwAAuF3J8UtuahJ11QPcNSHVBg | T29: - | W29: B0523_7500DC0E9B50350E58A1BD42C130CCF55194F219CF554649F1C4F9C615435A82_D2064 | AF29: 未知 | AG29: - | CF29: 用户_增长期 | CL29: 【9进142】 | CP29: 问卷_已填 | CR29: 体验卡 | CT29: 【9体142】 | CU29: 体验营_直播 | CV29: 渠道_公众号_关注后+关键词
A30: shaa电信phoeni | B30: 【9体142】 shaa电信phoeni | C30: B0523_D9CB121BCCC21778E2948D1D5EA5490C5194F219CF554649F1C4F9C615435A82_D2064 | D30: 未流失 | F30: 个人微信 | G30: 鱼丸115 | H30: 生财有术 | I30: 0 | J30: 0 | K30: - | L30: 【9体142】,渠道_公众号_文章导流(文末) | M30: - | N30: 46077.873 | O30: - | P30: 通过渠道码 公众号-文末导流—纯文字测试 添加 | Q30: 扫描二维码 | R30: o917H0p5SHAjQaCM4uWrkw7dcM1I | S30: wmElzPCwAAt6tiew8HsdW_dg8lTT8-0A | T30: - | W30: B0523_D9CB121BCCC21778E2948D1D5EA5490C5194F219CF554649F1C4F9C615435A82_D2064 | AF30: 未知 | AG30: - | CT30: 【9体142】 | CV30: 渠道_公众号_文章导流(文末)
A31: 婷婷 | B31: 【9体142】 婷婷 | C31: B0523_0D9C5F0EA002BD8C2B079B00EB19746E5194F219CF554649F1C4F9C615435A82_D2064 | D31: 未流失 | F31: 个人微信 | G31: 鱼丸115 | H31: 生财有术 | I31: 0 | J31: 0 | K31: - | L31: 【9体142】,渠道_KOC导流_陈雪,体验营_直播,【9进142】 | M31: - | N31: 46077.891 | O31: - | P31: 通过渠道码 KOC导流-陈雪（学姐号） 添加 | Q31: 扫描二维码 | R31: o917H0pP_nZzqdm0biELORyYoT0Q | S31: wmElzPCwAAeF-tQOfL4Gu7bAmkdSO_7Q | T31: - | W31: B0523_0D9C5F0EA002BD8C2B079B00EB19746E5194F219CF554649F1C4F9C615435A82_D2064 | AF31: 未知 | AG31: - | CL31: 【9进142】 | CT31: 【9体142】 | CU31: 体验营_直播 | CV31: 渠道_KOC导流_陈雪
A32: 茶禅一味 | B32: 问 【9体142】 茶禅一味 | C32: B0523_1C9D287BCABE3264416F46EC8F0259B15194F219CF554649F1C4F9C615435A82_D2064 | D32: 未流失 | F32: 个人微信 | G32: 鱼丸115 | H32: 生财有术 | I32: 0 | J32: 0 | K32: - | L32: 问卷_已填,用户_探索期,渠道_公众号_菜单免费体验,体验卡,【9体142】 | M32: - | N32: 46077.895 | O32: - | P32: 通过渠道码 公众号-菜单栏联系我们/免费体验营 添加 | Q32: 扫描二维码 | R32: o917H0qoPLc4eCt91LroRMfWx2Lo | S32: wmElzPCwAA0kvLF1ChDXkbJNfV9TWfcA | T32: - | W32: B0523_1C9D287BCABE3264416F46EC8F0259B15194F219CF554649F1C4F9C615435A82_D2064 | AF32: 未知 | AG32: - | CF32: 用户_探索期 | CP32: 问卷_已填 | CR32: 体验卡 | CT32: 【9体142】 | CV32: 渠道_公众号_菜单免费体验
A33: 一红 | B33: 问 【9】【9体142】 一红 | C33: B0523_ECB33CD5DE25F2E8B521FB6ED36FC9975194F219CF554649F1C4F9C615435A82_D2064 | D33: 未流失 | F33: 个人微信 | G33: 鱼丸115 | H33: 生财有术 | I33: 0 | J33: 0 | K33: - | L33: 【9体142】,【9进142】,体验卡,用户_新手期,问卷_已填,渠道_公众号_文章导流(文末) | M33: - | N33: 46077.905 | O33: - | P33: 通过渠道码 公众号-文末导流—纯文字测试 添加 | Q33: 扫描二维码 | R33: o917H0qYfbnjvNlKsQXq483OPW3U | S33: wmElzPCwAAnORcUv4VabmpZX7ArPFDXA | T33: - | W33: B0523_ECB33CD5DE25F2E8B521FB6ED36FC9975194F219CF554649F1C4F9C615435A82_D2064 | AF33: 未知 | AG33: - | CF33: 用户_新手期 | CL33: 【9进142】 | CP33: 问卷_已填 | CR33: 体验卡 | CT33: 【9体142】 | CV33: 渠道_公众号_文章导流(文末)
A34: 西西 | B34: 【9体142】 西西 | C34: B0523_EE4850C1DC60ACE9F58F0E6ADD7E0F515194F219CF554649F1C4F9C615435A82_D2064 | D34: 未流失 | F34: 个人微信 | G34: 鱼丸115 | H34: 生财有术 | I34: 0 | J34: 0 | K34: - | L34: 【9体142】,渠道_用户分销_冬冬 | M34: - | N34: 46077.908 | O34: - | P34: 其他渠道 | Q34: 扫描二维码 | R34: o917H0kA9XHwKpLeKSBglDIHQU6o | S34: wmElzPCwAAcmT0hKXDXH2NOTg9SWyqkQ | T34: - | W34: B0523_EE4850C1DC60ACE9F58F0E6ADD7E0F515194F219CF554649F1C4F9C615435A82_D2064 | AF34: 未知 | AG34: - | CE34: 渠道_用户分销_冬冬 | CT34: 【9体142】
A35: 虞苗苗 | B35: 【9体142】 虞苗苗 | D35: 未流失 | F35: 个人微信 | G35: 鱼丸115 | H35: 生财有术 | I35: 0 | J35: 0 | K35: - | L35: 【9体142】,体验营_直播,渠道_公众号_关注后+关键词 | M35: - | N35: 46077.919 | O35: - | P35: 通过渠道码 公众号-关注后参与+关键词回复 添加 | Q35: 扫描二维码 | R35: o917H0pXULu4JHScCgFTQiBTkBsg | S35: wmElzPCwAA8J4sMNOdcjRJuT7RzVAKzA | T35: - | W35: B0523_7FCEDC9C82F8C93509FBD15D1FA37DF65194F219CF554649F1C4F9C615435A82_D2064 | AF35: 未知 | AG35: - | CT35: 【9体142】 | CU35: 体验营_直播 | CV35: 渠道_公众号_关注后+关键词
